Workbook

Sheet swiss_qna
A2: Staatssekretariat für Wirtschaft SECO
A3: Secrétariat d'Etat à l'économie SECO
A4: Segreteria di Stato dell’economia SECO
A5: Secretariat da stadi per l'economia SECO
A6: State Secretariat for Economic Affairs SECO
A8: You may choose the language to label the Swiss GDP and its expenditure components in the dropdown-menu below.
A9: Pages labelled at the end with "_q" contain quarterly data, pages with "_y" contain yearly figures.
A10: Pages labelled at the beginning with "nom" contain figures at current prices, pages with "real" contain values at prices of the preceding year (chained values, reference year 2015), pages with "defl" contain implicit price deflators and those with "gc" contain contributions to real GDP-growth.
A12: Sie können im Dropdown-Menu die Sprache wählen, im welcher Sie das BIP der Schweiz gemäss Verwendungsseite beschriftet haben möchten.
A13: Seiten mit der Endbezeichnung "_q" enthalten Quartalszahlen, diejenigen mit "_y" Jahreszahlen.
A14: Seiten mit der Anfangsbezeichnung "nom" enthalten Werte zu laufenden Preisen, diejenigen mit "real" Werte zu Preisen des Vorjahres (verkettet, Referenzjahr 2015), diejenigen mit "defl" implizite Deflatoren und diejenigen mit "gc" Beiträge zum realen BIP-Wachstum.
A16: Vous pouvez choisir ci-dessous la langue avec laquelle vous souhaitez visualiser le PIB de la Suisse selon l'approche par la dépense.
... A22: Le pagine contrassegnate all'inizio con "nom" contengono dati ai prezzi correnti, pagine con "real" contengono valori ai prezzi dell'anno precedente (serie concatenate, anno di riferimento 2015), pagine con "defl" contengono i deflatori impliciti, pagine con "gc" contengono i contributi alla crescita reale del PIL.

Sheet nom_q
A1: =IF(INDIRECT("beschriftung!"&ADDRESS(beschriftung!$C$1*12+ROW(beschriftung!$A1)-1,COLUMN(beschriftung!A$1)))="","",INDIRECT("beschriftung!"&ADDRESS(beschriftung!$C$1*12+ROW(beschriftung!$A1)-1,COLUMN(beschriftung!A$1)))) -> ESA 2010, Quarterly aggregates of Gross Domestic Product, expenditure approach, seasonally, calendar and sport event adjusted data. Background information on sport event adjustment can be found in the publication “Konjunkturtendenzen” (“Economic Trends”) from autumn 2022 and in the technical note from 5 September 2022 on the website www.seco.admin.ch.
A2: =IF(INDIRECT("beschriftung!"&ADDRESS(beschriftung!$C$1*12+ROW(beschriftung!$A2)-1,COLUMN(beschriftung!A$1)))="","",INDIRECT("beschriftung!"&ADDRESS(beschriftung!$C$1*12+ROW(beschriftung!$A2)-1,COLUMN(beschriftung!A$1)))) -> In Mio. Swiss Francs, at current prices, percentage change to previous quarter
A3: =IF(INDIRECT("beschriftung!"&ADDRESS(beschriftung!$C$1*12+ROW(beschriftung!$A5)-1,COLUMN(beschriftung!A$1)))="","",INDIRECT("beschriftung!"&ADDRESS(beschriftung!$C$1*12+ROW(beschriftung!$A5)-1,COLUMN(beschriftung!A$1))))
C4: =IF(INDIRECT("beschriftung!"&ADDRESS(beschriftung!$C$1*12+ROW(beschriftung!$A5)-1,COLUMN(beschriftung!C$1)))="","",INDIRECT("beschriftung!"&ADDRESS(beschriftung!$C$1*12+ROW(beschriftung!$A5)-1,COLUMN(beschriftung!C$1)))) -> Gross domestic product
E5: =IF(INDIRECT("beschriftung!"&ADDRESS(beschriftung!$C$1*12+ROW(beschriftung!$A6)-1,COLUMN(beschriftung!E$1)))="","",INDIRECT("beschriftung!"&ADDRESS(beschriftung!$C$1*12+ROW(beschriftung!$A6)-1,COLUMN(beschriftung!E$1)))) -> Internal demand | Y5: =IF(INDIRECT("beschriftung!"&ADDRESS(beschriftung!$C$1*12+ROW(beschriftung!$A6)-1,COLUMN(beschriftung!Y$1)))="","",INDIRECT("beschriftung!"&ADDRESS(beschriftung!$C$1*12+ROW(beschriftung!$A6)-1,COLUMN(beschriftung!Y$1)))) -> Trade balance (goods and services) | AU5: =IF(INDIRECT("beschriftung!"&ADDRESS(beschriftung!$C$1*12+ROW(beschriftung!$A6)-1,COLUMN(beschriftung!AU$1)))="","",INDIRECT("beschriftung!"&ADDRESS(beschriftung!$C$1*12+ROW(beschriftung!$A6)-1,COLUMN(beschriftung!AU$1)))) -> Global demand excluding inventories change, stat. discrepancies and valuables
G6: =IF(INDIRECT("beschriftung!"&ADDRESS(beschriftung!$C$1*12+ROW(beschriftung!$A7)-1,COLUMN(beschriftung!G$1)))="","",INDIRECT("beschriftung!"&ADDRESS(beschriftung!$C$1*12+ROW(beschriftung!$A7)-1,COLUMN(beschriftung!G$1)))) -> Final consumption expenditure | M6: =IF(INDIRECT("beschriftung!"&ADDRESS(beschriftung!$C$1*12+ROW(beschriftung!$A7)-1,COLUMN(beschriftung!M$1)))="","",INDIRECT("beschriftung!"&ADDRESS(beschriftung!$C$1*12+ROW(beschriftung!$A7)-1,COLUMN(beschriftung!M$1)))) -> Gross capital formation | AA6: =IF(INDIRECT("beschriftung!"&ADDRESS(beschriftung!$C$1*12+ROW(beschriftung!$A7)-1,COLUMN(beschriftung!AA$1)))="","",INDIRECT("beschriftung!"&ADDRESS(beschriftung!$C$1*12+ROW(beschriftung!$A7)-1,COLUMN(beschriftung!AA$1)))) -> Exports of goods and services | AK6: =IF(INDIRECT("beschriftung!"&ADDRESS(beschriftung!$C$1*12+ROW(beschriftung!$A7)-1,COLUMN(beschriftung!AK$1)))="","",INDIRECT("beschriftung!"&ADDRESS(beschriftung!$C$1*12+ROW(beschriftung!$A7)-1,COLUMN(beschriftung!AK$1)))) -> Imports of goods and services | AW6: =IF(INDIRECT("beschriftung!"&ADDRESS(beschriftung!$C$1*12+ROW(beschriftung!$A7)-1,COLUMN(beschriftung!AW$1)))="","",INDIRECT("beschriftung!"&ADDRESS(beschriftung!$C$1*12+ROW(beschriftung!$A7)-1,COLUMN(beschriftung!AW$1)))) -> Final domestic demand | AY6: =IF(INDIRECT("beschriftung!"&ADDRESS(beschriftung!$C$1*12+ROW(beschriftung!$A7)-1,COLUMN(beschriftung!AY$1)))="","",INDIRECT("beschriftung!"&ADDRESS(beschriftung!$C$1*12+ROW(beschriftung!$A7)-1,COLUMN(beschriftung!AY$1)))) -> Exports of goods and services (excluding valuables) | BC6: =IF(INDIRECT("beschriftung!"&ADDRESS(beschriftung!$C$1*12+ROW(beschriftung!$A7)-1,COLUMN(beschriftung!BC$1)))="","",INDIRECT("beschriftung!"&ADDRESS(beschriftung!$C$1*12+ROW(beschriftung!$A7)-1,COLUMN(beschriftung!BC$1)))) -> Imports of goods and services (excluding valuables)
I7: =IF(INDIRECT("beschriftung!"&ADDRESS(beschriftung!$C$1*12+ROW(beschriftung!$A8)-1,COLUMN(beschriftung!I$1)))="","",INDIRECT("beschriftung!"&ADDRESS(beschriftung!$C$1*12+ROW(beschriftung!$A8)-1,COLUMN(beschriftung!I$1)))) -> Households and NPISH | K7: =IF(INDIRECT("beschriftung!"&ADDRESS(beschriftung!$C$1*12+ROW(beschriftung!$A8)-1,COLUMN(beschriftung!K$1)))="","",INDIRECT("beschriftung!"&ADDRESS(beschriftung!$C$1*12+ROW(beschriftung!$A8)-1,COLUMN(beschriftung!K$1)))) -> General government | O7: =IF(INDIRECT("beschriftung!"&ADDRESS(beschriftung!$C$1*12+ROW(beschriftung!$A8)-1,COLUMN(beschriftung!O$1)))="","",INDIRECT("beschriftung!"&ADDRESS(beschriftung!$C$1*12+ROW(beschriftung!$A8)-1,COLUMN(beschriftung!O$1)))) -> Gross fixed capital formation | U7: =IF(INDIRECT("beschriftung!"&ADDRESS(beschriftung!$C$1*12+ROW(beschriftung!$A8)-1,COLUMN(beschriftung!U$1)))="","",INDIRECT("beschriftung!"&ADDRESS(beschriftung!$C$1*12+ROW(beschriftung!$A8)-1,COLUMN(beschriftung!U$1)))) -> Changes in inventories and statistical discrepancies | W7: =IF(INDIRECT("beschriftung!"&ADDRESS(beschriftung!$C$1*12+ROW(beschriftung!$A8)-1,COLUMN(beschriftung!W$1)))="","",INDIRECT("beschriftung!"&ADDRESS(beschriftung!$C$1*12+ROW(beschriftung!$A8)-1,COLUMN(beschriftung!W$1)))) -> Acquisitions less disposals of valuables | AC7: =IF(INDIRECT("beschriftung!"&ADDRESS(beschriftung!$C$1*12+ROW(beschriftung!$A8)-1,COLUMN(beschriftung!AC$1)))="","",INDIRECT("beschriftung!"&ADDRESS(beschriftung!$C$1*12+ROW(beschriftung!$A8)-1,COLUMN(beschriftung!AC$1)))) -> Exports (exp.) of goods | AI7: =IF(INDIRECT("beschriftung!"&ADDRESS(beschriftung!$C$1*12+ROW(beschriftung!$A8)-1,COLUMN(beschriftung!AI$1)))="","",INDIRECT("beschriftung!"&ADDRESS(beschriftung!$C$1*12+ROW(beschriftung!$A8)-1,COLUMN(beschriftung!AI$1)))) -> Exports of services | AM7: =IF(INDIRECT("beschriftung!"&ADDRESS(beschriftung!$C$1*12+ROW(beschriftung!$A8)-1,COLUMN(beschriftung!AM$1)))="","",INDIRECT("beschriftung!"&ADDRESS(beschriftung!$C$1*12+ROW(beschriftung!$A8)-1,COLUMN(beschriftung!AM$1)))) -> Imports (imp.) of goods | AS7: =IF(INDIRECT("beschriftung!"&ADDRESS(beschriftung!$C$1*12+ROW(beschriftung!$A8)-1,COLUMN(beschriftung!AS$1)))="","",INDIRECT("beschriftung!"&ADDRESS(beschriftung!$C$1*12+ROW(beschriftung!$A8)-1,COLUMN(beschriftung!AS$1)))) -> Imports of services | BA7: =IF(INDIRECT("beschriftung!"&ADDRESS(beschriftung!$C$1*12+ROW(beschriftung!$A8)-1,COLUMN(beschriftung!BA$1)))="","",INDIRECT("beschriftung!"&ADDRESS(beschriftung!$C$1*12+ROW(beschriftung!$A8)-1,COLUMN(beschriftung!BA$1)))) -> thereof exports of goods excluding valuables
Q8: =IF(INDIRECT("beschriftung!"&ADDRESS(beschriftung!$C$1*12+ROW(beschriftung!$A9)-1,COLUMN(beschriftung!Q$1)))="","",INDIRECT("beschriftung!"&ADDRESS(beschriftung!$C$1*12+ROW(beschriftung!$A9)-1,COLUMN(beschriftung!Q$1)))) -> Construction | S8: =IF(INDIRECT("beschriftung!"&ADDRESS(beschriftung!$C$1*12+ROW(beschriftung!$A9)-1,COLUMN(beschriftung!S$1)))="","",INDIRECT("beschriftung!"&ADDRESS(beschriftung!$C$1*12+ROW(beschriftung!$A9)-1,COLUMN(beschriftung!S$1)))) -> Fixed assets and software | AE8: =IF(INDIRECT("beschriftung!"&ADDRESS(beschriftung!$C$1*12+ROW(beschriftung!$A9)-1,COLUMN(beschriftung!AE$1)))="","",INDIRECT("beschriftung!"&ADDRESS(beschriftung!$C$1*12+ROW(beschriftung!$A9)-1,COLUMN(beschriftung!AE$1)))) -> thereof exp. of goods excluding non-monetary gold | AG8: =IF(INDIRECT("beschriftung!"&ADDRESS(beschriftung!$C$1*12+ROW(beschriftung!$A9)-1,COLUMN(beschriftung!AG$1)))="","",INDIRECT("beschriftung!"&ADDRESS(beschriftung!$C$1*12+ROW(beschriftung!$A9)-1,COLUMN(beschriftung!AG$1)))) -> thereof exp. of goods excluding valuables and merchanting | AO8: =IF(INDIRECT("beschriftung!"&ADDRESS(beschriftung!$C$1*12+ROW(beschriftung!$A9)-1,COLUMN(beschriftung!AO$1)))="","",INDIRECT("beschriftung!"&ADDRESS(beschriftung!$C$1*12+ROW(beschriftung!$A9)-1,COLUMN(beschriftung!AO$1)))) -> thereof imp. of goods excluding non-monetary gold | AQ8: =IF(INDIRECT("beschriftung!"&ADDRESS(beschriftung!$C$1*12+ROW(beschriftung!$A9)-1,COLUMN(beschriftung!AQ$1)))="","",INDIRECT("beschriftung!"&ADDRESS(beschriftung!$C$1*12+ROW(beschriftung!$A9)-1,COLUMN(beschriftung!AQ$1)))) -> thereof imp. of goods excluding valuables
C11: B.1*b | E11: P.3+P.5 | G11: P.3 | I11: S.14+S15 | K11: S.13 | M11: P.5 | O11: P.51 | Q11: P.5111c | S11: P.5111be | U11: P.52 | W11: P.53 | AA11: P.6 | AC11: P.61 | AI11: P.62 | AK11: P.7 | AM11: P.71 | AS11: P.72 | AW11: P.3+P.51
A12: 1980 | B12: 1 | C12: 50219.523 | E12: 53790.619 | G12: 34282.617 | I12: 29603.005 | K12: 4679.6116 | M12: 19508.002 | O12: 15383.762 | Q12: 6084.2698 | S12: 9299.4919 | U12: 1710.0567 | W12: 2414.1836 | Y12: -3571.0961 | AA12: 22972.912 | AC12: 17395.752 | AE12: 12310.211 | AG12: 10957.194 | AI12: 5577.1601 | AK12: 26544.008 | AM12: 22487.765 | AO12: 15428.234 | AQ12: 13806.995 | AS12: 4056.243 | AU12: 66372.704 | AW12: 49666.379 | AY12: 16706.325 | BA12: 11129.165 | BC12: 17863.238
A13: 1980 | B13: 2 | C13: 50869.75 | D13: 0.0129477 | E13: 51784.139 | F13: -0.037301683 | G13: 34662.214 | H13: 0.01107259 | I13: 29857.971 | J13: 0.0086128141 | K13: 4804.2438 | L13: 0.026633019 | M13: 17121.924 | N13: -0.12231278 | O13: 15416.203 | P13: 0.0021087834 | Q13: 6406.2668 | R13: 0.052922865 | S13: 9009.9359 | T13: -0.031136752 | U13: 1463.5709 | W13: 242.15043 | Y13: -914.38821 | AA13: 23078.424 | AB13: 0.0045928857 | AC13: 17347.62 | AD13: -0.0027668998 | AE13: 12349.936 | AF13: 0.0032270319 | AG13: 11090.722 | AH13: 0.01218636 | AI13: 5730.8043 | AJ13: 0.027548834 | AK13: 23992.812 | AL13: -0.096111934 | AM13: 19867.366 | AN13: -0.11652553 | AO13: 14842.82 | AP13: -0.037944339 | AQ13: 13544.076 | AR13: -0.0190424 | AS13: 4125.4457 | AT13: 0.01706079 | AU13: 67075.701 | AV13: 0.010591665 | AW13: 50078.417 | AX13: 0.008296123 | AY13: 16997.284 | AZ13: 0.017416103 | BA13: 11266.48 | BB13: 0.012338286 | BC13: 17669.522 | BD13: -0.010844373
A14: 1980 | B14: 3 | C14: 51636.923 | D14: 0.015081111 | E14: 51774.869 | F14: -0.00017900004 | G14: 35146.872 | H14: 0.013982308 | I14: 30245.028 | J14: 0.01296327 | K14: 4901.8446 | L14: 0.020315541 | M14: 16627.997 | N14: -0.028847641 | O14: 15769.262 | P14: 0.022901847 | Q14: 6679.2947 | R14: 0.042618867 | S14: 9089.9676 | T14: 0.0088826032 | U14: 1745.3998 | W14: -886.66509 | Y14: -137.94649 | AA14: 24165.838 | AB14: 0.047118204 | AC14: 18271.626 | AD14: 0.053264188 | AE14: 12391.699 | AF14: 0.003381621 | AG14: 11212.342 | AH14: 0.010965903 | AI14: 5894.2114 | AJ14: 0.028513804 | AK14: 24303.784 | AL14: 0.012961056 | AM14: 20078.533 | AN14: 0.010628832 | AO14: 15229.718 | AP14: 0.026066397 | AQ14: 14090.948 | AR14: 0.040377203 | AS14: 4225.251 | AT14: 0.024192602 | AU14: 68207.722 | AV14: 0.016876762 | AW14: 50916.134 | AX14: 0.01672811 | AY14: 17291.588 | AZ14: 0.01731473 | BA14: 11397.376 | BB14: 0.011618212 | BC14: 18316.199 | BD14: 0.036598454
A15: 1980 | B15: 4 | C15: 52490.256 | D15: 0.016525649 | E15: 52514.094 | F15: 0.014277673 | G15: 35622.311 | H15: 0.013527192 | I15: 30629.542 | J15: 0.012713326 | K15: 4992.7682 | L15: 0.018548857 | M15: 16891.783 | N15: 0.015863976 | O15: 16237.238 | P15: 0.029676448 | Q15: 6954.4241 | R15: 0.041191383 | S15: 9282.8139 | T15: 0.02121529 | U15: 1355.5279 | W15: -700.98274 | Y15: -23.837488 | AA15: 24895.291 | AB15: 0.030185325 | AC15: 18828.656 | AD15: 0.03048606 | AE15: 12864.208 | AF15: 0.038131037 | AG15: 11415.522 | AH15: 0.018121121 | AI15: 6066.6351 | AJ15: 0.029253069 | AK15: 24919.129 | AL15: 0.025318883 | AM15: 20578.796 | AN15: 0.024915311 | AO15: 15284.69 | AP15: 0.0036095202 | AQ15: 14065.294 | AR15: -0.0018206342 | AS15: 4340.3327 | AT15: 0.027236668 | AU15: 69540.355 | AV15: 0.019537859 | AW15: 51859.549 | AX15: 0.018528786 | AY15: 17680.806 | AZ15: 0.022509133 | BA15: 11614.171 | BB15: 0.019021472 | BC15: 18405.626 | BD15: 0.0048824155
A16: 1981 | B16: 1 | C16: 53212.598 | D16: 0.013761438 | E16: 53108.093 | F16: 0.011311232 | G16: 36349.388 | H16: 0.020410717 | I16: 31241.365 | J16: 0.019974921 | K16: 5108.0225 | L16: 0.02308423 | M16: 16758.705 | N16: -0.0078782549 | O16: 16563.294 | P16: 0.020080771 | Q16: 7156.8406 | R16: 0.02910615 | S16: 9406.4536 | T16: 0.01331921 | U16: 949.85754 | W16: -754.44641 | Y16: 104.50479 | AA16: 25501.468 | AB16: 0.02434905 | AC16: 19334.627 | AD16: 0.026872362 | AE16: 13206.496 | AF16: 0.026607834 | AG16: 11782.755 | AH16: 0.032169619 | AI16: 6166.8413 | AJ16: 0.016517594 | AK16: 25396.963 | AL16: 0.019175406 | AM16: 20917.586 | AN16: 0.016463066 | AO16: 15194.691 | AP16: -0.005888217 | AQ16: 14332.264 | AR16: 0.018980772 | AS16: 4479.377 | AT16: 0.032035407 | AU16: 71074.381 | AV16: 0.022059511 | AW16: 52912.682 | AX16: 0.020307411 | AY16: 18161.699 | AZ16: 0.027198594 | BA16: 11994.858 | BB16: 0.03277779 | BC16: 18811.641 | BD16: 0.022059258
A17: 1981 | B17: 2 | C17: 54513.464 | D17: 0.024446581 | E17: 53597.137 | F17: 0.0092084691 | G17: 37242.004 | H17: 0.024556583 | I17: 32003.339 | J17: 0.024389916 | K17: 5238.6649 | L17: 0.025575941 | M17: 16355.133 | N17: -0.024081366 | O17: 16917.478 | P17: 0.021383663 | Q17: 7313.4621 | R17: 0.021884177 | S17: 9604.016 | T17: 0.02100285 | U17: 816.20961 | W17: -1378.5549 | Y17: 916.32665 | AA17: 26091.02 | AB17: 0.023118362 | AC17: 19683.711 | AD17: 0.018054852 | AE17: 13539.864 | AF17: 0.025242738 | AG17: 11968.947 | AH17: 0.015802081 | AI17: 6407.3097 | AJ17: 0.038993764 | AK17: 25174.694 | AL17: -0.0087518215 | AM17: 20562.063 | AN17: -0.016996391 | AO17: 15459.981 | AP17: 0.017459371 | AQ17: 14447.171 | AR17: 0.0080173761 | AS17: 4612.6308 | AT17: 0.029748287 | AU17: 72757.056 | AV17: 0.023674845 | AW17: 54159.482 | AX17: 0.023563361 | AY17: 18597.574 | AZ17: 0.023999644 | BA17: 12190.264 | BB17: 0.016290811 | BC17: 19059.802 | BD17: 0.013191882
A18: 1981 | B18: 3 | C18: 55709.571 | D18: 0.021941502 | E18: 56124.664 | F18: 0.047157869 | G18: 37935.577 | H18: 0.018623394 | I18: 32592.219 | J18: 0.01840058 | K18: 5343.3574 | L18: 0.019984578 | M18: 18189.087 | N18: 0.11213325 | O18: 17503.878 | P18: 0.034662372 | Q18: 7380.9368 | R18: 0.0092260979 | S18: 10122.941 | T18: 0.054032104 | U18: 893.23974 | W18: -208.03068 | Y18: -415.09286 | AA18: 27857.9 | AB18: 0.067719839 | AC18: 21189.369 | AD18: 0.076492608 | AE18: 14043.173 | AF18: 0.037172365 | AG18: 12375.463 | AH18: 0.033964245 | AI18: 6668.531 | AJ18: 0.040769268 | AK18: 28272.993 | AL18: 0.12307197 | AM18: 23556.918 | AN18: 0.14564955 | AO18: 16167.492 | AP18: 0.045764054 | AQ18: 15175.305 | AR18: 0.050399766 | AS18: 4716.0748 | AT18: 0.022426242 | AU18: 74707.711 | AV18: 0.026810529 | AW18: 55439.455 | AX18: 0.023633395 | AY18: 19268.256 | AZ18: 0.036062915 | BA18: 12599.725 | BB18: 0.033589215 | BC18: 19891.38 | BD18: 0.04362994
A19: 1981 | B19: 4 | C19: 56811.774 | D19: 0.019784806 | E19: 56389.12 | F19: 0.0047119357 | G19: 38371.556 | H19: 0.011492612 | I19: 32908.575 | J19: 0.0097064614 | K19: 5462.9812 | L19: 0.022387372 | M19: 18017.564 | N19: -0.009429997 | O19: 17073.502 | P19: -0.024587458 | Q19: 7260.1678 | R19: -0.016362299 | S19: 9813.3344 | T19: -0.030584666 | U19: 1444.2102 | W19: -500.14826 | Y19: 422.65439 | AA19: 26825.154 | AB19: -0.037071919 | AC19: 19960.892 | AD19: -0.057976096 | AE19: 13707.565 | AF19: -0.023898339 | AG19: 12293.153 | AH19: -0.0066510678 | AI19: 6864.2621 | AJ19: 0.029351451 | AK19: 26402.5 | AL19: -0.066158297 | AM19: 21607.198 | AN19: -0.082766361 | AO19: 15455.688 | AP19: -0.04402688 | AQ19: 14659.476 | AR19: -0.033991345 | AS19: 4795.3021 | AT19: 0.016799417 | AU19: 74822.342 | AV19: 0.0015343921 | AW19: 55445.058 | AX19: 0.00010106482 | AY19: 19377.284 | AZ19: 0.005658423 | BA19: 12513.022 | BB19: -0.0068813496 | BC19: 19454.778 | BD19: -0.021949293
A20: 1982 | B20: 1 | C20: 57364.509 | D20: 0.0097292392 | E20: 57046.13 | F20: 0.01165136 | G20: 38738.423 | H20: 0.0095609276 | I20: 33152.341 | J20: 0.0074073971 | K20: 5586.082 | L20: 0.022533628 | M20: 18307.706 | N20: 0.0161033 | O20: 16916.246 | P20: -0.0092105502 | Q20: 7376.3621 | R20: 0.016004354 | S20: 9539.8837 | T20: -0.027865212 | U20: 1098.2697 | W20: 293.19083 | Y20: 318.37982 | AA20: 25481.332 | AB20: -0.050095614 | AC20: 18487.348 | AD20: -0.073821555 | AE20: 13547.19 | AF20: -0.011699706 | AG20: 12128.918 | AH20: -0.01335992 | AI20: 6993.9836 | AJ20: 0.018898101 | AK20: 25162.952 | AL20: -0.046948131 | AM20: 20310.968 | AN20: -0.059990661 | AO20: 14734.362 | AP20: -0.046670549 | AQ20: 13864.659 | AR20: -0.054218669 | AS20: 4851.9842 | AT20: 0.01182033 | AU20: 74982.883 | AV20: 0.002145624 | AW20: 55654.669 | AX20: 0.003780523 | AY20: 19328.214 | AZ20: -0.002532383 | BA20: 12334.23 | BB20: -0.014288493 | BC20: 18716.643 | BD20: -0.037941077
A21: 1982 | B21: 2 | C21: 58177.413 | D21: 0.014170838 | E21: 58282.246 | F21: 0.021668712 | G21: 39628.793 | H21: 0.02298414 | I21: 33938.499 | J21: 0.023713496 | K21: 5690.2934 | L21: 0.018655553 | M21: 18653.453 | N21: 0.018885315 | O21: 17110.006 | P21: 0.011454105 | Q21: 7308.2501 | R21: -0.0092338139 | S21: 9801.7562 | T21: 0.027450273 | U21: 760.10265 | W21: 783.34418 | Y21: -104.83315 | AA21: 25189.021 | AB21: -0.011471551 | AC21: 17973.206 | AD21: -0.027810492 | AE21: 13666.667 | AF21: 0.0088193148 | AG21: 12299 | AH21: 0.014022853 | AI21: 7215.8154 | AJ21: 0.031717526 | AK21: 25293.854 | AL21: 0.0052021949 | AM21: 20398.997 | AN21: 0.0043340736 | AO21: 14909.488 | AP21: 0.01188554 | AQ21: 14137.106 | AR21: 0.019650521 | AS21: 4894.8575 | AT21: 0.008836251 | AU21: 76449.274 | AV21: 0.019556348 | AW21: 56738.799 | AX21: 0.019479584 | AY21: 19710.475 | AZ21: 0.019777384 | BA21: 12494.66 | BB21: 0.013006863 | BC21: 19031.964 | BD21: 0.016847098
A22: 1982 | B22: 3 | C22: 58624.972 | D22: 0.0076930122 | E22: 58481.934 | F22: 0.0034262266 | G22: 40332.709 | H22: 0.017762745 | I22: 34556.138 | J22: 0.01819877 | K22: 5776.5706 | L22: 0.015162173 | M22: 18149.225 | N22: -0.027031347 | O22: 17076.65 | P22: -0.0019495046 | Q22: 7299.5327 | R22: -0.0011928209 | S22: 9777.1176 | T22: -0.0025136927 | U22: 164.85581 | W22: 907.71908 | Y22: 143.03821 | AA22: 26048.375 | AB22: 0.03411622 | AC22: 18613.83 | AD22: 0.035643278 | AE22: 13238.472 | AF22: -0.031331317 | AG22: 12305.838 | AH22: 0.00055596585 | AI22: 7434.5457 | AJ22: 0.030312613 | AK22: 25905.337 | AL22: 0.024175154 | AM22: 20962.082 | AN22: 0.027603566 | AO22: 14696.104 | AP22: -0.014311969 | AQ22: 13941.392 | AR22: -0.013844053 | AS22: 4943.2553 | AT22: 0.0098874701 | AU22: 77344.763 | AV22: 0.01171351 | AW22: 57409.359 | AX22: 0.01181837 | AY22: 19935.404 | AZ22: 0.011411657 | BA22: 12500.859 | BB22: 0.00049612915 | BC22: 18884.647 | BD22: -0.007740509
A23: 1982 | B23: 4 | C23: 59092.797 | D23: 0.007979959 | E23: 58200.918 | F23: -0.0048051846 | G23: 40905.865 | H23: 0.014210713 | I23: 34982.561 | J23: 0.012340014 | K23: 5923.3039 | L23: 0.025401458 | M23: 17295.052 | N23: -0.047063884 | O23: 17265.12 | P23: 0.011036696 | Q23: 7475.6034 | R23: 0.024120827 | S23: 9789.5166 | T23: 0.0012681687 | U23: 79.173015 | W23: -49.240952 | Y23: 891.87957 | AA23: 26862.125 | AB23: 0.031239928 | AC23: 19293.488 | AD23: 0.036513612 | AE23: 13740.442 | AF23: 0.037917453 | AG23: 12410.037 | AH23: 0.0084674863 | AI23: 7568.6369 | AJ23: 0.018036234 | AK23: 25970.245 | AL23: 0.0025055845 | AM23: 20977.541 | AN23: 0.00073746851 | AO23: 15280.778 | AP23: 0.039784297 | AQ23: 14337.727 | AR23: 0.02842871 | AS23: 4992.7044 | AT23: 0.010003355 | AU23: 78344.056 | AV23: 0.012919977 | AW23: 58170.985 | AX23: 0.013266588 | AY23: 20173.07 | AZ23: 0.011921817 | BA23: 12604.434 | BB23: 0.0082854333 | BC23: 19330.432 | BD23: 0.023605679
A24: 1983 | B24: 1 | C24: 59326.143 | D24: 0.003948803 | E24: 60199.172 | F24: 0.034333722 | G24: 41364.674 | H24: 0.011216214 | I24: 35379.236 | J24: 0.011339194 | K24: 5985.4388 | L24: 0.010489902 | M24: 18834.497 | N24: 0.089010728 | O24: 17650.73 | P24: 0.022334617 | Q24: 7531.5368 | R24: 0.007482127 | S24: 10119.193 | T24: 0.033676477 | U24: -351.10316 | W24: 1534.8706 | Y24: -873.02873 | AA24: 25541.164 | AB24: -0.04917559 | AC24: 17953.443 | AD24: -0.069455787 | AE24: 13461.725 | AF24: -0.020284361 | AG24: 12340.14 | AH24: -0.0056323105 | AI24: 7587.7204 | AJ24: 0.0025214 | AK24: 26414.193 | AL24: 0.017094466 | AM24: 21434.127 | AN24: 0.021765486 | AO24: 15345.001 | AP24: 0.0042028424 | AQ24: 14470.786 | AR24: 0.0092802901 | AS24: 4980.0655 | AT24: -0.0025314725 | AU24: 79128.097 | AV24: 0.010007669 | AW24: 59015.404 | AX24: 0.01451615 | AY24: 20112.693 | AZ24: -0.002992971 | BA24: 12524.973 | BB24: -0.0063042084 | BC24: 19450.851 | BD24: 0.0062295233
... A193: 2025 | B193: 2 | C193: 209886.92 | D193: -0.00036957948 | E193: 195992.9 | F193: 0.080737142 | G193: 131449.85 | H193: 0.0027174437 | I193: 106852.53 | J193: 0.0007567326 | K193: 24597.317 | L193: 0.011324861 | M193: 64543.057 | N193: 0.28424664 | O193: 52317.993 | P193: -0.0034175427 | Q193: 17273.551 | R193: 0.0017142808 | S193: 35044.442 | T193: -0.0059277424 | U193: 7010.5428 | W193: 5214.5212 | Y193: 13894.012 | AA193: 156965.37 | AB193: -0.13746326 | AC193: 117693.8 | AD193: -0.17863254 | AE193: 89283.036 | AF193: -0.063410161 | AG193: 71288.57 | AH193: -0.06294164 | AI193: 39271.566 | AJ193: 0.015004978 | AK193: 143071.36 | AL193: -0.067135005 | AM193: 96445.588 | AN193: -0.092099162 | AO193: 60844.979 | AP193: -0.072829663 | AQ193: 58180.262 | AR193: -0.081898791 | AS193: 46625.767 | AT193: -0.010876886 | AU193: 307682.4 | AV193: -0.020020624 | AW193: 183767.84 | AX193: 0.00096315924 | AY193: 123914.56 | AZ193: -0.049568988 | BA193: 84642.996 | BB193: -0.076818796 | BC193: 104806.03 | BD193: -0.051603752

Sheet real_q
A1: =IF(INDIRECT("beschriftung!"&ADDRESS(beschriftung!$C$1*12+ROW(beschriftung!$A1)-1,COLUMN(beschriftung!A$1)))="","",INDIRECT("beschriftung!"&ADDRESS(beschriftung!$C$1*12+ROW(beschriftung!$A1)-1,COLUMN(beschriftung!A$1)))) -> ESA 2010, Quarterly aggregates of Gross Domestic Product, expenditure approach, seasonally, calendar and sport event adjusted data. Background information on sport event adjustment can be found in the publication “Konjunkturtendenzen” (“Economic Trends”) from autumn 2022 and in the technical note from 5 September 2022 on the website www.seco.admin.ch.
A2: =IF(INDIRECT("beschriftung!"&ADDRESS(beschriftung!$C$1*12+ROW(beschriftung!$A3)-1,COLUMN(beschriftung!A$1)))="","",INDIRECT("beschriftung!"&ADDRESS(beschriftung!$C$1*12+ROW(beschriftung!$A3)-1,COLUMN(beschriftung!A$1)))) -> In Mio. Swiss Francs, at prices of the preceding year, chained values ("annual overlap"), reference year 2015, percentage change to previous quarter
A3: =IF(INDIRECT("beschriftung!"&ADDRESS(beschriftung!$C$1*12+ROW(beschriftung!$A5)-1,COLUMN(beschriftung!A$1)))="","",INDIRECT("beschriftung!"&ADDRESS(beschriftung!$C$1*12+ROW(beschriftung!$A5)-1,COLUMN(beschriftung!A$1))))
C4: =IF(INDIRECT("beschriftung!"&ADDRESS(beschriftung!$C$1*12+ROW(beschriftung!$A5)-1,COLUMN(beschriftung!C$1)))="","",INDIRECT("beschriftung!"&ADDRESS(beschriftung!$C$1*12+ROW(beschriftung!$A5)-1,COLUMN(beschriftung!C$1)))) -> Gross domestic product
E5: =IF(INDIRECT("beschriftung!"&ADDRESS(beschriftung!$C$1*12+ROW(beschriftung!$A6)-1,COLUMN(beschriftung!E$1)))="","",INDIRECT("beschriftung!"&ADDRESS(beschriftung!$C$1*12+ROW(beschriftung!$A6)-1,COLUMN(beschriftung!E$1)))) -> Internal demand | Y5: =IF(INDIRECT("beschriftung!"&ADDRESS(beschriftung!$C$1*12+ROW(beschriftung!$A6)-1,COLUMN(beschriftung!Y$1)))="","",INDIRECT("beschriftung!"&ADDRESS(beschriftung!$C$1*12+ROW(beschriftung!$A6)-1,COLUMN(beschriftung!Y$1)))) -> Trade balance (goods and services) | AU5: =IF(INDIRECT("beschriftung!"&ADDRESS(beschriftung!$C$1*12+ROW(beschriftung!$A6)-1,COLUMN(beschriftung!AU$1)))="","",INDIRECT("beschriftung!"&ADDRESS(beschriftung!$C$1*12+ROW(beschriftung!$A6)-1,COLUMN(beschriftung!AU$1)))) -> Global demand excluding inventories change, stat. discrepancies and valuables
G6: =IF(INDIRECT("beschriftung!"&ADDRESS(beschriftung!$C$1*12+ROW(beschriftung!$A7)-1,COLUMN(beschriftung!G$1)))="","",INDIRECT("beschriftung!"&ADDRESS(beschriftung!$C$1*12+ROW(beschriftung!$A7)-1,COLUMN(beschriftung!G$1)))) -> Final consumption expenditure | M6: =IF(INDIRECT("beschriftung!"&ADDRESS(beschriftung!$C$1*12+ROW(beschriftung!$A7)-1,COLUMN(beschriftung!M$1)))="","",INDIRECT("beschriftung!"&ADDRESS(beschriftung!$C$1*12+ROW(beschriftung!$A7)-1,COLUMN(beschriftung!M$1)))) -> Gross capital formation | AA6: =IF(INDIRECT("beschriftung!"&ADDRESS(beschriftung!$C$1*12+ROW(beschriftung!$A7)-1,COLUMN(beschriftung!AA$1)))="","",INDIRECT("beschriftung!"&ADDRESS(beschriftung!$C$1*12+ROW(beschriftung!$A7)-1,COLUMN(beschriftung!AA$1)))) -> Exports of goods and services | AK6: =IF(INDIRECT("beschriftung!"&ADDRESS(beschriftung!$C$1*12+ROW(beschriftung!$A7)-1,COLUMN(beschriftung!AK$1)))="","",INDIRECT("beschriftung!"&ADDRESS(beschriftung!$C$1*12+ROW(beschriftung!$A7)-1,COLUMN(beschriftung!AK$1)))) -> Imports of goods and services | AW6: =IF(INDIRECT("beschriftung!"&ADDRESS(beschriftung!$C$1*12+ROW(beschriftung!$A7)-1,COLUMN(beschriftung!AW$1)))="","",INDIRECT("beschriftung!"&ADDRESS(beschriftung!$C$1*12+ROW(beschriftung!$A7)-1,COLUMN(beschriftung!AW$1)))) -> Final domestic demand | AY6: =IF(INDIRECT("beschriftung!"&ADDRESS(beschriftung!$C$1*12+ROW(beschriftung!$A7)-1,COLUMN(beschriftung!AY$1)))="","",INDIRECT("beschriftung!"&ADDRESS(beschriftung!$C$1*12+ROW(beschriftung!$A7)-1,COLUMN(beschriftung!AY$1)))) -> Exports of goods and services (excluding valuables) | BC6: =IF(INDIRECT("beschriftung!"&ADDRESS(beschriftung!$C$1*12+ROW(beschriftung!$A7)-1,COLUMN(beschriftung!BC$1)))="","",INDIRECT("beschriftung!"&ADDRESS(beschriftung!$C$1*12+ROW(beschriftung!$A7)-1,COLUMN(beschriftung!BC$1)))) -> Imports of goods and services (excluding valuables)
I7: =IF(INDIRECT("beschriftung!"&ADDRESS(beschriftung!$C$1*12+ROW(beschriftung!$A8)-1,COLUMN(beschriftung!I$1)))="","",INDIRECT("beschriftung!"&ADDRESS(beschriftung!$C$1*12+ROW(beschriftung!$A8)-1,COLUMN(beschriftung!I$1)))) -> Households and NPISH | K7: =IF(INDIRECT("beschriftung!"&ADDRESS(beschriftung!$C$1*12+ROW(beschriftung!$A8)-1,COLUMN(beschriftung!K$1)))="","",INDIRECT("beschriftung!"&ADDRESS(beschriftung!$C$1*12+ROW(beschriftung!$A8)-1,COLUMN(beschriftung!K$1)))) -> General government | O7: =IF(INDIRECT("beschriftung!"&ADDRESS(beschriftung!$C$1*12+ROW(beschriftung!$A8)-1,COLUMN(beschriftung!O$1)))="","",INDIRECT("beschriftung!"&ADDRESS(beschriftung!$C$1*12+ROW(beschriftung!$A8)-1,COLUMN(beschriftung!O$1)))) -> Gross fixed capital formation | U7: =IF(INDIRECT("beschriftung!"&ADDRESS(beschriftung!$C$1*12+ROW(beschriftung!$A8)-1,COLUMN(beschriftung!U$1)))="","",INDIRECT("beschriftung!"&ADDRESS(beschriftung!$C$1*12+ROW(beschriftung!$A8)-1,COLUMN(beschriftung!U$1)))) -> Changes in inventories and statistical discrepancies | W7: =IF(INDIRECT("beschriftung!"&ADDRESS(beschriftung!$C$1*12+ROW(beschriftung!$A8)-1,COLUMN(beschriftung!W$1)))="","",INDIRECT("beschriftung!"&ADDRESS(beschriftung!$C$1*12+ROW(beschriftung!$A8)-1,COLUMN(beschriftung!W$1)))) -> Acquisitions less disposals of valuables | AC7: =IF(INDIRECT("beschriftung!"&ADDRESS(beschriftung!$C$1*12+ROW(beschriftung!$A8)-1,COLUMN(beschriftung!AC$1)))="","",INDIRECT("beschriftung!"&ADDRESS(beschriftung!$C$1*12+ROW(beschriftung!$A8)-1,COLUMN(beschriftung!AC$1)))) -> Exports (exp.) of goods | AI7: =IF(INDIRECT("beschriftung!"&ADDRESS(beschriftung!$C$1*12+ROW(beschriftung!$A8)-1,COLUMN(beschriftung!AI$1)))="","",INDIRECT("beschriftung!"&ADDRESS(beschriftung!$C$1*12+ROW(beschriftung!$A8)-1,COLUMN(beschriftung!AI$1)))) -> Exports of services | AM7: =IF(INDIRECT("beschriftung!"&ADDRESS(beschriftung!$C$1*12+ROW(beschriftung!$A8)-1,COLUMN(beschriftung!AM$1)))="","",INDIRECT("beschriftung!"&ADDRESS(beschriftung!$C$1*12+ROW(beschriftung!$A8)-1,COLUMN(beschriftung!AM$1)))) -> Imports (imp.) of goods | AS7: =IF(INDIRECT("beschriftung!"&ADDRESS(beschriftung!$C$1*12+ROW(beschriftung!$A8)-1,COLUMN(beschriftung!AS$1)))="","",INDIRECT("beschriftung!"&ADDRESS(beschriftung!$C$1*12+ROW(beschriftung!$A8)-1,COLUMN(beschriftung!AS$1)))) -> Imports of services | BA7: =IF(INDIRECT("beschriftung!"&ADDRESS(beschriftung!$C$1*12+ROW(beschriftung!$A8)-1,COLUMN(beschriftung!BA$1)))="","",INDIRECT("beschriftung!"&ADDRESS(beschriftung!$C$1*12+ROW(beschriftung!$A8)-1,COLUMN(beschriftung!BA$1)))) -> thereof exports of goods excluding valuables
Q8: =IF(INDIRECT("beschriftung!"&ADDRESS(beschriftung!$C$1*12+ROW(beschriftung!$A9)-1,COLUMN(beschriftung!Q$1)))="","",INDIRECT("beschriftung!"&ADDRESS(beschriftung!$C$1*12+ROW(beschriftung!$A9)-1,COLUMN(beschriftung!Q$1)))) -> Construction | S8: =IF(INDIRECT("beschriftung!"&ADDRESS(beschriftung!$C$1*12+ROW(beschriftung!$A9)-1,COLUMN(beschriftung!S$1)))="","",INDIRECT("beschriftung!"&ADDRESS(beschriftung!$C$1*12+ROW(beschriftung!$A9)-1,COLUMN(beschriftung!S$1)))) -> Fixed assets and software | AE8: =IF(INDIRECT("beschriftung!"&ADDRESS(beschriftung!$C$1*12+ROW(beschriftung!$A9)-1,COLUMN(beschriftung!AE$1)))="","",INDIRECT("beschriftung!"&ADDRESS(beschriftung!$C$1*12+ROW(beschriftung!$A9)-1,COLUMN(beschriftung!AE$1)))) -> thereof exp. of goods excluding non-monetary gold | AG8: =IF(INDIRECT("beschriftung!"&ADDRESS(beschriftung!$C$1*12+ROW(beschriftung!$A9)-1,COLUMN(beschriftung!AG$1)))="","",INDIRECT("beschriftung!"&ADDRESS(beschriftung!$C$1*12+ROW(beschriftung!$A9)-1,COLUMN(beschriftung!AG$1)))) -> thereof exp. of goods excluding valuables and merchanting | AO8: =IF(INDIRECT("beschriftung!"&ADDRESS(beschriftung!$C$1*12+ROW(beschriftung!$A9)-1,COLUMN(beschriftung!AO$1)))="","",INDIRECT("beschriftung!"&ADDRESS(beschriftung!$C$1*12+ROW(beschriftung!$A9)-1,COLUMN(beschriftung!AO$1)))) -> thereof imp. of goods excluding non-monetary gold | AQ8: =IF(INDIRECT("beschriftung!"&ADDRESS(beschriftung!$C$1*12+ROW(beschriftung!$A9)-1,COLUMN(beschriftung!AQ$1)))="","",INDIRECT("beschriftung!"&ADDRESS(beschriftung!$C$1*12+ROW(beschriftung!$A9)-1,COLUMN(beschriftung!AQ$1)))) -> thereof imp. of goods excluding valuables
C11: B.1*b | E11: P.3+P.5 | G11: P.3 | I11: S.14+S15 | K11: S.13 | M11: P.5 | O11: P.51 | Q11: P.5111c | S11: P.5111be | U11: P.52 | W11: P.53 | AA11: P.6 | AC11: P.61 | AI11: P.62 | AK11: P.7 | AM11: P.71 | AS11: P.72 | AW11: P.3+P.51
A12: 1980 | B12: 1 | C12: 90356.053 | E12: 90154.083 | G12: 59792.713 | I12: 50174.554 | K12: 9437.6302 | M12: 30112.351 | O12: 20667.654 | Q12: 10057.306 | S12: 11232.882 | AA12: 26016.149 | AC12: 16877.284 | AE12: 13824.058 | AG12: 13298.866 | AI12: 9480.5561 | AK12: 24856.425 | AM12: 19623.109 | AO12: 13889.035 | AQ12: 13128.325 | AS12: 5186.7571 | AU12: 102215.07 | AW12: 80279.158 | AY12: 23141.32 | BA12: 13756.815 | BC12: 18530.27
A13: 1980 | B13: 2 | C13: 90496.493 | D13: 0.0015542904 | E13: 86135.573 | F13: -0.044573798 | G13: 59975.808 | H13: 0.0030621578 | I13: 50203.003 | J13: 0.00056701017 | K13: 9615.495 | L13: 0.018846346 | M13: 26249.315 | N13: -0.1282874 | O13: 20445.508 | P13: -0.010748459 | Q13: 10330.468 | R13: 0.02716053 | S13: 10833.545 | T13: -0.03555073 | AA13: 26391.787 | AB13: 0.014438669 | AC13: 17061.885 | AD13: 0.010937817 | AE13: 13616.164 | AF13: -0.015038588 | AG13: 13213.958 | AH13: -0.0063845823 | AI13: 9720.9659 | AJ13: 0.025358195 | AK13: 22848.725 | AL13: -0.080771887 | AM13: 17718.929 | AN13: -0.097037623 | AO13: 13313.017 | AP13: -0.041472867 | AQ13: 12835.903 | AR13: -0.022274108 | AS13: 5235.5394 | AT13: 0.009405165 | AU13: 102236.84 | AV13: 0.00021295083 | AW13: 80181.573 | AX13: -0.0012155699 | AY13: 23244.525 | AZ13: 0.0044598124 | BA13: 13674.095 | BB13: -0.006012997 | BC13: 18250.822 | BD13: -0.015080629
A14: 1980 | B14: 3 | C14: 90957.631 | D14: 0.0050956481 | E14: 85487.126 | F14: -0.0075282101 | G14: 60196.213 | H14: 0.0036749075 | I14: 50332.773 | J14: 0.0025849088 | K14: 9715.9688 | L14: 0.010449157 | M14: 25456.371 | N14: -0.030208188 | O14: 20624.729 | P14: 0.0087657853 | Q14: 10541.657 | R14: 0.020443386 | S14: 10838.558 | T14: 0.00046274896 | AA14: 26830.901 | AB14: 0.016638286 | AC14: 17282.75 | AD14: 0.012944917 | AE14: 13623.399 | AF14: 0.00053141565 | AG14: 13298.275 | AH14: 0.0063809297 | AI14: 9991.3878 | AJ14: 0.027818418 | AK14: 22596.294 | AL14: -0.011047926 | AM14: 17438.874 | AN14: -0.01580542 | AO14: 13668.646 | AP14: 0.026712859 | AQ14: 13338.851 | AR14: 0.039182888 | AS14: 5297.65 | AT14: 0.011863265 | AU14: 102999.43 | AV14: 0.0074590181 | AW14: 80601.892 | AX14: 0.0052420897 | AY14: 23569.732 | AZ14: 0.013990665 | BA14: 13769.226 | BB14: 0.0069570444 | BC14: 18849.529 | BD14: 0.032804355
A15: 1980 | B15: 4 | C15: 91483.531 | D15: 0.0057818094 | E15: 85278.969 | F15: -0.002434956 | G15: 60492.778 | H15: 0.0049266278 | I15: 50576.117 | J15: 0.0048346904 | K15: 9769.3473 | L15: 0.0054938936 | M15: 24998.277 | N15: -0.017995257 | O15: 20847.829 | P15: 0.010817093 | Q15: 10716.589 | R15: 0.016594289 | S15: 10909.789 | T15: 0.0065720188 | AA15: 27326.023 | AB15: 0.018453421 | AC15: 17584.271 | AD15: 0.017446396 | AE15: 14006.926 | AF15: 0.028152073 | AG15: 13311.108 | AH15: 0.00096497787 | AI15: 10206.953 | AJ15: 0.021575126 | AK15: 22616.114 | AL15: 0.00087714788 | AM15: 17442.156 | AN15: 0.00018822402 | AO15: 13341.184 | AP15: -0.023957161 | AQ15: 12855.366 | AR15: -0.036246355 | AS15: 5319.6402 | AT15: 0.004150937 | AU15: 103743.5 | AV15: 0.0072240697 | AW15: 81146.033 | AX15: 0.0067509669 | AY15: 23772.836 | AZ15: 0.0086171496 | BA15: 13795.606 | BB15: 0.001915866 | BC15: 18341.961 | BD15: -0.026927353
A16: 1981 | B16: 1 | C16: 91447.508 | D16: -0.00039375678 | E16: 84405.042 | F16: -0.010247855 | G16: 60485.098 | H16: -0.00012695011 | I16: 50526.634 | J16: -0.00097837318 | K16: 9819.2274 | L16: 0.0051057686 | M16: 24204.096 | N16: -0.031769441 | O16: 20874.085 | P16: 0.0012594009 | Q16: 10889.229 | R16: 0.016109651 | S16: 10802.547 | T16: -0.0098299286 | AA16: 28521.498 | AB16: 0.043748558 | AC16: 18569.475 | AD16: 0.056027562 | AE16: 14308.381 | AF16: 0.021521825 | AG16: 13517.67 | AH16: 0.015518061 | AI16: 10273.101 | AJ16: 0.0064806377 | AK16: 23135.562 | AL16: 0.022968032 | AM16: 17888.173 | AN16: 0.025571191 | AO16: 12918.594 | AP16: -0.031675579 | AQ16: 12639.386 | AR16: -0.016800752 | AS16: 5375.3429 | AT16: 0.010471139 | AU16: 104104.52 | AV16: 0.003479901 | AW16: 81170.316 | AX16: 0.00029925764 | AY16: 24077.228 | AZ16: 0.012804191 | BA16: 14018.778 | BB16: 0.016177036 | BC16: 18151.176 | BD16: -0.01040157
A17: 1981 | B17: 2 | C17: 92492.736 | D17: 0.011429814 | E17: 83787.19 | F17: -0.0073200921 | G17: 60946.718 | H17: 0.0076319639 | I17: 50932.746 | J17: 0.0080375865 | K17: 9869.8007 | L17: 0.0051504354 | M17: 23226.786 | N17: -0.040377881 | O17: 20901.836 | P17: 0.001329477 | Q17: 10884.446 | R17: -0.00043922536 | S17: 10831.339 | T17: 0.0026653379 | AA17: 29602.998 | AB17: 0.037918779 | AC17: 19341.916 | AD17: 0.04159732 | AE17: 14958.728 | AF17: 0.045452163 | AG17: 13813.112 | AH17: 0.021855972 | AI17: 10541.875 | AJ17: 0.0261629 | AK17: 23136.71 | AL17: 4.9643218e-05 | AM17: 17798.884 | AN17: -0.0049915414 | AO17: 13248.488 | AP17: 0.025536337 | AQ17: 12693.934 | AR17: 0.0043157012 | AS17: 5505.8242 | AT17: 0.024274036 | AU17: 105169.55 | AV17: 0.010230425 | AW17: 81630.626 | AX17: 0.0056709088 | AY17: 24641.026 | AZ17: 0.023416258 | BA17: 14326.863 | BB17: 0.02197654 | BC17: 18316.937 | BD17: 0.0091322721
A18: 1981 | B18: 3 | C18: 92813.975 | D18: 0.0034731278 | E18: 86717.117 | F18: 0.034968685 | G18: 60890.497 | H18: -0.00092246055 | I18: 50886.005 | J18: -0.00091770404 | K18: 9860.4081 | L18: -0.0009516437 | M18: 25974.308 | N18: 0.11829111 | O18: 21304.253 | P18: 0.019252698 | Q18: 10834.081 | R18: -0.0046272676 | S18: 11234.621 | T18: 0.037232851 | AA18: 32284.474 | AB18: 0.09058125 | AC18: 21525.69 | AD18: 0.11290374 | AE18: 15627.33 | AF18: 0.044696468 | AG18: 14123.326 | AH18: 0.022457881 | AI18: 10733.421 | AJ18: 0.018170058 | AK18: 26847.052 | AL18: 0.16036601 | AM18: 21186.706 | AN18: 0.19033906 | AO18: 13931.576 | AP18: 0.051559684 | AQ18: 13266.319 | AR18: 0.045091236 | AS18: 5618.4283 | AT18: 0.020451817 | AU18: 106149.08 | AV18: 0.0093137514 | AW18: 82065.558 | AX18: 0.005328056 | AY18: 25149.624 | AZ18: 0.02064027 | BA18: 14641.2 | BB18: 0.021940394 | BC18: 19032.319 | BD18: 0.039055751
A19: 1981 | B19: 4 | C19: 92465.756 | D19: -0.0037517981 | E19: 86146.1 | F19: -0.0065848286 | G19: 60908.59 | H19: 0.00029712751 | I19: 50897.885 | J19: 0.0002334499 | K19: 9867.1904 | L19: 0.00068782827 | M19: 25432.527 | N19: -0.020858339 | O19: 20519.227 | P19: -0.036848295 | Q19: 10547.285 | R19: -0.026471688 | S19: 10736.411 | T19: -0.044345935 | AA19: 32215.198 | AB19: -0.0021458182 | AC19: 21387.368 | AD19: -0.0064259167 | AE19: 15200.56 | AF19: -0.027309236 | AG19: 13788.817 | AH19: -0.02368486 | AI19: 10873.279 | AJ19: 0.013030069 | AK19: 26651.061 | AL19: -0.0073002735 | AM19: 20874.46 | AN19: -0.014737831 | AO19: 13805.975 | AP19: -0.0090155397 | AQ19: 13249.476 | AR19: -0.0012695918 | AS19: 5804.9504 | AT19: 0.033198271 | AU19: 104944.74 | AV19: -0.011345694 | AW19: 81132.441 | AX19: -0.011370387 | AY19: 24866.022 | AZ19: -0.011276577 | BA19: 14289.482 | BB19: -0.024022476 | BC19: 19165.968 | BD19: 0.0070222258
A20: 1982 | B20: 1 | C20: 91825.683 | D20: -0.0069222739 | E20: 86711.414 | F20: 0.0065622693 | G20: 60700.815 | H20: -0.0034112598 | I20: 50693.894 | J20: -0.0040078464 | K20: 9869.3969 | L20: 0.00022361763 | M20: 26129.998 | N20: 0.027424348 | O20: 20090.606 | P20: -0.020888759 | Q20: 10552.039 | R20: 0.00045073931 | S20: 10342.416 | T20: -0.03669711 | AA20: 30849.191 | AB20: -0.042402546 | AC20: 20298.946 | AD20: -0.050890891 | AE20: 15042.891 | AF20: -0.010372588 | AG20: 13419.54 | AH20: -0.02678084 | AI20: 10727.805 | AJ20: -0.013379033 | AK20: 26254.345 | AL20: -0.014885585 | AM20: 20432.011 | AN20: -0.021195738 | AO20: 13501.038 | AP20: -0.022087311 | AQ20: 12724.87 | AR20: -0.039594499 | AS20: 5905.8033 | AT20: 0.017373599 | AU20: 103633.94 | AV20: -0.012490421 | AW20: 80415.81 | AX20: -0.0088328542 | AY20: 24300.054 | AZ20: -0.022760688 | BA20: 13891.357 | BB20: -0.027861418 | BC20: 18672.96 | BD20: -0.025723095
A21: 1982 | B21: 2 | C21: 91228.14 | D21: -0.0065073617 | E21: 86819.634 | F21: 0.0012480521 | G21: 60989.128 | H21: 0.0047497438 | I21: 50974.084 | J21: 0.0055271027 | K21: 9869.7582 | L21: 3.6613554e-05 | M21: 25975.837 | N21: -0.0058997537 | O21: 20093.263 | P21: 0.00013221782 | Q21: 10345.998 | R21: -0.019526137 | S21: 10500.451 | T21: 0.015280295 | AA21: 30074.126 | AB21: -0.025124337 | AC21: 19643.666 | AD21: -0.032281475 | AE21: 15164.251 | AF21: 0.0080676316 | AG21: 13369.73 | AH21: -0.0037117623 | AI21: 10692.432 | AJ21: -0.0032972754 | AK21: 26021.407 | AL21: -0.0088723371 | AM21: 20211.095 | AN21: -0.010812236 | AO21: 13376.674 | AP21: -0.009211423 | AQ21: 12626.455 | AR21: -0.0077340624 | AS21: 5906.3639 | AT21: 9.491955e-05 | AU21: 103780.69 | AV21: 0.0014161033 | AW21: 80684.805 | AX21: 0.0033450426 | AY21: 24198.671 | AZ21: -0.0041721228 | BA21: 13826.69 | BB21: -0.0046551968 | BC21: 18565.832 | BD21: -0.00573706
A22: 1982 | B22: 3 | C22: 90746.527 | D22: -0.0052792184 | E22: 85927.521 | F22: -0.010275479 | G22: 61114.887 | H22: 0.0020619905 | I22: 51084.509 | J22: 0.0021662886 | K22: 9883.8341 | L22: 0.0014261591 | M22: 25047.745 | N22: -0.035729047 | O22: 19919.728 | P22: -0.0086364551 | Q22: 10302.583 | R22: -0.0041962921 | S22: 10375.069 | T22: -0.011940602 | AA22: 29297.166 | AB22: -0.025834818 | AC22: 18909.056 | AD22: -0.037396762 | AE22: 14253.656 | AF22: -0.060048824 | AG22: 13101.239 | AH22: -0.020082006 | AI22: 10782.25 | AJ22: 0.0084001722 | AK22: 25111.836 | AL22: -0.034954737 | AM22: 19334.743 | AN22: -0.043359951 | AO22: 12992.736 | AP22: -0.028702042 | AQ22: 12204.214 | AR22: -0.033440964 | AS22: 5926.8881 | AT22: 0.0034749344 | AU22: 103427.45 | AV22: -0.0034037111 | AW22: 80589.421 | AX22: -0.0011821705 | AY22: 23959.39 | AZ22: -0.0098881994 | BA22: 13550.149 | BB22: -0.020000466 | BC22: 18120.822 | BD22: -0.02396929
A23: 1982 | B23: 4 | C23: 90471.18 | D23: -0.003034234 | E23: 83771.855 | F23: -0.025087022 | G23: 61303.596 | H23: 0.0030877697 | I23: 51132.305 | J23: 0.00093562856 | K23: 10044.126 | L23: 0.016217547 | M23: 22906.342 | N23: -0.085492841 | O23: 20026.972 | P23: 0.0053838193 | Q23: 10534.669 | R23: 0.022526985 | S23: 10297.534 | T23: -0.0074732542 | AA23: 30006.321 | AB23: 0.024205579 | AC23: 19457.506 | AD23: 0.02900461 | AE23: 15337.356 | AF23: 0.076029664 | AG23: 13409.857 | AH23: 0.023556394 | AI23: 10896.984 | AJ23: 0.01064097 | AK23: 24536.677 | AL23: -0.022903903 | AM23: 18795.51 | AN23: -0.027889331 | AO23: 13525.459 | AP23: 0.041001541 | AQ23: 12492.08 | AR23: 0.02358743 | AS23: 5919.9313 | AT23: -0.0011737684 | AU23: 104205.35 | AV23: 0.0075211623 | AW23: 80893.954 | AX23: 0.00377882 | AY23: 24403.616 | AZ23: 0.018540792 | BA23: 13862.283 | BB23: 0.023035462 | BC23: 18429.886 | BD23: 0.017055703
A24: 1983 | B24: 1 | C24: 91221.823 | D24: 0.0082970355 | E24: 87337.722 | F24: 0.042566397 | G24: 61944.357 | H24: 0.010452264 | I24: 51698.844 | J24: 0.011079865 | K24: 10110.329 | L24: 0.0065912095 | M24: 25615.536 | N24: 0.11827266 | O24: 20382.505 | P24: 0.017752675 | Q24: 10603.475 | R24: 0.0065313124 | S24: 10569.598 | T24: 0.02642033 | AA24: 28914.789 | AB24: -0.036376736 | AC24: 18314.816 | AD24: -0.058727497 | AE24: 14998.082 | AF24: -0.022120792 | AG24: 13487.608 | AH24: 0.0057980141 | AI24: 11092.258 | AJ24: 0.017920023 | AK24: 25433.176 | AL24: 0.036537097 | AM24: 19621.418 | AN24: 0.043941771 | AO24: 13869.174 | AP24: 0.025412452 | AQ24: 12998.938 | AR24: 0.040574305 | AS24: 5947.6562 | AT24: 0.0046833092 | AU24: 105448.23 | AV24: 0.011927271 | AW24: 81917.001 | AX24: 0.012646763 | AY24: 24643.314 | AZ24: 0.0098222273 | BA24: 13931.116 | BB24: 0.0049654461 | BC24: 19005.986 | BD24: 0.031259007
... A193: 2025 | B193: 2 | C193: 197858.18 | D193: 0.0012452521 | E193: 175032.59 | F193: 0.055625099 | G193: 121406.49 | H193: 0.0039108679 | I193: 99635.589 | J193: 0.0028087115 | K193: 21790.672 | L193: 0.0087642761 | M193: 53555.784 | N193: 0.18580449 | O193: 48224.703 | P193: -0.005879806 | Q193: 14891.408 | R193: -0.0014594226 | S193: 33344.362 | T193: -0.0080366999 | AA193: 134623.41 | AB193: -0.11290088 | AC193: 97258.298 | AD193: -0.15277753 | AE193: 88733.233 | AF193: -0.037208019 | AG193: 77330.646 | AH193: -0.040791035 | AI193: 37187.645 | AJ193: 0.021326974 | AK193: 111022.08 | AL193: -0.064979069 | AM193: 71486.306 | AN193: -0.096867966 | AO193: 57857.675 | AP193: -0.060896901 | AQ193: 56316.129 | AR193: -0.065824144 | AS193: 39741.812 | AT193: 0.0010070091 | AU193: 292423.46 | AV193: -0.01034511 | AW193: 169618.7 | AX193: 0.0011094793 | AY193: 123333.15 | AZ193: -0.026515942 | BA193: 86224.232 | BB193: -0.047135906 | BC193: 95992.543 | BD193: -0.037396523

Sheet defl_q
A1: =IF(INDIRECT("beschriftung!"&ADDRESS(beschriftung!$C$1*12+ROW(beschriftung!$A1)-1,COLUMN(beschriftung!A$1)))="","",INDIRECT("beschriftung!"&ADDRESS(beschriftung!$C$1*12+ROW(beschriftung!$A1)-1,COLUMN(beschriftung!A$1)))) -> ESA 2010, Quarterly aggregates of Gross Domestic Product, expenditure approach, seasonally, calendar and sport event adjusted data. Background information on sport event adjustment can be found in the publication “Konjunkturtendenzen” (“Economic Trends”) from autumn 2022 and in the technical note from 5 September 2022 on the website www.seco.admin.ch.
A2: =IF(INDIRECT("beschriftung!"&ADDRESS(beschriftung!$C$1*12+ROW(beschriftung!$A4)-1,COLUMN(beschriftung!A$1)))="","",INDIRECT("beschriftung!"&ADDRESS(beschriftung!$C$1*12+ROW(beschriftung!$A4)-1,COLUMN(beschriftung!A$1)))) -> Implicit chain price indexes, percentage change to previous quarter
A3: =IF(INDIRECT("beschriftung!"&ADDRESS(beschriftung!$C$1*12+ROW(beschriftung!$A5)-1,COLUMN(beschriftung!A$1)))="","",INDIRECT("beschriftung!"&ADDRESS(beschriftung!$C$1*12+ROW(beschriftung!$A5)-1,COLUMN(beschriftung!A$1))))
C4: =IF(INDIRECT("beschriftung!"&ADDRESS(beschriftung!$C$1*12+ROW(beschriftung!$A5)-1,COLUMN(beschriftung!C$1)))="","",INDIRECT("beschriftung!"&ADDRESS(beschriftung!$C$1*12+ROW(beschriftung!$A5)-1,COLUMN(beschriftung!C$1)))) -> Gross domestic product
E5: =IF(INDIRECT("beschriftung!"&ADDRESS(beschriftung!$C$1*12+ROW(beschriftung!$A6)-1,COLUMN(beschriftung!E$1)))="","",INDIRECT("beschriftung!"&ADDRESS(beschriftung!$C$1*12+ROW(beschriftung!$A6)-1,COLUMN(beschriftung!E$1)))) -> Internal demand | Y5: =IF(INDIRECT("beschriftung!"&ADDRESS(beschriftung!$C$1*12+ROW(beschriftung!$A6)-1,COLUMN(beschriftung!Y$1)))="","",INDIRECT("beschriftung!"&ADDRESS(beschriftung!$C$1*12+ROW(beschriftung!$A6)-1,COLUMN(beschriftung!Y$1)))) -> Trade balance (goods and services) | AU5: =IF(INDIRECT("beschriftung!"&ADDRESS(beschriftung!$C$1*12+ROW(beschriftung!$A6)-1,COLUMN(beschriftung!AU$1)))="","",INDIRECT("beschriftung!"&ADDRESS(beschriftung!$C$1*12+ROW(beschriftung!$A6)-1,COLUMN(beschriftung!AU$1)))) -> Global demand excluding inventories change, stat. discrepancies and valuables
G6: =IF(INDIRECT("beschriftung!"&ADDRESS(beschriftung!$C$1*12+ROW(beschriftung!$A7)-1,COLUMN(beschriftung!G$1)))="","",INDIRECT("beschriftung!"&ADDRESS(beschriftung!$C$1*12+ROW(beschriftung!$A7)-1,COLUMN(beschriftung!G$1)))) -> Final consumption expenditure | M6: =IF(INDIRECT("beschriftung!"&ADDRESS(beschriftung!$C$1*12+ROW(beschriftung!$A7)-1,COLUMN(beschriftung!M$1)))="","",INDIRECT("beschriftung!"&ADDRESS(beschriftung!$C$1*12+ROW(beschriftung!$A7)-1,COLUMN(beschriftung!M$1)))) -> Gross capital formation | AA6: =IF(INDIRECT("beschriftung!"&ADDRESS(beschriftung!$C$1*12+ROW(beschriftung!$A7)-1,COLUMN(beschriftung!AA$1)))="","",INDIRECT("beschriftung!"&ADDRESS(beschriftung!$C$1*12+ROW(beschriftung!$A7)-1,COLUMN(beschriftung!AA$1)))) -> Exports of goods and services | AK6: =IF(INDIRECT("beschriftung!"&ADDRESS(beschriftung!$C$1*12+ROW(beschriftung!$A7)-1,COLUMN(beschriftung!AK$1)))="","",INDIRECT("beschriftung!"&ADDRESS(beschriftung!$C$1*12+ROW(beschriftung!$A7)-1,COLUMN(beschriftung!AK$1)))) -> Imports of goods and services | AW6: =IF(INDIRECT("beschriftung!"&ADDRESS(beschriftung!$C$1*12+ROW(beschriftung!$A7)-1,COLUMN(beschriftung!AW$1)))="","",INDIRECT("beschriftung!"&ADDRESS(beschriftung!$C$1*12+ROW(beschriftung!$A7)-1,COLUMN(beschriftung!AW$1)))) -> Final domestic demand | AY6: =IF(INDIRECT("beschriftung!"&ADDRESS(beschriftung!$C$1*12+ROW(beschriftung!$A7)-1,COLUMN(beschriftung!AY$1)))="","",INDIRECT("beschriftung!"&ADDRESS(beschriftung!$C$1*12+ROW(beschriftung!$A7)-1,COLUMN(beschriftung!AY$1)))) -> Exports of goods and services (excluding valuables) | BC6: =IF(INDIRECT("beschriftung!"&ADDRESS(beschriftung!$C$1*12+ROW(beschriftung!$A7)-1,COLUMN(beschriftung!BC$1)))="","",INDIRECT("beschriftung!"&ADDRESS(beschriftung!$C$1*12+ROW(beschriftung!$A7)-1,COLUMN(beschriftung!BC$1)))) -> Imports of goods and services (excluding valuables)
I7: =IF(INDIRECT("beschriftung!"&ADDRESS(beschriftung!$C$1*12+ROW(beschriftung!$A8)-1,COLUMN(beschriftung!I$1)))="","",INDIRECT("beschriftung!"&ADDRESS(beschriftung!$C$1*12+ROW(beschriftung!$A8)-1,COLUMN(beschriftung!I$1)))) -> Households and NPISH | K7: =IF(INDIRECT("beschriftung!"&ADDRESS(beschriftung!$C$1*12+ROW(beschriftung!$A8)-1,COLUMN(beschriftung!K$1)))="","",INDIRECT("beschriftung!"&ADDRESS(beschriftung!$C$1*12+ROW(beschriftung!$A8)-1,COLUMN(beschriftung!K$1)))) -> General government | O7: =IF(INDIRECT("beschriftung!"&ADDRESS(beschriftung!$C$1*12+ROW(beschriftung!$A8)-1,COLUMN(beschriftung!O$1)))="","",INDIRECT("beschriftung!"&ADDRESS(beschriftung!$C$1*12+ROW(beschriftung!$A8)-1,COLUMN(beschriftung!O$1)))) -> Gross fixed capital formation | U7: =IF(INDIRECT("beschriftung!"&ADDRESS(beschriftung!$C$1*12+ROW(beschriftung!$A8)-1,COLUMN(beschriftung!U$1)))="","",INDIRECT("beschriftung!"&ADDRESS(beschriftung!$C$1*12+ROW(beschriftung!$A8)-1,COLUMN(beschriftung!U$1)))) -> Changes in inventories and statistical discrepancies | W7: =IF(INDIRECT("beschriftung!"&ADDRESS(beschriftung!$C$1*12+ROW(beschriftung!$A8)-1,COLUMN(beschriftung!W$1)))="","",INDIRECT("beschriftung!"&ADDRESS(beschriftung!$C$1*12+ROW(beschriftung!$A8)-1,COLUMN(beschriftung!W$1)))) -> Acquisitions less disposals of valuables | AC7: =IF(INDIRECT("beschriftung!"&ADDRESS(beschriftung!$C$1*12+ROW(beschriftung!$A8)-1,COLUMN(beschriftung!AC$1)))="","",INDIRECT("beschriftung!"&ADDRESS(beschriftung!$C$1*12+ROW(beschriftung!$A8)-1,COLUMN(beschriftung!AC$1)))) -> Exports (exp.) of goods | AI7: =IF(INDIRECT("beschriftung!"&ADDRESS(beschriftung!$C$1*12+ROW(beschriftung!$A8)-1,COLUMN(beschriftung!AI$1)))="","",INDIRECT("beschriftung!"&ADDRESS(beschriftung!$C$1*12+ROW(beschriftung!$A8)-1,COLUMN(beschriftung!AI$1)))) -> Exports of services | AM7: =IF(INDIRECT("beschriftung!"&ADDRESS(beschriftung!$C$1*12+ROW(beschriftung!$A8)-1,COLUMN(beschriftung!AM$1)))="","",INDIRECT("beschriftung!"&ADDRESS(beschriftung!$C$1*12+ROW(beschriftung!$A8)-1,COLUMN(beschriftung!AM$1)))) -> Imports (imp.) of goods | AS7: =IF(INDIRECT("beschriftung!"&ADDRESS(beschriftung!$C$1*12+ROW(beschriftung!$A8)-1,COLUMN(beschriftung!AS$1)))="","",INDIRECT("beschriftung!"&ADDRESS(beschriftung!$C$1*12+ROW(beschriftung!$A8)-1,COLUMN(beschriftung!AS$1)))) -> Imports of services | BA7: =IF(INDIRECT("beschriftung!"&ADDRESS(beschriftung!$C$1*12+ROW(beschriftung!$A8)-1,COLUMN(beschriftung!BA$1)))="","",INDIRECT("beschriftung!"&ADDRESS(beschriftung!$C$1*12+ROW(beschriftung!$A8)-1,COLUMN(beschriftung!BA$1)))) -> thereof exports of goods excluding valuables
Q8: =IF(INDIRECT("beschriftung!"&ADDRESS(beschriftung!$C$1*12+ROW(beschriftung!$A9)-1,COLUMN(beschriftung!Q$1)))="","",INDIRECT("beschriftung!"&ADDRESS(beschriftung!$C$1*12+ROW(beschriftung!$A9)-1,COLUMN(beschriftung!Q$1)))) -> Construction | S8: =IF(INDIRECT("beschriftung!"&ADDRESS(beschriftung!$C$1*12+ROW(beschriftung!$A9)-1,COLUMN(beschriftung!S$1)))="","",INDIRECT("beschriftung!"&ADDRESS(beschriftung!$C$1*12+ROW(beschriftung!$A9)-1,COLUMN(beschriftung!S$1)))) -> Fixed assets and software | AE8: =IF(INDIRECT("beschriftung!"&ADDRESS(beschriftung!$C$1*12+ROW(beschriftung!$A9)-1,COLUMN(beschriftung!AE$1)))="","",INDIRECT("beschriftung!"&ADDRESS(beschriftung!$C$1*12+ROW(beschriftung!$A9)-1,COLUMN(beschriftung!AE$1)))) -> thereof exp. of goods excluding non-monetary gold | AG8: =IF(INDIRECT("beschriftung!"&ADDRESS(beschriftung!$C$1*12+ROW(beschriftung!$A9)-1,COLUMN(beschriftung!AG$1)))="","",INDIRECT("beschriftung!"&ADDRESS(beschriftung!$C$1*12+ROW(beschriftung!$A9)-1,COLUMN(beschriftung!AG$1)))) -> thereof exp. of goods excluding valuables and merchanting | AO8: =IF(INDIRECT("beschriftung!"&ADDRESS(beschriftung!$C$1*12+ROW(beschriftung!$A9)-1,COLUMN(beschriftung!AO$1)))="","",INDIRECT("beschriftung!"&ADDRESS(beschriftung!$C$1*12+ROW(beschriftung!$A9)-1,COLUMN(beschriftung!AO$1)))) -> thereof imp. of goods excluding non-monetary gold | AQ8: =IF(INDIRECT("beschriftung!"&ADDRESS(beschriftung!$C$1*12+ROW(beschriftung!$A9)-1,COLUMN(beschriftung!AQ$1)))="","",INDIRECT("beschriftung!"&ADDRESS(beschriftung!$C$1*12+ROW(beschriftung!$A9)-1,COLUMN(beschriftung!AQ$1)))) -> thereof imp. of goods excluding valuables
C11: B.1*b | E11: P.3+P.5 | G11: P.3 | I11: S.14+S15 | K11: S.13 | M11: P.5 | O11: P.51 | Q11: P.5111c | S11: P.5111be | U11: P.52 | W11: P.53 | AA11: P.6 | AC11: P.61 | AI11: P.62 | AK11: P.7 | AM11: P.71 | AS11: P.72 | AW11: P.3+P.51
A12: 1980 | B12: 1 | C12: 55.579589 | E12: 59.665206 | G12: 57.335778 | I12: 59.000038 | K12: 49.584605 | M12: 64.784056 | O12: 74.434002 | Q12: 60.496021 | S12: 82.788122 | AA12: 88.302508 | AC12: 103.07198 | AE12: 89.049185 | AG12: 82.391942 | AI12: 58.827351 | AK12: 106.78932 | AM12: 114.59838 | AO12: 111.08211 | AQ12: 105.16951 | AS12: 78.203835 | AU12: 64.934359 | AW12: 61.86709 | AY12: 72.192621 | BA12: 80.899286 | BC12: 96.400308
A13: 1980 | B13: 2 | C13: 56.211847 | D13: 0.011375728 | E13: 60.119341 | F13: 0.0076113831 | G13: 57.79366 | H13: 0.007985978 | I13: 59.474471 | J13: 0.0080412445 | K13: 49.963562 | L13: 0.0076426375 | M13: 65.228078 | N13: 0.006853892 | O13: 75.401416 | P13: 0.01299694 | Q13: 62.013329 | R13: 0.025081119 | S13: 83.167017 | T13: 0.0045766831 | AA13: 87.445475 | AB13: -0.0097056466 | AC13: 101.67469 | AD13: -0.013556439 | AE13: 90.700558 | AF13: 0.018544503 | AG13: 83.93187 | AH13: 0.018690272 | AI13: 58.953034 | AJ13: 0.0021364628 | AK13: 105.00723 | AL13: -0.016687965 | AM13: 112.1251 | AN13: -0.021582188 | AO13: 111.49103 | AP13: 0.0036811973 | AQ13: 105.51713 | AR13: 0.0033053307 | AS13: 78.796956 | AT13: 0.0075842937 | AU13: 65.608151 | AV13: 0.010376505 | AW13: 62.456267 | AX13: 0.0095232691 | AY13: 73.123816 | AZ13: 0.012898765 | BA13: 82.392873 | BB13: 0.018462297 | BC13: 96.814937 | BD13: 0.0043011194
A14: 1980 | B14: 3 | C14: 56.770303 | D14: 0.0099348386 | E14: 60.564522 | F14: 0.0074049561 | G14: 58.387181 | H14: 0.01026966 | I14: 60.090128 | J14: 0.010351603 | K14: 50.451424 | L14: 0.009764354 | M14: 65.319589 | N14: 0.0014029276 | O14: 76.458033 | P14: 0.014013225 | Q14: 63.360955 | R14: 0.021731221 | S14: 83.866948 | T14: 0.0084159598 | AA14: 90.067185 | AB14: 0.029981085 | AC14: 105.72176 | AD14: 0.039804011 | AE14: 90.958936 | AF14: 0.0028486916 | AG14: 84.314255 | AH14: 0.0045559025 | AI14: 58.992919 | AJ14: 0.00067656453 | AK14: 107.55651 | AL14: 0.024277194 | AM14: 115.13664 | AN14: 0.026858766 | AO14: 111.42083 | AP14: -0.00062964305 | AQ14: 105.6384 | AR14: 0.0011492835 | AS14: 79.75708 | AT14: 0.012184786 | AU14: 66.221457 | AV14: 0.0093480169 | AW14: 63.1699 | AX14: 0.011426123 | AY14: 73.363531 | AZ14: 0.0032782004 | BA14: 82.774267 | BB14: 0.0046289638 | BC14: 97.170595 | BD14: 0.0036735892
A15: 1980 | B15: 4 | C15: 57.376728 | D15: 0.010682078 | E15: 61.579185 | F15: 0.016753423 | G15: 58.886882 | H15: 0.0085584005 | I15: 60.561278 | J15: 0.0078407278 | K15: 51.106467 | L15: 0.012983632 | M15: 67.571789 | N15: 0.034479705 | O15: 77.884552 | P15: 0.018657534 | Q15: 64.89401 | R15: 0.024195586 | S15: 85.087016 | T15: 0.014547664 | AA15: 91.104699 | AB15: 0.011519333 | AC15: 107.07669 | AD15: 0.012816069 | AE15: 91.841758 | AF15: 0.0097057273 | AG15: 85.759368 | AH15: 0.017139604 | AI15: 59.436298 | AJ15: 0.0075157894 | AK15: 110.18307 | AL15: 0.024420315 | AM15: 117.9831 | AN15: 0.024722434 | AO15: 114.56772 | AP15: 0.028243311 | AQ15: 109.41185 | AR15: 0.035720457 | AS15: 81.590719 | AT15: 0.0229903 | AU15: 67.031046 | AV15: 0.012225471 | AW15: 63.908914 | AX15: 0.011698841 | AY15: 74.373989 | AZ15: 0.013773297 | BA15: 84.187463 | BB15: 0.017072897 | BC15: 100.3471 | BD15: 0.032690025
A16: 1981 | B16: 1 | C16: 58.189226 | D16: 0.014160771 | E16: 62.920522 | F16: 0.021782309 | G16: 60.096435 | H16: 0.020540274 | I16: 61.831479 | J16: 0.020973814 | K16: 52.020615 | L16: 0.017887134 | M16: 69.23913 | N16: 0.0246751 | O16: 79.348602 | P16: 0.018797696 | Q16: 65.724034 | R16: 0.01279045 | S16: 87.076261 | T16: 0.023378952 | AA16: 89.411392 | AB16: -0.018586381 | AC16: 104.12048 | AD16: -0.02760837 | AE16: 92.299025 | AF16: 0.0049788547 | AG16: 87.165574 | AH16: 0.016397107 | AI16: 60.029016 | AJ16: 0.0099723288 | AK16: 109.77457 | AL16: -0.0037074728 | AM16: 116.93529 | AN16: -0.0088810261 | AO16: 117.61876 | AP16: 0.026630912 | AQ16: 113.39367 | AR16: 0.036392953 | AS16: 83.33193 | AT16: 0.021340805 | AU16: 68.272137 | AV16: 0.018515179 | AW16: 65.187231 | AX16: 0.020002167 | AY16: 75.431023 | AZ16: 0.014212425 | BA16: 85.56279 | BB16: 0.016336478 | BC16: 103.63869 | BD16: 0.03280202
A17: 1981 | B17: 2 | C17: 58.938103 | D17: 0.01286967 | E17: 63.968176 | F17: 0.016650444 | G17: 61.10584 | H17: 0.016796429 | I17: 62.834506 | J17: 0.016221944 | K17: 53.077718 | L17: 0.020320844 | M17: 70.414964 | N17: 0.016982221 | O17: 80.937761 | P17: 0.02002756 | Q17: 67.191862 | R17: 0.022333212 | S17: 88.668778 | T17: 0.018288766 | AA17: 88.136412 | AB17: -0.014259706 | AC17: 101.76712 | AD17: -0.022602274 | AE17: 90.514811 | AF17: -0.019330798 | AG17: 86.64917 | AH17: -0.0059244065 | AI17: 60.779603 | AJ17: 0.01250373 | AK17: 108.80844 | AL17: -0.0088010278 | AM17: 115.52445 | AN17: -0.012065073 | AO17: 116.69242 | AP17: -0.0078758459 | AQ17: 113.81161 | AR17: 0.0036857682 | AS17: 83.777299 | AT17: 0.0053445179 | AU17: 69.180721 | AV17: 0.013308271 | AW17: 66.347014 | AX17: 0.017791558 | AY17: 75.474022 | AZ17: 0.0005700382 | BA17: 85.086764 | BB17: -0.0055634633 | BC17: 104.05562 | BD17: 0.0040228716
A18: 1981 | B18: 3 | C18: 60.022826 | D18: 0.018404453 | E18: 64.721552 | F18: 0.011777346 | G18: 62.301309 | H18: 0.019563901 | I18: 64.049475 | J18: 0.019336029 | K18: 54.190023 | L18: 0.020956165 | M18: 70.027225 | N18: -0.0055064843 | O18: 82.161426 | P18: 0.0151186 | Q18: 68.127023 | R18: 0.013917767 | S18: 90.104878 | T18: 0.016196222 | AA18: 86.288844 | AB18: -0.020962593 | AC18: 98.437582 | AD18: -0.032717234 | AE18: 89.862907 | AF18: -0.0072021897 | AG18: 87.624287 | AH18: 0.011253631 | AI18: 62.128661 | AJ18: 0.022195909 | AK18: 105.31135 | AL18: -0.032139893 | AM18: 111.18726 | AN18: -0.03754351 | AO18: 116.04927 | AP18: -0.0055114607 | AQ18: 114.38972 | AR18: 0.0050794893 | AS18: 83.939396 | AT18: 0.001934854 | AU18: 70.379991 | AV18: 0.017335321 | AW18: 67.555081 | AX18: 0.018208324 | AY18: 76.614491 | AZ18: 0.015110756 | BA18: 86.056645 | BB18: 0.011398729 | BC18: 104.5137 | BD18: 0.0044022559
A19: 1981 | B19: 4 | C19: 61.44088 | D19: 0.023625241 | E19: 65.457542 | F19: 0.011371645 | G19: 62.998595 | H19: 0.011192159 | I19: 64.656075 | J19: 0.0094708005 | K19: 55.365114 | L19: 0.021684628 | M19: 70.844568 | N19: 0.011671796 | O19: 83.207334 | P19: 0.012729913 | Q19: 68.834473 | R19: 0.010384278 | S19: 91.402374 | T19: 0.014399843 | AA19: 83.268631 | AB19: -0.035001207 | AC19: 93.330288 | AD19: -0.051883578 | AE19: 90.178025 | AF19: 0.0035066615 | AG19: 89.15307 | AH19: 0.017447022 | AI19: 63.129644 | AJ19: 0.016111448 | AK19: 99.067348 | AL19: -0.059290863 | AM19: 103.51021 | AN19: -0.06904612 | AO19: 111.94927 | AP19: -0.035329858 | AQ19: 110.64193 | AR19: -0.032763349 | AS19: 82.607116 | AT19: -0.015871933 | AU19: 71.296895 | AV19: 0.013027897 | AW19: 68.338949 | AX19: 0.011603386 | AY19: 77.926756 | AZ19: 0.017128147 | BA19: 87.568061 | BB19: 0.017563034 | BC19: 101.50689 | BD19: -0.028769493
A20: 1982 | B20: 1 | C20: 62.471095 | D20: 0.016767583 | E20: 65.78849 | F20: 0.005055912 | G20: 63.818622 | H20: 0.01301659 | I20: 65.39711 | J20: 0.011461178 | K20: 56.600034 | L20: 0.022305023 | M20: 70.063942 | N20: -0.011018863 | O20: 84.199778 | P20: 0.011927357 | Q20: 69.904615 | R20: 0.015546607 | S20: 92.240383 | T20: 0.0091683505 | AA20: 82.599674 | AB20: -0.0080337188 | AC20: 91.075409 | AD20: -0.024160199 | AE20: 90.057094 | AF20: -0.0013410279 | AG20: 90.382512 | AH20: 0.013790234 | AI20: 65.194919 | AJ20: 0.032714826 | AK20: 95.843 | AL20: -0.032547027 | AM20: 99.407582 | AN20: -0.039635016 | AO20: 109.13503 | AP20: -0.025138479 | AQ20: 108.95717 | AR20: -0.015227078 | AS20: 82.15621 | AT20: -0.0054584367 | AU20: 72.353598 | AV20: 0.014821167 | AW20: 69.208616 | AX20: 0.012725782 | AY20: 79.539796 | AZ20: 0.020699438 | BA20: 88.79068 | BB20: 0.013961925 | BC20: 100.23394 | BD20: -0.012540563
A21: 1982 | B21: 2 | C21: 63.771346 | D21: 0.020813642 | E21: 67.130259 | F21: 0.020395206 | G21: 64.976815 | H21: 0.018148197 | I21: 66.57991 | J21: 0.018086428 | K21: 57.653828 | L21: 0.018618257 | M21: 71.810787 | N21: 0.024932162 | O21: 85.152952 | P21: 0.011320391 | Q21: 70.638425 | R21: 0.010497294 | S21: 93.346051 | T21: 0.011986816 | AA21: 83.756453 | AB21: 0.014004644 | AC21: 91.496189 | AD21: 0.0046201266 | AE21: 90.124247 | AF21: 0.0007456674 | AG21: 91.991383 | AH21: 0.017800687 | AI21: 67.485258 | AJ21: 0.035130637 | AK21: 97.204021 | AL21: 0.014200524 | AM21: 100.9297 | AN21: 0.015311866 | AO21: 111.45886 | AP21: 0.021293103 | AQ21: 111.96418 | AR21: 0.027598029 | AS21: 82.874297 | AT21: 0.0087405018 | AU21: 73.664254 | AV21: 0.018114592 | AW21: 70.321542 | AX21: 0.016080751 | AY21: 81.452716 | AZ21: 0.024049846 | BA21: 90.366241 | BB21: 0.017744665 | BC21: 102.5107 | BD21: 0.022714473
A22: 1982 | B22: 3 | C22: 64.602993 | D22: 0.013041077 | E22: 68.059608 | F22: 0.013843959 | G22: 65.994901 | H22: 0.015668447 | I22: 67.645044 | J22: 0.015997825 | K22: 58.444634 | L22: 0.013716452 | M22: 72.458519 | N22: 0.0090199744 | O22: 85.727326 | P22: 0.0067452051 | Q22: 70.851479 | R22: 0.0030161278 | S22: 94.23665 | T22: 0.0095408324 | AA22: 88.910904 | AB22: 0.061540937 | AC22: 98.438702 | AD22: 0.075877617 | AE22: 92.877734 | AF22: 0.030552126 | AG22: 93.928806 | AH22: 0.021060917 | AI22: 68.951707 | AJ22: 0.021729905 | AK22: 103.15987 | AL22: 0.061271625 | AM22: 108.41666 | AN22: 0.074179957 | AO22: 113.11015 | AP22: 0.014815302 | AQ22: 114.23424 | AR22: 0.020274924 | AS22: 83.403891 | AT22: 0.0063903297 | AU22: 74.781656 | AV22: 0.015168851 | AW22: 71.236842 | AX22: 0.013015927 | AY22: 83.204973 | AZ22: 0.021512577 | BA22: 92.256242 | BB22: 0.020914903 | BC22: 104.21518 | BD22: 0.016627327
A23: 1982 | B23: 4 | C23: 65.316708 | D23: 0.011047714 | E23: 69.475502 | F23: 0.020803741 | G23: 66.726699 | H23: 0.011088704 | I23: 68.415773 | J23: 0.011393725 | K23: 58.972818 | L23: 0.0090373472 | M23: 75.503334 | N23: 0.042021493 | O23: 86.209337 | P23: 0.0056226059 | Q23: 70.961918 | R23: 0.0015587289 | S23: 95.066615 | T23: 0.0088072417 | AA23: 89.521553 | AB23: 0.0068681021 | AC23: 99.157043 | AD23: 0.0072973456 | AE23: 89.58807 | AF23: -0.035419294 | AG23: 92.54414 | AH23: -0.014741648 | AI23: 69.456254 | AJ23: 0.0073173999 | AK23: 105.84255 | AL23: 0.026005106 | AM23: 111.60932 | AN23: 0.029448087 | AO23: 112.97789 | AP23: -0.0011693012 | AQ23: 114.77454 | AR23: 0.0047297183 | AS23: 84.337202 | AT23: 0.011190258 | AU23: 75.182374 | AV23: 0.0053585127 | AW23: 71.910177 | AX23: 0.0094520509 | AY23: 82.664267 | AZ23: -0.006498488 | BA23: 90.9261 | BB23: -0.014417906 | BC23: 104.88634 | BD23: 0.0064401345
A24: 1983 | B24: 1 | C24: 65.035033 | D24: -0.0043124519 | E24: 68.926886 | F24: -0.007896548 | G24: 66.777147 | H24: 0.00075604758 | I24: 68.433321 | J24: 0.00025648729 | K24: 59.20123 | L24: 0.0038731636 | M24: 73.527632 | N24: -0.02616708 | O24: 86.597453 | P24: 0.0045020184 | Q24: 71.028951 | R24: 0.00094464479 | S24: 95.738676 | T24: 0.0070693717 | AA24: 88.332527 | AB24: -0.01328201 | AC24: 98.026886 | AD24: -0.011397645 | AE24: 89.756314 | AF24: 0.0018779741 | AG24: 91.492429 | AH24: -0.011364433 | AI24: 68.405552 | AJ24: -0.015127537 | AK24: 103.85723 | AL24: -0.018757294 | AM24: 109.23842 | AN24: -0.021242837 | AO24: 110.64106 | AP24: -0.020683979 | AQ24: 111.32283 | AR24: -0.030073792 | AS24: 83.731564 | AT24: -0.0071811502 | AU24: 75.039755 | AV24: -0.0018969764 | AW24: 72.042926 | AX24: 0.0018460406 | AY24: 81.615212 | AZ24: -0.012690549 | BA24: 89.906457 | BB24: -0.011213972 | BC24: 102.34066 | BD24: -0.024270803
... A193: 2025 | B193: 2 | C193: 106.07947 | D193: -0.0016128232 | E193: 111.97509 | F193: 0.023788789 | G193: 108.2725 | H193: -0.001188775 | I193: 107.24334 | J193: -0.0020462316 | K193: 112.88003 | L193: 0.0025383381 | M193: 120.51557 | N193: 0.083017186 | O193: 108.48795 | P193: 0.0024768266 | Q193: 115.99676 | R193: 0.0031783419 | S193: 105.09855 | T193: 0.0021260438 | AA193: 116.59589 | AB193: -0.027688429 | AC193: 121.01158 | AD193: -0.030517388 | AE193: 100.61961 | AF193: -0.027214749 | AG193: 92.186698 | AH193: -0.023092575 | AI193: 105.6038 | AJ193: -0.0061899824 | AK193: 128.86748 | AL193: -0.0023057627 | AM193: 134.91477 | AN193: 0.0052802954 | AO193: 105.16319 | AP193: -0.012706551 | AQ193: 103.31012 | AR193: -0.017207303 | AS193: 117.3217 | AT193: -0.01187194 | AU193: 105.2181 | AV193: -0.0097766537 | AW193: 108.34174 | AX193: -0.00014615792 | AY193: 100.47141 | AZ193: -0.02368097 | BA193: 98.166135 | BB193: -0.031151232 | BC193: 109.18143 | BD193: -0.014759171

Sheet gc_q
A1: =IF(INDIRECT("beschriftung!"&ADDRESS(beschriftung!$C$1*12+ROW(beschriftung!$A1)-1,COLUMN(beschriftung!A$1)))="","",INDIRECT("beschriftung!"&ADDRESS(beschriftung!$C$1*12+ROW(beschriftung!$A1)-1,COLUMN(beschriftung!A$1)))) -> ESA 2010, Quarterly aggregates of Gross Domestic Product, expenditure approach, seasonally, calendar and sport event adjusted data. Background information on sport event adjustment can be found in the publication “Konjunkturtendenzen” (“Economic Trends”) from autumn 2022 and in the technical note from 5 September 2022 on the website www.seco.admin.ch.
A2: =IF(INDIRECT("beschriftung!"&ADDRESS(beschriftung!$C$1*12+ROW(beschriftung!$A6)-1,COLUMN(beschriftung!A$1)))="","",INDIRECT("beschriftung!"&ADDRESS(beschriftung!$C$1*12+ROW(beschriftung!$A6)-1,COLUMN(beschriftung!A$1)))) -> Contributions to real GDP-growth
A3: =IF(INDIRECT("beschriftung!"&ADDRESS(beschriftung!$C$1*12+ROW(beschriftung!$A5)-1,COLUMN(beschriftung!A$1)))="","",INDIRECT("beschriftung!"&ADDRESS(beschriftung!$C$1*12+ROW(beschriftung!$A5)-1,COLUMN(beschriftung!A$1))))
C4: =IF(INDIRECT("beschriftung!"&ADDRESS(beschriftung!$C$1*12+ROW(beschriftung!$A5)-1,COLUMN(beschriftung!C$1)))="","",INDIRECT("beschriftung!"&ADDRESS(beschriftung!$C$1*12+ROW(beschriftung!$A5)-1,COLUMN(beschriftung!C$1)))) -> Gross domestic product
E5: =IF(INDIRECT("beschriftung!"&ADDRESS(beschriftung!$C$1*12+ROW(beschriftung!$A6)-1,COLUMN(beschriftung!E$1)))="","",INDIRECT("beschriftung!"&ADDRESS(beschriftung!$C$1*12+ROW(beschriftung!$A6)-1,COLUMN(beschriftung!E$1)))) -> Internal demand | Y5: =IF(INDIRECT("beschriftung!"&ADDRESS(beschriftung!$C$1*12+ROW(beschriftung!$A6)-1,COLUMN(beschriftung!Y$1)))="","",INDIRECT("beschriftung!"&ADDRESS(beschriftung!$C$1*12+ROW(beschriftung!$A6)-1,COLUMN(beschriftung!Y$1)))) -> Trade balance (goods and services) | AU5: =IF(INDIRECT("beschriftung!"&ADDRESS(beschriftung!$C$1*12+ROW(beschriftung!$A6)-1,COLUMN(beschriftung!AU$1)))="","",INDIRECT("beschriftung!"&ADDRESS(beschriftung!$C$1*12+ROW(beschriftung!$A6)-1,COLUMN(beschriftung!AU$1)))) -> Global demand excluding inventories change, stat. discrepancies and valuables
G6: =IF(INDIRECT("beschriftung!"&ADDRESS(beschriftung!$C$1*12+ROW(beschriftung!$A7)-1,COLUMN(beschriftung!G$1)))="","",INDIRECT("beschriftung!"&ADDRESS(beschriftung!$C$1*12+ROW(beschriftung!$A7)-1,COLUMN(beschriftung!G$1)))) -> Final consumption expenditure | M6: =IF(INDIRECT("beschriftung!"&ADDRESS(beschriftung!$C$1*12+ROW(beschriftung!$A7)-1,COLUMN(beschriftung!M$1)))="","",INDIRECT("beschriftung!"&ADDRESS(beschriftung!$C$1*12+ROW(beschriftung!$A7)-1,COLUMN(beschriftung!M$1)))) -> Gross capital formation | AA6: =IF(INDIRECT("beschriftung!"&ADDRESS(beschriftung!$C$1*12+ROW(beschriftung!$A7)-1,COLUMN(beschriftung!AA$1)))="","",INDIRECT("beschriftung!"&ADDRESS(beschriftung!$C$1*12+ROW(beschriftung!$A7)-1,COLUMN(beschriftung!AA$1)))) -> Exports of goods and services | AK6: =IF(INDIRECT("beschriftung!"&ADDRESS(beschriftung!$C$1*12+ROW(beschriftung!$A7)-1,COLUMN(beschriftung!AK$1)))="","",INDIRECT("beschriftung!"&ADDRESS(beschriftung!$C$1*12+ROW(beschriftung!$A7)-1,COLUMN(beschriftung!AK$1)))) -> Imports of goods and services | AW6: =IF(INDIRECT("beschriftung!"&ADDRESS(beschriftung!$C$1*12+ROW(beschriftung!$A7)-1,COLUMN(beschriftung!AW$1)))="","",INDIRECT("beschriftung!"&ADDRESS(beschriftung!$C$1*12+ROW(beschriftung!$A7)-1,COLUMN(beschriftung!AW$1)))) -> Final domestic demand | AY6: =IF(INDIRECT("beschriftung!"&ADDRESS(beschriftung!$C$1*12+ROW(beschriftung!$A7)-1,COLUMN(beschriftung!AY$1)))="","",INDIRECT("beschriftung!"&ADDRESS(beschriftung!$C$1*12+ROW(beschriftung!$A7)-1,COLUMN(beschriftung!AY$1)))) -> Exports of goods and services (excluding valuables) | BC6: =IF(INDIRECT("beschriftung!"&ADDRESS(beschriftung!$C$1*12+ROW(beschriftung!$A7)-1,COLUMN(beschriftung!BC$1)))="","",INDIRECT("beschriftung!"&ADDRESS(beschriftung!$C$1*12+ROW(beschriftung!$A7)-1,COLUMN(beschriftung!BC$1)))) -> Imports of goods and services (excluding valuables)
I7: =IF(INDIRECT("beschriftung!"&ADDRESS(beschriftung!$C$1*12+ROW(beschriftung!$A8)-1,COLUMN(beschriftung!I$1)))="","",INDIRECT("beschriftung!"&ADDRESS(beschriftung!$C$1*12+ROW(beschriftung!$A8)-1,COLUMN(beschriftung!I$1)))) -> Households and NPISH | K7: =IF(INDIRECT("beschriftung!"&ADDRESS(beschriftung!$C$1*12+ROW(beschriftung!$A8)-1,COLUMN(beschriftung!K$1)))="","",INDIRECT("beschriftung!"&ADDRESS(beschriftung!$C$1*12+ROW(beschriftung!$A8)-1,COLUMN(beschriftung!K$1)))) -> General government | O7: =IF(INDIRECT("beschriftung!"&ADDRESS(beschriftung!$C$1*12+ROW(beschriftung!$A8)-1,COLUMN(beschriftung!O$1)))="","",INDIRECT("beschriftung!"&ADDRESS(beschriftung!$C$1*12+ROW(beschriftung!$A8)-1,COLUMN(beschriftung!O$1)))) -> Gross fixed capital formation | U7: =IF(INDIRECT("beschriftung!"&ADDRESS(beschriftung!$C$1*12+ROW(beschriftung!$A8)-1,COLUMN(beschriftung!U$1)))="","",INDIRECT("beschriftung!"&ADDRESS(beschriftung!$C$1*12+ROW(beschriftung!$A8)-1,COLUMN(beschriftung!U$1)))) -> Changes in inventories and statistical discrepancies | W7: =IF(INDIRECT("beschriftung!"&ADDRESS(beschriftung!$C$1*12+ROW(beschriftung!$A8)-1,COLUMN(beschriftung!W$1)))="","",INDIRECT("beschriftung!"&ADDRESS(beschriftung!$C$1*12+ROW(beschriftung!$A8)-1,COLUMN(beschriftung!W$1)))) -> Acquisitions less disposals of valuables | AC7: =IF(INDIRECT("beschriftung!"&ADDRESS(beschriftung!$C$1*12+ROW(beschriftung!$A8)-1,COLUMN(beschriftung!AC$1)))="","",INDIRECT("beschriftung!"&ADDRESS(beschriftung!$C$1*12+ROW(beschriftung!$A8)-1,COLUMN(beschriftung!AC$1)))) -> Exports (exp.) of goods | AI7: =IF(INDIRECT("beschriftung!"&ADDRESS(beschriftung!$C$1*12+ROW(beschriftung!$A8)-1,COLUMN(beschriftung!AI$1)))="","",INDIRECT("beschriftung!"&ADDRESS(beschriftung!$C$1*12+ROW(beschriftung!$A8)-1,COLUMN(beschriftung!AI$1)))) -> Exports of services | AM7: =IF(INDIRECT("beschriftung!"&ADDRESS(beschriftung!$C$1*12+ROW(beschriftung!$A8)-1,COLUMN(beschriftung!AM$1)))="","",INDIRECT("beschriftung!"&ADDRESS(beschriftung!$C$1*12+ROW(beschriftung!$A8)-1,COLUMN(beschriftung!AM$1)))) -> Imports (imp.) of goods | AS7: =IF(INDIRECT("beschriftung!"&ADDRESS(beschriftung!$C$1*12+ROW(beschriftung!$A8)-1,COLUMN(beschriftung!AS$1)))="","",INDIRECT("beschriftung!"&ADDRESS(beschriftung!$C$1*12+ROW(beschriftung!$A8)-1,COLUMN(beschriftung!AS$1)))) -> Imports of services | BA7: =IF(INDIRECT("beschriftung!"&ADDRESS(beschriftung!$C$1*12+ROW(beschriftung!$A8)-1,COLUMN(beschriftung!BA$1)))="","",INDIRECT("beschriftung!"&ADDRESS(beschriftung!$C$1*12+ROW(beschriftung!$A8)-1,COLUMN(beschriftung!BA$1)))) -> thereof exports of goods excluding valuables
Q8: =IF(INDIRECT("beschriftung!"&ADDRESS(beschriftung!$C$1*12+ROW(beschriftung!$A9)-1,COLUMN(beschriftung!Q$1)))="","",INDIRECT("beschriftung!"&ADDRESS(beschriftung!$C$1*12+ROW(beschriftung!$A9)-1,COLUMN(beschriftung!Q$1)))) -> Construction | S8: =IF(INDIRECT("beschriftung!"&ADDRESS(beschriftung!$C$1*12+ROW(beschriftung!$A9)-1,COLUMN(beschriftung!S$1)))="","",INDIRECT("beschriftung!"&ADDRESS(beschriftung!$C$1*12+ROW(beschriftung!$A9)-1,COLUMN(beschriftung!S$1)))) -> Fixed assets and software | AE8: =IF(INDIRECT("beschriftung!"&ADDRESS(beschriftung!$C$1*12+ROW(beschriftung!$A9)-1,COLUMN(beschriftung!AE$1)))="","",INDIRECT("beschriftung!"&ADDRESS(beschriftung!$C$1*12+ROW(beschriftung!$A9)-1,COLUMN(beschriftung!AE$1)))) -> thereof exp. of goods excluding non-monetary gold | AG8: =IF(INDIRECT("beschriftung!"&ADDRESS(beschriftung!$C$1*12+ROW(beschriftung!$A9)-1,COLUMN(beschriftung!AG$1)))="","",INDIRECT("beschriftung!"&ADDRESS(beschriftung!$C$1*12+ROW(beschriftung!$A9)-1,COLUMN(beschriftung!AG$1)))) -> thereof exp. of goods excluding valuables and merchanting | AO8: =IF(INDIRECT("beschriftung!"&ADDRESS(beschriftung!$C$1*12+ROW(beschriftung!$A9)-1,COLUMN(beschriftung!AO$1)))="","",INDIRECT("beschriftung!"&ADDRESS(beschriftung!$C$1*12+ROW(beschriftung!$A9)-1,COLUMN(beschriftung!AO$1)))) -> thereof imp. of goods excluding non-monetary gold | AQ8: =IF(INDIRECT("beschriftung!"&ADDRESS(beschriftung!$C$1*12+ROW(beschriftung!$A9)-1,COLUMN(beschriftung!AQ$1)))="","",INDIRECT("beschriftung!"&ADDRESS(beschriftung!$C$1*12+ROW(beschriftung!$A9)-1,COLUMN(beschriftung!AQ$1)))) -> thereof imp. of goods excluding valuables
C11: B.1*b | E11: P.3+P.5 | G11: P.3 | I11: S.14+S15 | K11: S.13 | M11: P.5 | O11: P.51 | Q11: P.5111c | S11: P.5111be | U11: P.52 | W11: P.53 | AA11: P.6 | AC11: P.61 | AI11: P.62 | AK11: P.7 | AM11: P.71 | AS11: P.72 | AW11: P.3+P.51
A12: 1980 | B12: 1
A13: 1980 | B13: 2 | E13: -0.047743428 | G13: 0.0020903979 | I13: 0.00033423665 | K13: 0.0017561612 | M13: -0.049833826 | O13: -0.0032925788 | Q13: 0.0032905926 | S13: -0.0065831714 | U13: -0.0040913819 | W13: -0.042449865 | Y13: 0.049297718 | AA13: 0.0066049665 | AC13: 0.0037887966 | AE13: -0.0036863789 | AG13: -0.0013930261 | AI13: 0.00281617 | AK13: 0.042692752 | AM13: 0.043452409 | AO13: 0.012741122 | AQ13: 0.006123883 | AS13: -0.00075965744 | AU13: 0.00028144677 | AW13: -0.0012021809 | AY13: 0.0014836277 | BA13: -0.0013325422 | BC13: 0.0053642256
A14: 1980 | B14: 3 | E14: -0.0076635303 | G14: 0.0025040507 | I14: 0.0015172108 | K14: 0.00098683991 | M14: -0.010167581 | O14: 0.0026564928 | Q14: 0.0025745317 | S14: 8.1961056e-05 | U14: 0.0066548931 | W14: -0.019478967 | Y14: 0.012759178 | AA14: 0.0075484037 | AC14: 0.0044144801 | AE14: 0.00012901478 | AG14: 0.0013911827 | AI14: 0.0031339236 | AK14: 0.0052107747 | AM14: 0.0061728643 | AO14: -0.0077943011 | AQ14: -0.010432448 | AS14: -0.00096208955 | AU14: 0.0098352924 | AW14: 0.0051605434 | AY14: 0.0046747489 | BA14: 0.0015408253 | BC14: -0.011394537
A15: 1980 | B15: 4 | E15: -0.0024414609 | G15: 0.0033533283 | I15: 0.0028317982 | K15: 0.00052153016 | M15: -0.0057947892 | O15: 0.0033034033 | Q15: 0.0021464901 | S15: 0.0011569132 | U15: -0.013311972 | W15: 0.0042137791 | Y15: 0.0082232703 | AA15: 0.0086361147 | AC15: 0.006173374 | AE15: 0.0067558639 | AG15: 0.00020953343 | AI15: 0.0024627407 | AK15: -0.00041284437 | AM15: -7.3189147e-05 | AO15: 0.0070658901 | AQ15: 0.0098910912 | AS15: -0.00033965522 | AU15: 0.0095423451 | AW15: 0.0066567317 | AY15: 0.0028856134 | BA15: 0.0004228727 | BC15: 0.009551436
A16: 1981 | B16: 1 | E16: -0.010349258 | G16: -8.5257796e-05 | I16: -0.0005709083 | K16: 0.0004856505 | M16: -0.010264001 | O16: 0.00039595817 | Q16: 0.0021343646 | S16: -0.0017384064 | U16: -0.0086689412 | W16: -0.0019910175 | Y16: 0.0099555016 | AA16: 0.020846524 | AC16: 0.020097515 | AE16: 0.0052745261 | AG16: 0.0033748504 | AI16: 0.00074900881 | AK16: -0.010891022 | AM16: -0.010025181 | AO16: 0.0092236438 | AQ16: 0.004501931 | AS16: -0.00086584119 | AU16: 0.0046390946 | AW16: 0.00031070038 | AY16: 0.0043283942 | BA16: 0.0035793854 | BC16: 0.0036360898
A17: 1981 | B17: 2 | E17: -0.006635261 | G17: 0.005213309 | I17: 0.0047189046 | K17: 0.00049440435 | M17: -0.01184857 | O17: 0.00041208121 | Q17: -5.9073716e-05 | S17: 0.00047115493 | U17: 0.0010243223 | W17: -0.013284973 | Y17: 0.018065075 | AA17: 0.018146288 | AC17: 0.015114253 | AE17: 0.011280483 | AG17: 0.0048395224 | AI17: 0.0030320349 | AK17: -8.1213096e-05 | AM17: 0.0019621481 | AO17: -0.0072918211 | AQ17: -0.0011623896 | AS17: -0.0020433612 | AU17: 0.013611242 | AW17: 0.0056253902 | AY17: 0.007985852 | BA17: 0.0049538171 | BC17: -0.0032057508
A18: 1981 | B18: 3 | E18: 0.034095188 | G18: -0.00063021011 | I18: -0.00053875853 | K18: -9.1451581e-05 | M18: 0.034725399 | O18: 0.0059387815 | Q18: -0.00062078878 | S18: 0.0065595702 | U18: 0.0048032303 | W18: 0.023983387 | Y18: -0.030622061 | AA18: 0.042902901 | AC18: 0.04076726 | AE18: 0.011101553 | AG18: 0.0049308403 | AI18: 0.002135641 | AK18: -0.073524962 | AM18: -0.071794441 | AO18: -0.014622291 | AQ18: -0.01195009 | AS18: -0.0017305208 | AU18: 0.012350508 | AW18: 0.0053085713 | AY18: 0.007041937 | BA18: 0.004906296 | BC18: -0.013680611
A19: 1981 | B19: 4 | E19: -0.0062889321 | G19: 0.00020254981 | I19: 0.00013657708 | K19: 6.5972727e-05 | M19: -0.0064914819 | O19: -0.011565286 | Q19: -0.0035072224 | S19: -0.008058064 | U19: 0.013948885 | W19: -0.0088750802 | Y19: 0.002537134 | AA19: -0.00088440277 | AC19: -0.0024441244 | AE19: -0.0068840654 | AG19: -0.0052614139 | AI19: 0.0015597216 | AK19: 0.0034215368 | AM19: 0.0062319251 | AO19: 0.0026164026 | AQ19: 0.00034583721 | AS19: -0.0028103884 | AU19: -0.015236132 | AW19: -0.011362737 | AY19: -0.003873395 | BA19: -0.0054331166 | BC19: -0.0024645511
A20: 1982 | B20: 1 | E20: 0.0059799094 | G20: -0.0023000671 | I20: -0.00232157 | K20: 2.1502918e-05 | M20: 0.0082799765 | O20: -0.0062812433 | Q20: 5.7601492e-05 | S20: -0.0063388448 | U20: 0.00066179203 | W20: 0.013899428 | Y20: -0.012902183 | AA20: -0.019497099 | AC20: -0.017880582 | AE20: -0.0025027016 | AG20: -0.0057949426 | AI20: -0.0016165168 | AK20: 0.0065949153 | AM20: 0.0080613658 | AO20: 0.0060088702 | AQ20: 0.010216801 | AS20: -0.0014664505 | AU20: -0.016334417 | AW20: -0.0085813104 | AY20: -0.0077531064 | BA20: -0.0061365896 | BC20: 0.0087503508
A21: 1982 | B21: 2 | E21: 0.00047802893 | G21: 0.0031978121 | I21: 0.0031942467 | K21: 3.5653807e-06 | M21: -0.0027197832 | O21: 3.0339069e-05 | Q21: -0.0025108182 | S21: 0.0025411573 | U21: -0.010193814 | W21: 0.0074436919 | Y21: -0.0069853906 | AA21: -0.010805635 | AC21: -0.010403625 | AE21: 0.0019052501 | AG21: -0.00078479986 | AI21: -0.00040200971 | AK21: 0.0038202442 | AM21: 0.0038282727 | AO21: 0.0023660002 | AQ21: 0.0018692766 | AS21: -8.028451e-06 | AU21: 0.0018252043 | AW21: 0.0032281512 | AY21: -0.0014029469 | BA21: -0.0010009371 | BC21: 0.0018612482
A22: 1982 | B22: 3 | E22: -0.009678943 | G22: 0.0014032224 | I22: 0.0012637307 | K22: 0.00013949165 | M22: -0.011082165 | O22: -0.0025388963 | Q22: -0.00052713847 | S22: -0.0020117579 | U22: -0.0087237452 | W22: 0.00018047614 | Y22: 0.0043997246 | AA22: -0.010511392 | AC22: -0.011553276 | AE22: -0.014106287 | AG22: -0.0042454378 | AI22: 0.0010418836 | AK22: 0.014911117 | AM22: 0.015203486 | AO22: 0.0073556511 | AQ22: 0.0081261514 | AS22: -0.00029236963 | AU22: -0.004389255 | AW22: -0.001135674 | AY22: -0.003253581 | BA22: -0.0042954646 | BC22: 0.0078337818
A23: 1982 | B23: 4 | E23: -0.023663981 | G23: 0.0021494853 | I23: 0.00055150064 | K23: 0.0015979847 | M23: -0.025813466 | O23: 0.0015585437 | Q23: 0.0028048877 | S23: -0.001246344 | U23: -0.0074933844 | W23: -0.019878625 | Y23: 0.020629747 | AA23: 0.0105586 | AC23: 0.0092091621 | AE23: 0.017168735 | AG23: 0.0049446703 | AI23: 0.0013494382 | AK23: 0.010071146 | AM23: 0.0099721743 | AO23: -0.010278264 | AQ23: -0.0056092409 | AS23: 9.8972106e-05 | AU23: 0.0099694192 | AW23: 0.003708029 | AY23: 0.0062613903 | BA23: 0.0049119521 | BC23: -0.0055102688
A24: 1983 | B24: 1 | E24: 0.041170768 | G24: 0.0072198952 | I24: 0.0065592099 | K24: 0.00066068521 | M24: 0.033950872 | O24: 0.0052031343 | Q24: 0.00082625132 | S24: 0.0043768829 | U24: 0.0027599371 | W24: 0.025987801 | Y24: -0.032873732 | AA24: -0.016879013 | AC24: -0.019174219 | AE24: -0.0051435957 | AG24: 0.0012176369 | AI24: 0.0022952061 | AK24: -0.015994719 | AM24: -0.01559903 | AO24: -0.0065713939 | AQ24: -0.0098445726 | AS24: -0.00039568915 | AU24: 0.01577736 | AW24: 0.012423029 | AY24: 0.0033543307 | BA24: 0.0010591246 | BC24: -0.010240262
... A193: 2025 | B193: 2 | E193: 0.052794923 | G193: 0.0024435301 | I193: 0.0014282937 | K193: 0.0010152365 | M193: 0.050351393 | O193: -0.0014692358 | Q193: -0.00011985963 | S193: -0.0013493762 | U193: -0.0027165458 | W193: 0.054537174 | Y193: -0.051549671 | AA193: -0.10033286 | AC193: -0.10426287 | AE193: -0.016893131 | AG193: -0.01477992 | AI193: 0.0039300076 | AK193: 0.048783189 | AM193: 0.049009269 | AO193: 0.019033318 | AQ193: 0.019866641 | AS193: -0.00022608051 | AU193: -0.015678762 | AW193: 0.00097429432 | AY193: -0.016653057 | BA193: -0.020583064 | BC193: 0.01964056

Sheet nom_y
A1: =IF(INDIRECT("beschriftung!"&ADDRESS(beschriftung!$C$1*12+ROW(beschriftung!$A1)-1,COLUMN(beschriftung!B$1)))="","",INDIRECT("beschriftung!"&ADDRESS(beschriftung!$C$1*12+ROW(beschriftung!$A1)-1,COLUMN(beschriftung!B$1)))) -> ESA 2010, Annual aggregates of Gross Domestic Product, expenditure approach (SFSO, SECO), seasonally, calendar and sport event adjusted data
A2: =IF(INDIRECT("beschriftung!"&ADDRESS(beschriftung!$C$1*12+ROW(beschriftung!$A2)-1,COLUMN(beschriftung!B$1)))="","",INDIRECT("beschriftung!"&ADDRESS(beschriftung!$C$1*12+ROW(beschriftung!$A2)-1,COLUMN(beschriftung!B$1)))) -> In Mio. Swiss Francs, at current prices, percentage change to previous year
A3: =IF(INDIRECT("beschriftung!"&ADDRESS(beschriftung!$C$1*12+ROW(beschriftung!$A5)-1,COLUMN(beschriftung!B$1)))="","",INDIRECT("beschriftung!"&ADDRESS(beschriftung!$C$1*12+ROW(beschriftung!$A5)-1,COLUMN(beschriftung!B$1))))
C4: =IF(INDIRECT("beschriftung!"&ADDRESS(beschriftung!$C$1*12+ROW(beschriftung!$A5)-1,COLUMN(beschriftung!C$1)))="","",INDIRECT("beschriftung!"&ADDRESS(beschriftung!$C$1*12+ROW(beschriftung!$A5)-1,COLUMN(beschriftung!C$1)))) -> Gross domestic product
E5: =IF(INDIRECT("beschriftung!"&ADDRESS(beschriftung!$C$1*12+ROW(beschriftung!$A6)-1,COLUMN(beschriftung!E$1)))="","",INDIRECT("beschriftung!"&ADDRESS(beschriftung!$C$1*12+ROW(beschriftung!$A6)-1,COLUMN(beschriftung!E$1)))) -> Internal demand | Y5: =IF(INDIRECT("beschriftung!"&ADDRESS(beschriftung!$C$1*12+ROW(beschriftung!$A6)-1,COLUMN(beschriftung!Y$1)))="","",INDIRECT("beschriftung!"&ADDRESS(beschriftung!$C$1*12+ROW(beschriftung!$A6)-1,COLUMN(beschriftung!Y$1)))) -> Trade balance (goods and services) | AU5: =IF(INDIRECT("beschriftung!"&ADDRESS(beschriftung!$C$1*12+ROW(beschriftung!$A6)-1,COLUMN(beschriftung!AU$1)))="","",INDIRECT("beschriftung!"&ADDRESS(beschriftung!$C$1*12+ROW(beschriftung!$A6)-1,COLUMN(beschriftung!AU$1)))) -> Global demand excluding inventories change, stat. discrepancies and valuables
G6: =IF(INDIRECT("beschriftung!"&ADDRESS(beschriftung!$C$1*12+ROW(beschriftung!$A7)-1,COLUMN(beschriftung!G$1)))="","",INDIRECT("beschriftung!"&ADDRESS(beschriftung!$C$1*12+ROW(beschriftung!$A7)-1,COLUMN(beschriftung!G$1)))) -> Final consumption expenditure | M6: =IF(INDIRECT("beschriftung!"&ADDRESS(beschriftung!$C$1*12+ROW(beschriftung!$A7)-1,COLUMN(beschriftung!M$1)))="","",INDIRECT("beschriftung!"&ADDRESS(beschriftung!$C$1*12+ROW(beschriftung!$A7)-1,COLUMN(beschriftung!M$1)))) -> Gross capital formation | AA6: =IF(INDIRECT("beschriftung!"&ADDRESS(beschriftung!$C$1*12+ROW(beschriftung!$A7)-1,COLUMN(beschriftung!AA$1)))="","",INDIRECT("beschriftung!"&ADDRESS(beschriftung!$C$1*12+ROW(beschriftung!$A7)-1,COLUMN(beschriftung!AA$1)))) -> Exports of goods and services | AK6: =IF(INDIRECT("beschriftung!"&ADDRESS(beschriftung!$C$1*12+ROW(beschriftung!$A7)-1,COLUMN(beschriftung!AK$1)))="","",INDIRECT("beschriftung!"&ADDRESS(beschriftung!$C$1*12+ROW(beschriftung!$A7)-1,COLUMN(beschriftung!AK$1)))) -> Imports of goods and services | AW6: =IF(INDIRECT("beschriftung!"&ADDRESS(beschriftung!$C$1*12+ROW(beschriftung!$A7)-1,COLUMN(beschriftung!AW$1)))="","",INDIRECT("beschriftung!"&ADDRESS(beschriftung!$C$1*12+ROW(beschriftung!$A7)-1,COLUMN(beschriftung!AW$1)))) -> Final domestic demand | AY6: =IF(INDIRECT("beschriftung!"&ADDRESS(beschriftung!$C$1*12+ROW(beschriftung!$A7)-1,COLUMN(beschriftung!AY$1)))="","",INDIRECT("beschriftung!"&ADDRESS(beschriftung!$C$1*12+ROW(beschriftung!$A7)-1,COLUMN(beschriftung!AY$1)))) -> Exports of goods and services (excluding valuables) | BC6: =IF(INDIRECT("beschriftung!"&ADDRESS(beschriftung!$C$1*12+ROW(beschriftung!$A7)-1,COLUMN(beschriftung!BC$1)))="","",INDIRECT("beschriftung!"&ADDRESS(beschriftung!$C$1*12+ROW(beschriftung!$A7)-1,COLUMN(beschriftung!BC$1)))) -> Imports of goods and services (excluding valuables)
I7: =IF(INDIRECT("beschriftung!"&ADDRESS(beschriftung!$C$1*12+ROW(beschriftung!$A8)-1,COLUMN(beschriftung!I$1)))="","",INDIRECT("beschriftung!"&ADDRESS(beschriftung!$C$1*12+ROW(beschriftung!$A8)-1,COLUMN(beschriftung!I$1)))) -> Households and NPISH | K7: =IF(INDIRECT("beschriftung!"&ADDRESS(beschriftung!$C$1*12+ROW(beschriftung!$A8)-1,COLUMN(beschriftung!K$1)))="","",INDIRECT("beschriftung!"&ADDRESS(beschriftung!$C$1*12+ROW(beschriftung!$A8)-1,COLUMN(beschriftung!K$1)))) -> General government | O7: =IF(INDIRECT("beschriftung!"&ADDRESS(beschriftung!$C$1*12+ROW(beschriftung!$A8)-1,COLUMN(beschriftung!O$1)))="","",INDIRECT("beschriftung!"&ADDRESS(beschriftung!$C$1*12+ROW(beschriftung!$A8)-1,COLUMN(beschriftung!O$1)))) -> Gross fixed capital formation | U7: =IF(INDIRECT("beschriftung!"&ADDRESS(beschriftung!$C$1*12+ROW(beschriftung!$A8)-1,COLUMN(beschriftung!U$1)))="","",INDIRECT("beschriftung!"&ADDRESS(beschriftung!$C$1*12+ROW(beschriftung!$A8)-1,COLUMN(beschriftung!U$1)))) -> Changes in inventories and statistical discrepancies | W7: =IF(INDIRECT("beschriftung!"&ADDRESS(beschriftung!$C$1*12+ROW(beschriftung!$A8)-1,COLUMN(beschriftung!W$1)))="","",INDIRECT("beschriftung!"&ADDRESS(beschriftung!$C$1*12+ROW(beschriftung!$A8)-1,COLUMN(beschriftung!W$1)))) -> Acquisitions less disposals of valuables | AC7: =IF(INDIRECT("beschriftung!"&ADDRESS(beschriftung!$C$1*12+ROW(beschriftung!$A8)-1,COLUMN(beschriftung!AC$1)))="","",INDIRECT("beschriftung!"&ADDRESS(beschriftung!$C$1*12+ROW(beschriftung!$A8)-1,COLUMN(beschriftung!AC$1)))) -> Exports (exp.) of goods | AI7: =IF(INDIRECT("beschriftung!"&ADDRESS(beschriftung!$C$1*12+ROW(beschriftung!$A8)-1,COLUMN(beschriftung!AI$1)))="","",INDIRECT("beschriftung!"&ADDRESS(beschriftung!$C$1*12+ROW(beschriftung!$A8)-1,COLUMN(beschriftung!AI$1)))) -> Exports of services | AM7: =IF(INDIRECT("beschriftung!"&ADDRESS(beschriftung!$C$1*12+ROW(beschriftung!$A8)-1,COLUMN(beschriftung!AM$1)))="","",INDIRECT("beschriftung!"&ADDRESS(beschriftung!$C$1*12+ROW(beschriftung!$A8)-1,COLUMN(beschriftung!AM$1)))) -> Imports (imp.) of goods | AS7: =IF(INDIRECT("beschriftung!"&ADDRESS(beschriftung!$C$1*12+ROW(beschriftung!$A8)-1,COLUMN(beschriftung!AS$1)))="","",INDIRECT("beschriftung!"&ADDRESS(beschriftung!$C$1*12+ROW(beschriftung!$A8)-1,COLUMN(beschriftung!AS$1)))) -> Imports of services | BA7: =IF(INDIRECT("beschriftung!"&ADDRESS(beschriftung!$C$1*12+ROW(beschriftung!$A8)-1,COLUMN(beschriftung!BA$1)))="","",INDIRECT("beschriftung!"&ADDRESS(beschriftung!$C$1*12+ROW(beschriftung!$A8)-1,COLUMN(beschriftung!BA$1)))) -> thereof exports of goods excluding valuables
Q8: =IF(INDIRECT("beschriftung!"&ADDRESS(beschriftung!$C$1*12+ROW(beschriftung!$A9)-1,COLUMN(beschriftung!Q$1)))="","",INDIRECT("beschriftung!"&ADDRESS(beschriftung!$C$1*12+ROW(beschriftung!$A9)-1,COLUMN(beschriftung!Q$1)))) -> Construction | S8: =IF(INDIRECT("beschriftung!"&ADDRESS(beschriftung!$C$1*12+ROW(beschriftung!$A9)-1,COLUMN(beschriftung!S$1)))="","",INDIRECT("beschriftung!"&ADDRESS(beschriftung!$C$1*12+ROW(beschriftung!$A9)-1,COLUMN(beschriftung!S$1)))) -> Fixed assets and software | AE8: =IF(INDIRECT("beschriftung!"&ADDRESS(beschriftung!$C$1*12+ROW(beschriftung!$A9)-1,COLUMN(beschriftung!AE$1)))="","",INDIRECT("beschriftung!"&ADDRESS(beschriftung!$C$1*12+ROW(beschriftung!$A9)-1,COLUMN(beschriftung!AE$1)))) -> thereof exp. of goods excluding non-monetary gold | AG8: =IF(INDIRECT("beschriftung!"&ADDRESS(beschriftung!$C$1*12+ROW(beschriftung!$A9)-1,COLUMN(beschriftung!AG$1)))="","",INDIRECT("beschriftung!"&ADDRESS(beschriftung!$C$1*12+ROW(beschriftung!$A9)-1,COLUMN(beschriftung!AG$1)))) -> thereof exp. of goods excluding valuables and merchanting | AO8: =IF(INDIRECT("beschriftung!"&ADDRESS(beschriftung!$C$1*12+ROW(beschriftung!$A9)-1,COLUMN(beschriftung!AO$1)))="","",INDIRECT("beschriftung!"&ADDRESS(beschriftung!$C$1*12+ROW(beschriftung!$A9)-1,COLUMN(beschriftung!AO$1)))) -> thereof imp. of goods excluding non-monetary gold | AQ8: =IF(INDIRECT("beschriftung!"&ADDRESS(beschriftung!$C$1*12+ROW(beschriftung!$A9)-1,COLUMN(beschriftung!AQ$1)))="","",INDIRECT("beschriftung!"&ADDRESS(beschriftung!$C$1*12+ROW(beschriftung!$A9)-1,COLUMN(beschriftung!AQ$1)))) -> thereof imp. of goods excluding valuables
C11: B.1*b | E11: P.3+P.5 | G11: P.3 | I11: S.14+S15 | K11: S.13 | M11: P.5 | O11: P.51 | Q11: P.5111c | S11: P.5111be | U11: P.52 | W11: P.53 | AA11: P.6 | AC11: P.61 | AI11: P.62 | AK11: P.7 | AM11: P.71 | AS11: P.72 | AW11: P.3+P.51
A12: 1980 | C12: 205216.45 | E12: 209863.72 | G12: 139714.01 | I12: 120335.55 | K12: 19378.468 | M12: 70149.706 | O12: 62806.465 | Q12: 26124.255 | S12: 36682.209 | U12: 6274.5552 | W12: 1068.6862 | Y12: -4647.2683 | AA12: 95112.465 | AC12: 71843.654 | AE12: 49916.054 | AG12: 44675.78 | AI12: 23268.811 | AK12: 99759.733 | AM12: 83012.461 | AO12: 60785.462 | AQ12: 55507.313 | AS12: 16747.272 | AU12: 271196.48 | AW12: 202520.48 | AY12: 68676.003 | BA12: 45407.192 | BC12: 72254.585
A13: 1981 | C13: 220247.41 | D13: 0.073244393 | E13: 219219.01 | F13: 0.044577944 | G13: 149898.52 | H13: 0.072895408 | I13: 128745.5 | J13: 0.069887516 | K13: 21153.026 | L13: 0.091573681 | M13: 69320.489 | N13: -0.011820675 | O13: 68058.152 | P13: 0.083616994 | Q13: 29111.407 | R13: 0.114344 | S13: 38946.745 | T13: 0.061733901 | U13: 4103.5171 | W13: -2841.1802 | Y13: 1028.393 | AA13: 106275.54 | AB13: 0.11736714 | AC13: 80168.598 | AD13: 0.11587585 | AE13: 54497.098 | AF13: 0.091774969 | AG13: 48420.319 | AH13: 0.083815865 | AI13: 26106.944 | AJ13: 0.12197156 | AK13: 105247.15 | AL13: 0.055006325 | AM13: 86643.765 | AN13: 0.043744081 | AO13: 62277.851 | AP13: 0.02455174 | AQ13: 58614.216 | AR13: 0.055972862 | AS13: 18603.385 | AT13: 0.11083073 | AU13: 293361.49 | AV13: 0.081730442 | AW13: 217956.68 | AX13: 0.076220429 | AY13: 75404.813 | AZ13: 0.097979063 | BA13: 49297.869 | BB13: 0.085684161 | BC13: 77217.601 | BD13: 0.068687899
A14: 1982 | C14: 233259.69 | D14: 0.059080308 | E14: 232011.23 | F14: 0.058353575 | G14: 159605.79 | H14: 0.064758916 | I14: 136629.54 | J14: 0.061237419 | K14: 22976.25 | L14: 0.086192108 | M14: 72405.437 | N14: 0.044502676 | O14: 68368.022 | P14: 0.0045530155 | Q14: 29459.748 | R14: 0.011965788 | S14: 38908.274 | T14: -0.00098778762 | U14: 2102.4011 | W14: 1935.0131 | Y14: 1248.4644 | AA14: 103580.85 | AB14: -0.02535569 | AC14: 74367.871 | AD14: -0.072356599 | AE14: 54192.771 | AF14: -0.0055842814 | AG14: 49143.792 | AH14: 0.014941527 | AI14: 29212.982 | AJ14: 0.11897361 | AK14: 102332.39 | AL14: -0.027694443 | AM14: 82649.587 | AN14: -0.046098848 | AO14: 59620.733 | AP14: -0.042665545 | AQ14: 56280.884 | AR14: -0.039808288 | AS14: 19682.801 | AT14: 0.05802259 | AU14: 307120.98 | AV14: 0.046902835 | AW14: 227973.81 | AX14: 0.045959297 | AY14: 79147.163 | AZ14: 0.049630119 | BA14: 49934.182 | BB14: 0.012907503 | BC14: 75963.686 | BD14: -0.01623872
A15: 1983 | C15: 240387.74 | D15: 0.030558424 | E15: 242952.77 | F15: 0.047159544 | G15: 167243.25 | H15: 0.047852045 | I15: 142899.8 | J15: 0.045892448 | K15: 24343.449 | L15: 0.0595049 | M15: 75709.517 | N15: 0.045633041 | O15: 72081.566 | P15: 0.05431697 | Q15: 31091.752 | R15: 0.05539775 | S15: 40989.814 | T15: 0.053498647 | U15: -2015.9474 | W15: 5643.8981 | Y15: -2565.0307 | AA15: 103679.17 | AB15: 0.00094917409 | AC15: 72844.116 | AD15: -0.020489427 | AE15: 55279.716 | AF15: 0.020057009 | AG15: 50333.817 | AH15: 0.024215149 | AI15: 30835.053 | AJ15: 0.055525703 | AK15: 106244.2 | AL15: 0.038226523 | AM15: 85901.123 | AN15: 0.039341229 | AO15: 62810.48 | AP15: 0.053500642 | AQ15: 58515.517 | AR15: 0.039705009 | AS15: 20343.076 | AT15: 0.033545785 | AU15: 321262.28 | AV15: 0.046044739 | AW15: 239324.82 | AX15: 0.049790839 | AY15: 81937.461 | AZ15: 0.035254554 | BA15: 51102.408 | BB15: 0.023395328 | BC15: 78858.594 | BD15: 0.038109104
A16: 1984 | C16: 257056.51 | D16: 0.06934119 | E16: 249792.59 | F16: 0.02815289 | G16: 175202.44 | H16: 0.047590488 | I16: 149699.54 | J16: 0.047583952 | K16: 25502.9 | L16: 0.047628855 | M16: 74590.151 | N16: -0.014785003 | O16: 76468.087 | P16: 0.06085496 | Q16: 32942.833 | R16: 0.059536079 | S16: 43525.254 | T16: 0.061855362 | U16: 2576.2086 | W16: -4454.1441 | Y16: 7263.9188 | AA16: 121628.05 | AB16: 0.17311946 | AC16: 87825.973 | AD16: 0.20567011 | AE16: 62448.973 | AF16: 0.12969056 | AG16: 55791.899 | AH16: 0.10843769 | AI16: 33802.078 | AJ16: 0.096222468 | AK16: 114364.13 | AL16: 0.076427068 | AM16: 92217.662 | AN16: 0.073532666 | AO16: 71040.074 | AP16: 0.13102263 | AQ16: 65589.463 | AR16: 0.12089008 | AS16: 22146.471 | AT16: 0.088649036 | AU16: 342216.24 | AV16: 0.065223829 | AW16: 251670.53 | AX16: 0.051585577 | AY16: 90545.708 | AZ16: 0.10505875 | BA16: 56743.63 | BB16: 0.11039054 | BC16: 87735.934 | BD16: 0.11257289
A17: 1985 | C17: 272654.52 | D17: 0.060679305 | E17: 265585.34 | F17: 0.063223442 | G17: 184243.05 | H17: 0.051600906 | I17: 156909.79 | J17: 0.048164797 | K17: 27333.257 | L17: 0.071770536 | M17: 81342.294 | N17: 0.090523248 | O17: 82128.65 | P17: 0.074025164 | Q17: 34028.248 | R17: 0.032948447 | S17: 48100.401 | T17: 0.10511478 | U17: 2385.4204 | W17: -3171.7757 | Y17: 7069.1816 | AA17: 130259.11 | AB17: 0.07096271 | AC17: 92896.032 | AD17: 0.057728469 | AE17: 68601.932 | AF17: 0.098527784 | AG17: 62003.434 | AH17: 0.11133399 | AI17: 37363.075 | AJ17: 0.10534847 | AK17: 123189.93 | AL17: 0.077172739 | AM17: 98608.922 | AN17: 0.069306248 | AO17: 76784.151 | AP17: 0.080856851 | AQ17: 72074.85 | AR17: 0.098878489 | AS17: 24581.004 | AT17: 0.10992872 | AU17: 366924.96 | AV17: 0.072202065 | AW17: 266371.7 | AX17: 0.058414339 | AY17: 100553.26 | AZ17: 0.11052486 | BA17: 63190.185 | BB17: 0.11360842 | BC17: 96655.854 | BD17: 0.10166781
A18: 1986 | C18: 286161.34 | D18: 0.049538202 | E18: 283845.79 | F18: 0.068755487 | G18: 192466.68 | H18: 0.04463468 | I18: 163379.61 | J18: 0.041232725 | K18: 29087.068 | L18: 0.064164003 | M18: 91379.114 | N18: 0.12338993 | O18: 88434.554 | P18: 0.076780809 | Q18: 35629.859 | R18: 0.047067088 | S18: 52804.695 | T18: 0.097801546 | U18: -875.53067 | W18: 3820.0912 | Y18: 2315.5469 | AA18: 125709.09 | AB18: -0.034930482 | AC18: 88841.787 | AD18: -0.043642823 | AE18: 68565.287 | AF18: -0.00053416988 | AG18: 62696.874 | AH18: 0.011183907 | AI18: 36867.307 | AJ18: -0.013268938 | AK18: 123393.55 | AL18: 0.001652905 | AM18: 99438.969 | AN18: 0.0084175609 | AO18: 75328.609 | AP18: -0.018956281 | AQ18: 70461.644 | AR18: -0.022382374 | AS18: 23954.578 | AT18: -0.025484125 | AU18: 381453.09 | AV18: 0.039594293 | AW18: 280901.23 | AX18: 0.054546086 | AY18: 100551.86 | AZ18: -1.391658e-05 | BA18: 63684.554 | BB18: 0.0078235091 | BC18: 94416.222 | BD18: -0.023171195
A19: 1987 | C19: 296875.34 | D19: 0.037440415 | E19: 293150.67 | F19: 0.032781443 | G19: 199569.07 | H19: 0.036901943 | I19: 169523.83 | J19: 0.037607027 | K19: 30045.241 | L19: 0.032941543 | M19: 93581.595 | N19: 0.024102667 | O19: 92839.855 | P19: 0.049814256 | Q19: 37811.75 | R19: 0.061237726 | S19: 55028.105 | T19: 0.042106293 | U19: -1187.9061 | W19: 1929.6455 | Y19: 3724.6715 | AA19: 122215.73 | AB19: -0.027789276 | AC19: 84091.215 | AD19: -0.053472267 | AE19: 69073.815 | AF19: 0.0074167016 | AG19: 62583.194 | AH19: -0.0018131675 | AI19: 38124.514 | AJ19: 0.034100863 | AK19: 118491.06 | AL19: -0.039730516 | AM19: 93510.241 | AN19: -0.059621774 | AO19: 76714.465 | AP19: 0.018397464 | AQ19: 71450.384 | AR19: 0.014032316 | AS19: 24980.817 | AT19: 0.042841013 | AU19: 394494.44 | AV19: 0.034188616 | AW19: 292408.93 | AX19: 0.040967054 | AY19: 102085.52 | AZ19: 0.015252401 | BA19: 63961.004 | BB19: 0.0043409323 | BC19: 96431.201 | BD19: 0.021341443
A20: 1988 | C20: 315136.32 | D20: 0.061510598 | E20: 311345.56 | F20: 0.062066691 | G20: 208730.17 | H20: 0.045904392 | I20: 176238.5 | J20: 0.039608992 | K20: 32491.67 | L20: 0.081424838 | M20: 102615.39 | N20: 0.096533884 | O20: 104043.54 | P20: 0.12067749 | Q20: 42175.112 | R20: 0.11539698 | S20: 61868.424 | T20: 0.12430592 | U20: -938.021 | W20: -490.12568 | Y20: 3790.7594 | AA20: 133540.02 | AB20: 0.092658186 | AC20: 93692.116 | AD20: 0.11417246 | AE20: 75902.716 | AF20: 0.098863816 | AG20: 68068.687 | AH20: 0.087651206 | AI20: 39847.9 | AJ20: 0.045204163 | AK20: 129749.26 | AL20: 0.095013076 | AM20: 102025.21 | AN20: 0.09105923 | AO20: 83937.968 | AP20: 0.0941609 | AQ20: 78290.316 | AR20: 0.095729811 | AS20: 27724.046 | AT20: 0.10981344 | AU20: 422088.7 | AV20: 0.069948401 | AW20: 312773.7 | AX20: 0.069644857 | AY20: 109315 | AZ20: 0.07081786 | BA20: 69467.095 | BB20: 0.086085127 | BC20: 106014.36 | BD20: 0.099378221
A21: 1989 | C21: 340493.51 | D21: 0.080464207 | E21: 336375.11 | F21: 0.08039155 | G21: 222910.96 | H21: 0.06793839 | I21: 186395.68 | J21: 0.05763314 | K21: 36515.283 | L21: 0.12383523 | M21: 113464.15 | N21: 0.10572255 | O21: 114137.11 | P21: 0.097012988 | Q21: 47259.969 | R21: 0.12056535 | S21: 66877.141 | T21: 0.080957566 | U21: 2249.3625 | W21: -2922.3231 | Y21: 4118.4013 | AA21: 152607.37 | AB21: 0.14278378 | AC21: 109473.24 | AD21: 0.16843594 | AE21: 86660.137 | AF21: 0.14172642 | AG21: 76213.863 | AH21: 0.11966113 | AI21: 43134.129 | AJ21: 0.082469295 | AK21: 148488.96 | AL21: 0.14443016 | AM21: 118018.42 | AN21: 0.15675743 | AO21: 96942.215 | AP21: 0.15492688 | AQ21: 89433.465 | AR21: 0.14233113 | AS21: 30470.543 | AT21: 0.099065518 | AU21: 458148.16 | AV21: 0.085430993 | AW21: 337048.07 | AX21: 0.077609996 | AY21: 121100.09 | AZ21: 0.10780854 | BA21: 77965.957 | BB21: 0.12234371 | BC21: 119904.01 | BD21: 0.13101665
A22: 1990 | C22: 369392.22 | D22: 0.084873016 | E22: 368670.66 | F22: 0.096010538 | G22: 239478.39 | H22: 0.074323089 | I22: 199327.76 | J22: 0.069379744 | K22: 40150.63 | L22: 0.099556855 | M22: 129192.27 | N22: 0.13861757 | O22: 121483.51 | P22: 0.064364661 | Q22: 50256.514 | R22: 0.063405564 | S22: 71226.993 | T22: 0.065042425 | U22: 6477.0356 | W22: 1231.7315 | Y22: 721.55721 | AA22: 152766.61 | AB22: 0.0010435108 | AC22: 110246.14 | AD22: 0.0070601894 | AE22: 90775.038 | AF22: 0.047483214 | AG22: 80495.026 | AH22: 0.056173018 | AI22: 42520.474 | AJ22: -0.014226655 | AK22: 152045.06 | AL22: 0.023948524 | AM22: 120856.31 | AN22: 0.024046155 | AO22: 99019.141 | AP22: 0.021424373 | AQ22: 91710.479 | AR22: 0.025460424 | AS22: 31188.745 | AT22: 0.023570379 | AU22: 485814.41 | AV22: 0.060387134 | AW22: 360961.9 | AX22: 0.070950792 | AY22: 124852.51 | AZ22: 0.030986161 | BA22: 82332.039 | BB22: 0.05599984 | BC22: 122899.22 | BD22: 0.024980118
A23: 1991 | C23: 385747.94 | D23: 0.044277373 | E23: 380081.14 | F23: 0.030950331 | G23: 257810.51 | H23: 0.07655019 | I23: 213621.94 | J23: 0.071711945 | K23: 44188.565 | L23: 0.10056965 | M23: 122270.64 | N23: -0.053576248 | O23: 121512.33 | P23: 0.00023728488 | Q23: 49214.255 | R23: -0.020738784 | S23: 72298.078 | T23: 0.015037631 | U23: 547.51101 | W23: 210.79261 | Y23: 5666.7953 | AA23: 153639.97 | AB23: 0.0057169345 | AC23: 108290.49 | AD23: -0.017738905 | AE23: 90543.192 | AF23: -0.0025540702 | AG23: 81919.69 | AH23: 0.017698781 | AI23: 45349.477 | AJ23: 0.066532713 | AK23: 147973.17 | AL23: -0.026780755 | AM23: 115278.57 | AN23: -0.04615185 | AO23: 97167.928 | AP23: -0.018695509 | AQ23: 90524.348 | AR23: -0.012933423 | AS23: 32694.606 | AT23: 0.048282191 | AU23: 508419.38 | AV23: 0.046530057 | AW23: 379322.84 | AX23: 0.050866705 | AY23: 129096.54 | AZ23: 0.033992345 | BA23: 83747.066 | BB23: 0.017186836 | BC23: 123218.95 | BD23: 0.002601567
A24: 1992 | C24: 393408.67 | D24: 0.01985942 | E24: 383104.07 | F24: 0.0079533773 | G24: 269397.79 | H24: 0.044944953 | I24: 222837.73 | J24: 0.043140652 | K24: 46560.056 | L24: 0.053667533 | M24: 113706.28 | N24: -0.070044227 | O24: 111095.15 | P24: -0.085729465 | Q24: 47377.727 | R24: -0.037317005 | S24: 63717.419 | T24: -0.11868447 | U24: 2275.7035 | W24: 335.43522 | Y24: 10304.597 | AA24: 160182.15 | AB24: 0.042581244 | AC24: 113547.55 | AD24: 0.048545864 | AE24: 94455.448 | AF24: 0.043208721 | AG24: 86131.748 | AH24: 0.051416924 | AI24: 46634.602 | AJ24: 0.028338265 | AK24: 149877.55 | AL24: 0.012869762 | AM24: 114844.65 | AN24: -0.0037640792 | AO24: 94448.422 | AP24: -0.027987693 | AQ24: 88531.782 | AR24: -0.022011391 | AS24: 35032.903 | AT24: 0.071519355 | AU24: 514697.65 | AV24: 0.012348601 | AW24: 380492.93 | AX24: 0.0030846908 | AY24: 134204.72 | AZ24: 0.039568639 | BA24: 87570.115 | BB24: 0.045649946 | BC24: 123564.69 | BD24: 0.0028058212
... A56: 2024 | C56: 824099.42 | D56: 0.023282753 | E56: 741026.11 | F56: 0.040443502 | G56: 517493.9 | H56: 0.027542529 | I56: 421680.53 | J56: 0.028444785 | K56: 95813.365 | L56: 0.023590384 | M56: 223532.22 | N56: 0.071590532 | O56: 206853.72 | P56: -0.0034318021 | Q56: 67860.903 | R56: 0.031042831 | S56: 138992.82 | T56: -0.019439345 | U56: 27304.37 | W56: -10625.876 | Y56: 83073.311 | AA56: 592626.48 | AB56: 0.0009672763 | AC56: 436298.3 | AD56: -0.0092762004 | AE56: 340581.65 | AF56: -0.028823392 | AG56: 274282.52 | AH56: 0.034015952 | AI56: 156328.18 | AJ56: 0.030709773 | AK56: 509553.17 | AL56: 0.021299073 | AM56: 325236.92 | AN56: -0.0068495063 | AO56: 236032.28 | AP56: -0.012542319 | AQ56: 226914.1 | AR56: -0.012749244 | AS56: 184316.26 | AT56: 0.075065677 | AU56: 1208025.4 | AV56: 0.0061801632 | AW56: 724347.62 | AX56: 0.018502428 | AY56: 483677.79 | AZ56: -0.011725764 | BA56: 327349.61 | BB56: -0.030782134 | BC56: 411230.36 | BD56: 0.024768576

Sheet real_y
A1: =IF(INDIRECT("beschriftung!"&ADDRESS(beschriftung!$C$1*12+ROW(beschriftung!$A1)-1,COLUMN(beschriftung!B$1)))="","",INDIRECT("beschriftung!"&ADDRESS(beschriftung!$C$1*12+ROW(beschriftung!$A1)-1,COLUMN(beschriftung!B$1)))) -> ESA 2010, Annual aggregates of Gross Domestic Product, expenditure approach (SFSO, SECO), seasonally, calendar and sport event adjusted data
A2: =IF(INDIRECT("beschriftung!"&ADDRESS(beschriftung!$C$1*12+ROW(beschriftung!$A3)-1,COLUMN(beschriftung!B$1)))="","",INDIRECT("beschriftung!"&ADDRESS(beschriftung!$C$1*12+ROW(beschriftung!$A3)-1,COLUMN(beschriftung!B$1)))) -> In Mio. Swiss Francs, at prices of the preceding year, chained values ("annual overlap"), reference year 2015, percentage change to previous year
A3: =IF(INDIRECT("beschriftung!"&ADDRESS(beschriftung!$C$1*12+ROW(beschriftung!$A5)-1,COLUMN(beschriftung!B$1)))="","",INDIRECT("beschriftung!"&ADDRESS(beschriftung!$C$1*12+ROW(beschriftung!$A5)-1,COLUMN(beschriftung!B$1))))
C4: =IF(INDIRECT("beschriftung!"&ADDRESS(beschriftung!$C$1*12+ROW(beschriftung!$A5)-1,COLUMN(beschriftung!C$1)))="","",INDIRECT("beschriftung!"&ADDRESS(beschriftung!$C$1*12+ROW(beschriftung!$A5)-1,COLUMN(beschriftung!C$1)))) -> Gross domestic product
E5: =IF(INDIRECT("beschriftung!"&ADDRESS(beschriftung!$C$1*12+ROW(beschriftung!$A6)-1,COLUMN(beschriftung!E$1)))="","",INDIRECT("beschriftung!"&ADDRESS(beschriftung!$C$1*12+ROW(beschriftung!$A6)-1,COLUMN(beschriftung!E$1)))) -> Internal demand | Y5: =IF(INDIRECT("beschriftung!"&ADDRESS(beschriftung!$C$1*12+ROW(beschriftung!$A6)-1,COLUMN(beschriftung!Y$1)))="","",INDIRECT("beschriftung!"&ADDRESS(beschriftung!$C$1*12+ROW(beschriftung!$A6)-1,COLUMN(beschriftung!Y$1)))) -> Trade balance (goods and services) | AU5: =IF(INDIRECT("beschriftung!"&ADDRESS(beschriftung!$C$1*12+ROW(beschriftung!$A6)-1,COLUMN(beschriftung!AU$1)))="","",INDIRECT("beschriftung!"&ADDRESS(beschriftung!$C$1*12+ROW(beschriftung!$A6)-1,COLUMN(beschriftung!AU$1)))) -> Global demand excluding inventories change, stat. discrepancies and valuables
G6: =IF(INDIRECT("beschriftung!"&ADDRESS(beschriftung!$C$1*12+ROW(beschriftung!$A7)-1,COLUMN(beschriftung!G$1)))="","",INDIRECT("beschriftung!"&ADDRESS(beschriftung!$C$1*12+ROW(beschriftung!$A7)-1,COLUMN(beschriftung!G$1)))) -> Final consumption expenditure | M6: =IF(INDIRECT("beschriftung!"&ADDRESS(beschriftung!$C$1*12+ROW(beschriftung!$A7)-1,COLUMN(beschriftung!M$1)))="","",INDIRECT("beschriftung!"&ADDRESS(beschriftung!$C$1*12+ROW(beschriftung!$A7)-1,COLUMN(beschriftung!M$1)))) -> Gross capital formation | AA6: =IF(INDIRECT("beschriftung!"&ADDRESS(beschriftung!$C$1*12+ROW(beschriftung!$A7)-1,COLUMN(beschriftung!AA$1)))="","",INDIRECT("beschriftung!"&ADDRESS(beschriftung!$C$1*12+ROW(beschriftung!$A7)-1,COLUMN(beschriftung!AA$1)))) -> Exports of goods and services | AK6: =IF(INDIRECT("beschriftung!"&ADDRESS(beschriftung!$C$1*12+ROW(beschriftung!$A7)-1,COLUMN(beschriftung!AK$1)))="","",INDIRECT("beschriftung!"&ADDRESS(beschriftung!$C$1*12+ROW(beschriftung!$A7)-1,COLUMN(beschriftung!AK$1)))) -> Imports of goods and services | AW6: =IF(INDIRECT("beschriftung!"&ADDRESS(beschriftung!$C$1*12+ROW(beschriftung!$A7)-1,COLUMN(beschriftung!AW$1)))="","",INDIRECT("beschriftung!"&ADDRESS(beschriftung!$C$1*12+ROW(beschriftung!$A7)-1,COLUMN(beschriftung!AW$1)))) -> Final domestic demand | AY6: =IF(INDIRECT("beschriftung!"&ADDRESS(beschriftung!$C$1*12+ROW(beschriftung!$A7)-1,COLUMN(beschriftung!AY$1)))="","",INDIRECT("beschriftung!"&ADDRESS(beschriftung!$C$1*12+ROW(beschriftung!$A7)-1,COLUMN(beschriftung!AY$1)))) -> Exports of goods and services (excluding valuables) | BC6: =IF(INDIRECT("beschriftung!"&ADDRESS(beschriftung!$C$1*12+ROW(beschriftung!$A7)-1,COLUMN(beschriftung!BC$1)))="","",INDIRECT("beschriftung!"&ADDRESS(beschriftung!$C$1*12+ROW(beschriftung!$A7)-1,COLUMN(beschriftung!BC$1)))) -> Imports of goods and services (excluding valuables)
I7: =IF(INDIRECT("beschriftung!"&ADDRESS(beschriftung!$C$1*12+ROW(beschriftung!$A8)-1,COLUMN(beschriftung!I$1)))="","",INDIRECT("beschriftung!"&ADDRESS(beschriftung!$C$1*12+ROW(beschriftung!$A8)-1,COLUMN(beschriftung!I$1)))) -> Households and NPISH | K7: =IF(INDIRECT("beschriftung!"&ADDRESS(beschriftung!$C$1*12+ROW(beschriftung!$A8)-1,COLUMN(beschriftung!K$1)))="","",INDIRECT("beschriftung!"&ADDRESS(beschriftung!$C$1*12+ROW(beschriftung!$A8)-1,COLUMN(beschriftung!K$1)))) -> General government | O7: =IF(INDIRECT("beschriftung!"&ADDRESS(beschriftung!$C$1*12+ROW(beschriftung!$A8)-1,COLUMN(beschriftung!O$1)))="","",INDIRECT("beschriftung!"&ADDRESS(beschriftung!$C$1*12+ROW(beschriftung!$A8)-1,COLUMN(beschriftung!O$1)))) -> Gross fixed capital formation | U7: =IF(INDIRECT("beschriftung!"&ADDRESS(beschriftung!$C$1*12+ROW(beschriftung!$A8)-1,COLUMN(beschriftung!U$1)))="","",INDIRECT("beschriftung!"&ADDRESS(beschriftung!$C$1*12+ROW(beschriftung!$A8)-1,COLUMN(beschriftung!U$1)))) -> Changes in inventories and statistical discrepancies | W7: =IF(INDIRECT("beschriftung!"&ADDRESS(beschriftung!$C$1*12+ROW(beschriftung!$A8)-1,COLUMN(beschriftung!W$1)))="","",INDIRECT("beschriftung!"&ADDRESS(beschriftung!$C$1*12+ROW(beschriftung!$A8)-1,COLUMN(beschriftung!W$1)))) -> Acquisitions less disposals of valuables | AC7: =IF(INDIRECT("beschriftung!"&ADDRESS(beschriftung!$C$1*12+ROW(beschriftung!$A8)-1,COLUMN(beschriftung!AC$1)))="","",INDIRECT("beschriftung!"&ADDRESS(beschriftung!$C$1*12+ROW(beschriftung!$A8)-1,COLUMN(beschriftung!AC$1)))) -> Exports (exp.) of goods | AI7: =IF(INDIRECT("beschriftung!"&ADDRESS(beschriftung!$C$1*12+ROW(beschriftung!$A8)-1,COLUMN(beschriftung!AI$1)))="","",INDIRECT("beschriftung!"&ADDRESS(beschriftung!$C$1*12+ROW(beschriftung!$A8)-1,COLUMN(beschriftung!AI$1)))) -> Exports of services | AM7: =IF(INDIRECT("beschriftung!"&ADDRESS(beschriftung!$C$1*12+ROW(beschriftung!$A8)-1,COLUMN(beschriftung!AM$1)))="","",INDIRECT("beschriftung!"&ADDRESS(beschriftung!$C$1*12+ROW(beschriftung!$A8)-1,COLUMN(beschriftung!AM$1)))) -> Imports (imp.) of goods | AS7: =IF(INDIRECT("beschriftung!"&ADDRESS(beschriftung!$C$1*12+ROW(beschriftung!$A8)-1,COLUMN(beschriftung!AS$1)))="","",INDIRECT("beschriftung!"&ADDRESS(beschriftung!$C$1*12+ROW(beschriftung!$A8)-1,COLUMN(beschriftung!AS$1)))) -> Imports of services | BA7: =IF(INDIRECT("beschriftung!"&ADDRESS(beschriftung!$C$1*12+ROW(beschriftung!$A8)-1,COLUMN(beschriftung!BA$1)))="","",INDIRECT("beschriftung!"&ADDRESS(beschriftung!$C$1*12+ROW(beschriftung!$A8)-1,COLUMN(beschriftung!BA$1)))) -> thereof exports of goods excluding valuables
Q8: =IF(INDIRECT("beschriftung!"&ADDRESS(beschriftung!$C$1*12+ROW(beschriftung!$A9)-1,COLUMN(beschriftung!Q$1)))="","",INDIRECT("beschriftung!"&ADDRESS(beschriftung!$C$1*12+ROW(beschriftung!$A9)-1,COLUMN(beschriftung!Q$1)))) -> Construction | S8: =IF(INDIRECT("beschriftung!"&ADDRESS(beschriftung!$C$1*12+ROW(beschriftung!$A9)-1,COLUMN(beschriftung!S$1)))="","",INDIRECT("beschriftung!"&ADDRESS(beschriftung!$C$1*12+ROW(beschriftung!$A9)-1,COLUMN(beschriftung!S$1)))) -> Fixed assets and software | AE8: =IF(INDIRECT("beschriftung!"&ADDRESS(beschriftung!$C$1*12+ROW(beschriftung!$A9)-1,COLUMN(beschriftung!AE$1)))="","",INDIRECT("beschriftung!"&ADDRESS(beschriftung!$C$1*12+ROW(beschriftung!$A9)-1,COLUMN(beschriftung!AE$1)))) -> thereof exp. of goods excluding non-monetary gold | AG8: =IF(INDIRECT("beschriftung!"&ADDRESS(beschriftung!$C$1*12+ROW(beschriftung!$A9)-1,COLUMN(beschriftung!AG$1)))="","",INDIRECT("beschriftung!"&ADDRESS(beschriftung!$C$1*12+ROW(beschriftung!$A9)-1,COLUMN(beschriftung!AG$1)))) -> thereof exp. of goods excluding valuables and merchanting | AO8: =IF(INDIRECT("beschriftung!"&ADDRESS(beschriftung!$C$1*12+ROW(beschriftung!$A9)-1,COLUMN(beschriftung!AO$1)))="","",INDIRECT("beschriftung!"&ADDRESS(beschriftung!$C$1*12+ROW(beschriftung!$A9)-1,COLUMN(beschriftung!AO$1)))) -> thereof imp. of goods excluding non-monetary gold | AQ8: =IF(INDIRECT("beschriftung!"&ADDRESS(beschriftung!$C$1*12+ROW(beschriftung!$A9)-1,COLUMN(beschriftung!AQ$1)))="","",INDIRECT("beschriftung!"&ADDRESS(beschriftung!$C$1*12+ROW(beschriftung!$A9)-1,COLUMN(beschriftung!AQ$1)))) -> thereof imp. of goods excluding valuables
C11: B.1*b | E11: P.3+P.5 | G11: P.3 | I11: S.14+S15 | K11: S.13 | M11: P.5 | O11: P.51 | Q11: P.5111c | S11: P.5111be | U11: P.52 | W11: P.53 | AA11: P.6 | AC11: P.61 | AI11: P.62 | AK11: P.7 | AM11: P.71 | AS11: P.72 | AW11: P.3+P.51
A12: 1980 | C12: 363293.71 | E12: 347055.75 | G12: 240457.51 | I12: 201286.45 | K12: 38538.441 | M12: 106816.31 | O12: 82585.72 | Q12: 41646.019 | S12: 43814.773 | AA12: 106564.86 | AC12: 68806.19 | AE12: 55070.547 | AG12: 53122.207 | AI12: 39399.863 | AK12: 92917.558 | AM12: 72223.068 | AO12: 54211.882 | AQ12: 52158.444 | AS12: 21039.587 | AU12: 411194.85 | AW12: 322208.66 | AY12: 93728.413 | BA12: 54995.743 | BC12: 73972.582
A13: 1981 | C13: 369219.98 | D13: 0.016312611 | E13: 341055.45 | F13: -0.017289156 | G13: 243230.9 | H13: 0.01153381 | I13: 203243.27 | J13: 0.0097215897 | K13: 39416.627 | L13: 0.022787252 | M13: 98837.717 | N13: -0.07469456 | O13: 83599.401 | P13: 0.012274293 | Q13: 43155.041 | R13: 0.036234478 | S13: 43604.917 | T13: -0.0047896193 | AA13: 122624.17 | AB13: 0.15069983 | AC13: 80824.449 | AD13: 0.17466828 | AE13: 60094.999 | AF13: 0.091236635 | AG13: 55242.925 | AH13: 0.039921494 | AI13: 42421.676 | AJ13: 0.07669602 | AK13: 99770.386 | AL13: 0.073751698 | AM13: 77748.223 | AN13: 0.076501246 | AO13: 53904.632 | AP13: -0.0056675705 | AQ13: 51849.116 | AR13: -0.0059305578 | AS13: 22304.546 | AT13: 0.060122807 | AU13: 420367.89 | AV13: 0.022308268 | AW13: 325998.94 | AX13: 0.011763451 | AY13: 98733.9 | AZ13: 0.053404158 | BA13: 57276.323 | BB13: 0.041468298 | BC13: 74666.399 | BD13: 0.0093793866
A14: 1982 | C14: 364271.53 | D14: -0.013402434 | E14: 343230.42 | F14: 0.0063771898 | G14: 244108.42 | H14: 0.0036077714 | I14: 203884.79 | J14: 0.0031564172 | K14: 39667.115 | L14: 0.0063548878 | M14: 100059.92 | N14: 0.012365776 | O14: 80130.569 | P14: -0.041493501 | Q14: 41735.289 | R14: -0.032898855 | S14: 41515.469 | T14: -0.047917716 | AA14: 120226.8 | AB14: -0.019550491 | AC14: 78309.174 | AD14: -0.031120223 | AE14: 59798.154 | AF14: -0.004939599 | AG14: 53300.367 | AH14: -0.035163915 | AI14: 43099.471 | AJ14: 0.015977575 | AK14: 101924.26 | AL14: 0.021588362 | AM14: 78773.358 | AN14: 0.013185316 | AO14: 53395.907 | AP14: -0.009437501 | AQ14: 50047.62 | AR14: -0.034744975 | AS14: 23658.987 | AT14: 0.060724873 | AU14: 415047.44 | AV14: -0.012656667 | AW14: 322583.99 | AX14: -0.010475345 | AY14: 96861.732 | AZ14: -0.018961751 | BA14: 55130.479 | BB14: -0.037464762 | BC14: 73789.5 | BD14: -0.01174423
A15: 1983 | C15: 366474.18 | D15: 0.0060467182 | E15: 351305.42 | F15: 0.023526462 | G15: 247626.33 | H15: 0.014411246 | I15: 206423.82 | J15: 0.012453278 | K15: 40700.618 | L15: 0.026054413 | M15: 104424.48 | N15: 0.043619444 | O15: 82900.762 | P15: 0.034570982 | Q15: 43870.686 | R15: 0.051165241 | S15: 42429.079 | T15: 0.02200649 | AA15: 116947.12 | AB15: -0.027279177 | AC15: 73821.86 | AD15: -0.057302538 | AE15: 60446.07 | AF15: 0.010835056 | AG15: 54046.968 | AH15: 0.014007428 | AI15: 45217.883 | AJ15: 0.049151688 | AK15: 103141.74 | AL15: 0.011944871 | AM15: 79391.941 | AN15: 0.0078526889 | AO15: 56748.244 | AP15: 0.06278265 | AQ15: 52632.695 | AR15: 0.051652311 | AS15: 24348.132 | AT15: 0.029128258 | AU15: 424173.94 | AV15: 0.021989064 | AW15: 329183.1 | AX15: 0.020457034 | AY15: 99419.065 | AZ15: 0.026401892 | BA15: 55852.279 | BB15: 0.013092584 | BC15: 77170.25 | BD15: 0.045816148
A16: 1984 | C16: 377715.11 | D16: 0.030673181 | E16: 347081.54 | F16: -0.012023379 | G16: 251614.18 | H16: 0.016104282 | I16: 209762.8 | J16: 0.016175354 | K16: 41339.092 | L16: 0.015687078 | M16: 96680.598 | N16: -0.07415773 | O16: 86518.453 | P16: 0.043638815 | Q16: 46417.734 | R16: 0.058058104 | S16: 43816.571 | T16: 0.032701441 | AA16: 135346.69 | AB16: 0.15733242 | AC16: 88002.054 | AD16: 0.19208666 | AE16: 65623.772 | AF16: 0.08565821 | AG16: 57430.965 | AH16: 0.062612139 | AI16: 48619.611 | AJ16: 0.075229713 | AK16: 108983.54 | AL16: 0.056638619 | AM16: 84140.858 | AN16: 0.059816116 | AO16: 62309.32 | AP16: 0.097995564 | AQ16: 56632.181 | AR16: 0.075988627 | AS16: 25400.488 | AT16: 0.043221249 | AU16: 439314.5 | AV16: 0.035694225 | AW16: 337214.29 | AX16: 0.02439733 | AY16: 106248.21 | AZ16: 0.068690456 | BA16: 59468.418 | BB16: 0.064744687 | BC16: 82381.994 | BD16: 0.067535658
A17: 1985 | C17: 391739.18 | D17: 0.037128699 | E17: 356521.25 | F17: 0.027197377 | G17: 258073.05 | H17: 0.025669739 | I17: 214235.65 | J17: 0.021323369 | K17: 43454.93 | L17: 0.05118251 | M17: 99656.968 | N17: 0.030785596 | O17: 89649.126 | P17: 0.036185034 | Q17: 46967.278 | R17: 0.011839078 | S17: 46209.468 | T17: 0.054611687 | AA17: 146178.41 | AB17: 0.080029468 | AC17: 94780.227 | AD17: 0.077022896 | AE17: 70757.566 | AF17: 0.078230706 | AG17: 62143.903 | AH17: 0.08206267 | AI17: 52890.42 | AJ17: 0.08784127 | AK17: 115638.35 | AL17: 0.061062481 | AM17: 89238.246 | AN17: 0.060581599 | AO17: 64594.457 | AP17: 0.036674083 | AQ17: 59316.31 | AR17: 0.047395817 | AS17: 27002.367 | AT17: 0.063064866 | AU17: 458569.55 | AV17: 0.043829768 | AW17: 346947.89 | AX17: 0.028864728 | AY17: 115324.45 | AZ17: 0.085424889 | BA17: 64462.9 | BB17: 0.083985455 | BC17: 86612.394 | BD17: 0.051351028
A18: 1986 | C18: 398932.61 | D18: 0.018362826 | E18: 379587.3 | F18: 0.064697533 | G18: 265421.44 | H18: 0.028474066 | I18: 220200.38 | J18: 0.027841887 | K18: 44849.971 | L18: 0.032103162 | M18: 114281.12 | N18: 0.14674491 | O18: 95925.223 | P18: 0.070007341 | Q18: 47777.399 | R18: 0.017248625 | S18: 51169.18 | T18: 0.10733108 | AA18: 148279.91 | AB18: 0.014376276 | AC18: 97374.341 | AD18: 0.027369776 | AE18: 72509.719 | AF18: 0.024762761 | AG18: 63366.147 | AH18: 0.019667959 | AI18: 51942.119 | AJ18: -0.017929539 | AK18: 128825.81 | AL18: 0.11404057 | AM18: 101519.06 | AN18: 0.1376183 | AO18: 70531.359 | AP18: 0.091910384 | AQ18: 64194.862 | AR18: 0.082246386 | AS18: 27527.735 | AT18: 0.019456397 | AU18: 472708.87 | AV18: 0.030833525 | AW18: 361269.81 | AX18: 0.04127975 | AY18: 115688.97 | AZ18: 0.0031608403 | BA18: 65470.529 | BB18: 0.015631154 | BC18: 92352.888 | BD18: 0.066277969
A19: 1987 | C19: 405085.34 | D19: 0.015422961 | E19: 387435.5 | F19: 0.020675609 | G19: 273113.02 | H19: 0.02897876 | I19: 226813.19 | J19: 0.030030882 | K19: 45884.619 | L19: 0.02306908 | M19: 114645.35 | N19: 0.00318715 | O19: 99921.613 | P19: 0.041661513 | Q19: 49571.195 | R19: 0.037544866 | S19: 53443.098 | T19: 0.044439212 | AA19: 144634.52 | AB19: -0.024584581 | AC19: 92923.657 | AD19: -0.045706951 | AE19: 73246.121 | AF19: 0.01015591 | AG19: 63229.457 | AH19: -0.0021571415 | AI19: 53309.002 | AJ19: 0.026315506 | AK19: 127118.54 | AL19: -0.013252524 | AM19: 98446.961 | AN19: -0.030261318 | AO19: 74790.931 | AP19: 0.060392596 | AQ19: 67756.546 | AR19: 0.055482392 | AS19: 29106.547 | AT19: 0.057353478 | AU19: 485664.54 | AV19: 0.027407296 | AW19: 373181.46 | AX19: 0.0329716 | AY19: 117061.37 | AZ19: 0.01186288 | BA19: 65699.426 | BB19: 0.0034961826 | BC19: 97520.688 | BD19: 0.05595711
A20: 1988 | C20: 418383.89 | D20: 0.03282902 | E20: 397033.53 | F20: 0.024773246 | G20: 280018.74 | H20: 0.025285227 | I20: 231728.98 | J20: 0.021673292 | K20: 47979.931 | L20: 0.0456648 | M20: 117360.32 | N20: 0.023681411 | O20: 108152.26 | P20: 0.082371077 | Q20: 53121.588 | R20: 0.071622111 | S20: 58239.993 | T20: 0.08975707 | AA20: 155734.37 | AB20: 0.076744179 | AC20: 102927.05 | AD20: 0.10765171 | AE20: 78659.949 | AF20: 0.073912833 | AG20: 67784.382 | AH20: 0.072038017 | AI20: 53765.938 | AJ20: 0.0085714508 | AK20: 134516.13 | AL20: 0.058194375 | AM20: 103822.75 | AN20: 0.054605954 | AO20: 78306.796 | AP20: 0.047009244 | AQ20: 71280.183 | AR20: 0.052004369 | AS20: 31191.357 | AT20: 0.071626849 | AU20: 507211.53 | AV20: 0.044365983 | AW20: 389381.26 | AX20: 0.043409989 | AY20: 122575.47 | AZ20: 0.047104288 | BA20: 70303.124 | BB20: 0.070072121 | BC20: 103087.91 | BD20: 0.057087637
A21: 1989 | C21: 436922.56 | D21: 0.044310183 | E21: 416514.18 | F21: 0.049065498 | G21: 289817.66 | H21: 0.034993798 | I21: 237588.46 | J21: 0.025285939 | K21: 52185.387 | L21: 0.087650322 | M21: 126477.89 | N21: 0.077688772 | O21: 113208.75 | P21: 0.046753434 | Q21: 56890.823 | R21: 0.070954858 | S21: 60002.077 | T21: 0.030255555 | AA21: 164976.19 | AB21: 0.059343488 | AC21: 109587.74 | AD21: 0.064712783 | AE21: 83365.183 | AF21: 0.059817404 | AG21: 71111.798 | AH21: 0.04908824 | AI21: 56277.827 | AJ21: 0.046718969 | AK21: 144092.81 | AL21: 0.071193527 | AM21: 112903.98 | AN21: 0.087468599 | AO21: 83287.348 | AP21: 0.063603065 | AQ21: 75577.916 | AR21: 0.06029352 | AS21: 31543.846 | AT21: 0.011300838 | AU21: 528417.03 | AV21: 0.041808017 | AW21: 404530.38 | AX21: 0.038905617 | AY21: 128718.02 | AZ21: 0.050112407 | BA21: 73963.032 | BB21: 0.052058959 | BC21: 107982.67 | BD21: 0.047481338
A22: 1990 | C22: 453143.87 | D22: 0.037126278 | E22: 439189.95 | F22: 0.054441788 | G22: 295837.55 | H22: 0.020771305 | I22: 241327.13 | J22: 0.015735915 | K22: 54610.699 | L22: 0.046474922 | M22: 141729.94 | N22: 0.12059061 | O22: 118284.67 | P22: 0.044836779 | Q22: 57467.246 | R22: 0.010132094 | S22: 64163.91 | T22: 0.069361487 | AA22: 168223.07 | AB22: 0.019680878 | AC22: 114426.36 | AD22: 0.044152884 | AE22: 87854.999 | AF22: 0.053857208 | AG22: 74266.65 | AH22: 0.044364682 | AI22: 53890.048 | AJ22: -0.042428404 | AK22: 152511.03 | AL22: 0.058422204 | AM22: 120787.43 | AN22: 0.069824336 | AO22: 86584.208 | AP22: 0.039584166 | AQ22: 77931.966 | AR22: 0.031147336 | AS22: 31993.645 | AT22: 0.014259497 | AU22: 541465.44 | AV22: 0.024693393 | AW22: 416229.71 | AX22: 0.028920777 | AY22: 130382.04 | AZ22: 0.012927657 | BA22: 77184.345 | BB22: 0.043553016 | BC22: 110882.62 | BD22: 0.026855723
A23: 1991 | C23: 448933.82 | D23: -0.0092907487 | E23: 431664.38 | F23: -0.017135133 | G23: 301937.69 | H23: 0.020619889 | I23: 245681.29 | J23: 0.018042543 | K23: 56435.522 | L23: 0.033415119 | M23: 129382.42 | N23: -0.087120061 | O23: 116053.14 | P23: -0.018865723 | Q23: 55513.249 | R23: -0.034001924 | S23: 63638.672 | T23: -0.0081858856 | AA23: 165613.75 | AB23: -0.015511075 | AC23: 110856.95 | AD23: -0.031193955 | AE23: 85716.162 | AF23: -0.024345085 | AG23: 73675.667 | AH23: -0.0079575853 | AI23: 55245.445 | AJ23: 0.025151144 | AK23: 147240.06 | AL23: -0.034561236 | AM23: 115687.86 | AN23: -0.042219356 | AO23: 84993.341 | AP23: -0.018373637 | AQ23: 76872.187 | AR23: -0.01359877 | AS23: 31837.323 | AT23: -0.0048860407 | AU23: 544765.39 | AV23: 0.0060944638 | AW23: 419281.01 | AX23: 0.0073308116 | AY23: 130710.61 | AZ23: 0.0025200509 | BA23: 76476.734 | BB23: -0.0091678029 | BC23: 109619.92 | BD23: -0.011387698
A24: 1992 | C24: 448283.12 | D24: -0.0014494306 | E24: 426605.37 | F24: -0.011719761 | G24: 303250.23 | H24: 0.0043470639 | I24: 246809.28 | J24: 0.0045912579 | K24: 56614.228 | L24: 0.0031665503 | M24: 123482.96 | N24: -0.045597037 | O24: 106438.25 | P24: -0.08284903 | Q24: 54832.47 | R24: -0.01226337 | S24: 55308.521 | T24: -0.13089762 | AA24: 171825.22 | AB24: 0.037505789 | AC24: 115625.09 | AD24: 0.043011657 | AE24: 88482.921 | AF24: 0.032278148 | AG24: 76497.496 | AH24: 0.038300698 | AI24: 56591.128 | AJ24: 0.024358268 | AK24: 149097.85 | AL24: 0.012617443 | AM24: 115023.03 | AN24: -0.0057467545 | AO24: 81073.573 | AP24: -0.046118536 | AQ24: 73409.293 | AR24: -0.045047429 | AS24: 34300.517 | AT24: 0.077368135 | AU24: 539243.91 | AV24: -0.010135519 | AW24: 409392.12 | AX24: -0.023585345 | AY24: 134551.4 | AZ24: 0.029383948 | BA24: 78932.049 | BB24: 0.03210538 | BC24: 108242.44 | BD24: -0.012565993
... A56: 2024 | C56: 779476.78 | D56: 0.0095937404 | E56: 673604.91 | F56: 0.02127363 | G56: 479390.85 | H56: 0.01573304 | I56: 393816.42 | J56: 0.018086827 | K56: 85669.158 | L56: 0.0054227773 | M56: 194671.93 | N56: 0.034650365 | O56: 191774.64 | P56: -0.0074815663 | Q56: 58979.926 | R56: 0.022344105 | S56: 132862.54 | T56: -0.021330465 | AA56: 527978.44 | AB56: -0.012638991 | AC56: 381387.77 | AD56: -0.027577838 | AE56: 335467.37 | AF56: -0.0059675342 | AG56: 294616.54 | AH56: 0.067160724 | AI56: 145897.95 | AJ56: 0.030736771 | AK56: 420688.47 | AL56: -0.00011571829 | AM56: 265505.72 | AN56: -0.028902562 | AO56: 223832.12 | AP56: 0.020376011 | AQ56: 216097.75 | AR56: 0.027833106 | AS56: 156167.06 | AT56: 0.054870036 | AU56: 1142578.1 | AV56: 0.0092285206 | AW56: 671115.28 | AX56: 0.0089576756 | AY56: 473061.82 | AZ56: 0.0096220951 | BA56: 327234.04 | BB56: 0.0001402057 | BC56: 372264.87 | BD56: 0.039384294

Sheet defl_y
A1: =IF(INDIRECT("beschriftung!"&ADDRESS(beschriftung!$C$1*12+ROW(beschriftung!$A1)-1,COLUMN(beschriftung!B$1)))="","",INDIRECT("beschriftung!"&ADDRESS(beschriftung!$C$1*12+ROW(beschriftung!$A1)-1,COLUMN(beschriftung!B$1)))) -> ESA 2010, Annual aggregates of Gross Domestic Product, expenditure approach (SFSO, SECO), seasonally, calendar and sport event adjusted data
A2: =IF(INDIRECT("beschriftung!"&ADDRESS(beschriftung!$C$1*12+ROW(beschriftung!$A4)-1,COLUMN(beschriftung!B$1)))="","",INDIRECT("beschriftung!"&ADDRESS(beschriftung!$C$1*12+ROW(beschriftung!$A4)-1,COLUMN(beschriftung!B$1)))) -> Implicit chain price indexes, year-on-year growth rates
A3: =IF(INDIRECT("beschriftung!"&ADDRESS(beschriftung!$C$1*12+ROW(beschriftung!$A5)-1,COLUMN(beschriftung!B$1)))="","",INDIRECT("beschriftung!"&ADDRESS(beschriftung!$C$1*12+ROW(beschriftung!$A5)-1,COLUMN(beschriftung!B$1))))
C4: =IF(INDIRECT("beschriftung!"&ADDRESS(beschriftung!$C$1*12+ROW(beschriftung!$A5)-1,COLUMN(beschriftung!C$1)))="","",INDIRECT("beschriftung!"&ADDRESS(beschriftung!$C$1*12+ROW(beschriftung!$A5)-1,COLUMN(beschriftung!C$1)))) -> Gross domestic product
E5: =IF(INDIRECT("beschriftung!"&ADDRESS(beschriftung!$C$1*12+ROW(beschriftung!$A6)-1,COLUMN(beschriftung!E$1)))="","",INDIRECT("beschriftung!"&ADDRESS(beschriftung!$C$1*12+ROW(beschriftung!$A6)-1,COLUMN(beschriftung!E$1)))) -> Internal demand | Y5: =IF(INDIRECT("beschriftung!"&ADDRESS(beschriftung!$C$1*12+ROW(beschriftung!$A6)-1,COLUMN(beschriftung!Y$1)))="","",INDIRECT("beschriftung!"&ADDRESS(beschriftung!$C$1*12+ROW(beschriftung!$A6)-1,COLUMN(beschriftung!Y$1)))) -> Trade balance (goods and services) | AU5: =IF(INDIRECT("beschriftung!"&ADDRESS(beschriftung!$C$1*12+ROW(beschriftung!$A6)-1,COLUMN(beschriftung!AU$1)))="","",INDIRECT("beschriftung!"&ADDRESS(beschriftung!$C$1*12+ROW(beschriftung!$A6)-1,COLUMN(beschriftung!AU$1)))) -> Global demand excluding inventories change, stat. discrepancies and valuables
G6: =IF(INDIRECT("beschriftung!"&ADDRESS(beschriftung!$C$1*12+ROW(beschriftung!$A7)-1,COLUMN(beschriftung!G$1)))="","",INDIRECT("beschriftung!"&ADDRESS(beschriftung!$C$1*12+ROW(beschriftung!$A7)-1,COLUMN(beschriftung!G$1)))) -> Final consumption expenditure | M6: =IF(INDIRECT("beschriftung!"&ADDRESS(beschriftung!$C$1*12+ROW(beschriftung!$A7)-1,COLUMN(beschriftung!M$1)))="","",INDIRECT("beschriftung!"&ADDRESS(beschriftung!$C$1*12+ROW(beschriftung!$A7)-1,COLUMN(beschriftung!M$1)))) -> Gross capital formation | AA6: =IF(INDIRECT("beschriftung!"&ADDRESS(beschriftung!$C$1*12+ROW(beschriftung!$A7)-1,COLUMN(beschriftung!AA$1)))="","",INDIRECT("beschriftung!"&ADDRESS(beschriftung!$C$1*12+ROW(beschriftung!$A7)-1,COLUMN(beschriftung!AA$1)))) -> Exports of goods and services | AK6: =IF(INDIRECT("beschriftung!"&ADDRESS(beschriftung!$C$1*12+ROW(beschriftung!$A7)-1,COLUMN(beschriftung!AK$1)))="","",INDIRECT("beschriftung!"&ADDRESS(beschriftung!$C$1*12+ROW(beschriftung!$A7)-1,COLUMN(beschriftung!AK$1)))) -> Imports of goods and services | AW6: =IF(INDIRECT("beschriftung!"&ADDRESS(beschriftung!$C$1*12+ROW(beschriftung!$A7)-1,COLUMN(beschriftung!AW$1)))="","",INDIRECT("beschriftung!"&ADDRESS(beschriftung!$C$1*12+ROW(beschriftung!$A7)-1,COLUMN(beschriftung!AW$1)))) -> Final domestic demand | AY6: =IF(INDIRECT("beschriftung!"&ADDRESS(beschriftung!$C$1*12+ROW(beschriftung!$A7)-1,COLUMN(beschriftung!AY$1)))="","",INDIRECT("beschriftung!"&ADDRESS(beschriftung!$C$1*12+ROW(beschriftung!$A7)-1,COLUMN(beschriftung!AY$1)))) -> Exports of goods and services (excluding valuables) | BC6: =IF(INDIRECT("beschriftung!"&ADDRESS(beschriftung!$C$1*12+ROW(beschriftung!$A7)-1,COLUMN(beschriftung!BC$1)))="","",INDIRECT("beschriftung!"&ADDRESS(beschriftung!$C$1*12+ROW(beschriftung!$A7)-1,COLUMN(beschriftung!BC$1)))) -> Imports of goods and services (excluding valuables)
I7: =IF(INDIRECT("beschriftung!"&ADDRESS(beschriftung!$C$1*12+ROW(beschriftung!$A8)-1,COLUMN(beschriftung!I$1)))="","",INDIRECT("beschriftung!"&ADDRESS(beschriftung!$C$1*12+ROW(beschriftung!$A8)-1,COLUMN(beschriftung!I$1)))) -> Households and NPISH | K7: =IF(INDIRECT("beschriftung!"&ADDRESS(beschriftung!$C$1*12+ROW(beschriftung!$A8)-1,COLUMN(beschriftung!K$1)))="","",INDIRECT("beschriftung!"&ADDRESS(beschriftung!$C$1*12+ROW(beschriftung!$A8)-1,COLUMN(beschriftung!K$1)))) -> General government | O7: =IF(INDIRECT("beschriftung!"&ADDRESS(beschriftung!$C$1*12+ROW(beschriftung!$A8)-1,COLUMN(beschriftung!O$1)))="","",INDIRECT("beschriftung!"&ADDRESS(beschriftung!$C$1*12+ROW(beschriftung!$A8)-1,COLUMN(beschriftung!O$1)))) -> Gross fixed capital formation | U7: =IF(INDIRECT("beschriftung!"&ADDRESS(beschriftung!$C$1*12+ROW(beschriftung!$A8)-1,COLUMN(beschriftung!U$1)))="","",INDIRECT("beschriftung!"&ADDRESS(beschriftung!$C$1*12+ROW(beschriftung!$A8)-1,COLUMN(beschriftung!U$1)))) -> Changes in inventories and statistical discrepancies | W7: =IF(INDIRECT("beschriftung!"&ADDRESS(beschriftung!$C$1*12+ROW(beschriftung!$A8)-1,COLUMN(beschriftung!W$1)))="","",INDIRECT("beschriftung!"&ADDRESS(beschriftung!$C$1*12+ROW(beschriftung!$A8)-1,COLUMN(beschriftung!W$1)))) -> Acquisitions less disposals of valuables | AC7: =IF(INDIRECT("beschriftung!"&ADDRESS(beschriftung!$C$1*12+ROW(beschriftung!$A8)-1,COLUMN(beschriftung!AC$1)))="","",INDIRECT("beschriftung!"&ADDRESS(beschriftung!$C$1*12+ROW(beschriftung!$A8)-1,COLUMN(beschriftung!AC$1)))) -> Exports (exp.) of goods | AI7: =IF(INDIRECT("beschriftung!"&ADDRESS(beschriftung!$C$1*12+ROW(beschriftung!$A8)-1,COLUMN(beschriftung!AI$1)))="","",INDIRECT("beschriftung!"&ADDRESS(beschriftung!$C$1*12+ROW(beschriftung!$A8)-1,COLUMN(beschriftung!AI$1)))) -> Exports of services | AM7: =IF(INDIRECT("beschriftung!"&ADDRESS(beschriftung!$C$1*12+ROW(beschriftung!$A8)-1,COLUMN(beschriftung!AM$1)))="","",INDIRECT("beschriftung!"&ADDRESS(beschriftung!$C$1*12+ROW(beschriftung!$A8)-1,COLUMN(beschriftung!AM$1)))) -> Imports (imp.) of goods | AS7: =IF(INDIRECT("beschriftung!"&ADDRESS(beschriftung!$C$1*12+ROW(beschriftung!$A8)-1,COLUMN(beschriftung!AS$1)))="","",INDIRECT("beschriftung!"&ADDRESS(beschriftung!$C$1*12+ROW(beschriftung!$A8)-1,COLUMN(beschriftung!AS$1)))) -> Imports of services | BA7: =IF(INDIRECT("beschriftung!"&ADDRESS(beschriftung!$C$1*12+ROW(beschriftung!$A8)-1,COLUMN(beschriftung!BA$1)))="","",INDIRECT("beschriftung!"&ADDRESS(beschriftung!$C$1*12+ROW(beschriftung!$A8)-1,COLUMN(beschriftung!BA$1)))) -> thereof exports of goods excluding valuables
Q8: =IF(INDIRECT("beschriftung!"&ADDRESS(beschriftung!$C$1*12+ROW(beschriftung!$A9)-1,COLUMN(beschriftung!Q$1)))="","",INDIRECT("beschriftung!"&ADDRESS(beschriftung!$C$1*12+ROW(beschriftung!$A9)-1,COLUMN(beschriftung!Q$1)))) -> Construction | S8: =IF(INDIRECT("beschriftung!"&ADDRESS(beschriftung!$C$1*12+ROW(beschriftung!$A9)-1,COLUMN(beschriftung!S$1)))="","",INDIRECT("beschriftung!"&ADDRESS(beschriftung!$C$1*12+ROW(beschriftung!$A9)-1,COLUMN(beschriftung!S$1)))) -> Fixed assets and software | AE8: =IF(INDIRECT("beschriftung!"&ADDRESS(beschriftung!$C$1*12+ROW(beschriftung!$A9)-1,COLUMN(beschriftung!AE$1)))="","",INDIRECT("beschriftung!"&ADDRESS(beschriftung!$C$1*12+ROW(beschriftung!$A9)-1,COLUMN(beschriftung!AE$1)))) -> thereof exp. of goods excluding non-monetary gold | AG8: =IF(INDIRECT("beschriftung!"&ADDRESS(beschriftung!$C$1*12+ROW(beschriftung!$A9)-1,COLUMN(beschriftung!AG$1)))="","",INDIRECT("beschriftung!"&ADDRESS(beschriftung!$C$1*12+ROW(beschriftung!$A9)-1,COLUMN(beschriftung!AG$1)))) -> thereof exp. of goods excluding valuables and merchanting | AO8: =IF(INDIRECT("beschriftung!"&ADDRESS(beschriftung!$C$1*12+ROW(beschriftung!$A9)-1,COLUMN(beschriftung!AO$1)))="","",INDIRECT("beschriftung!"&ADDRESS(beschriftung!$C$1*12+ROW(beschriftung!$A9)-1,COLUMN(beschriftung!AO$1)))) -> thereof imp. of goods excluding non-monetary gold | AQ8: =IF(INDIRECT("beschriftung!"&ADDRESS(beschriftung!$C$1*12+ROW(beschriftung!$A9)-1,COLUMN(beschriftung!AQ$1)))="","",INDIRECT("beschriftung!"&ADDRESS(beschriftung!$C$1*12+ROW(beschriftung!$A9)-1,COLUMN(beschriftung!AQ$1)))) -> thereof imp. of goods excluding valuables
C11: B.1*b | E11: P.3+P.5 | G11: P.3 | I11: S.14+S15 | K11: S.13 | M11: P.5 | O11: P.51 | Q11: P.5111c | S11: P.5111be | U11: P.52 | W11: P.53 | AA11: P.6 | AC11: P.61 | AI11: P.62 | AK11: P.7 | AM11: P.71 | AS11: P.72 | AW11: P.3+P.51
A12: 1980 | C12: 56.487753 | E12: 60.469743 | G12: 58.10341 | I12: 59.783234 | K12: 50.283477 | M12: 65.673213 | O12: 76.05003 | Q12: 62.729298 | S12: 83.721098 | AA12: 89.253121 | AC12: 104.41452 | AE12: 90.640199 | AG12: 84.100007 | AI12: 59.058101 | AK12: 107.36371 | AM12: 114.93898 | AO12: 112.12572 | AQ12: 106.42057 | AS12: 79.598865 | AU12: 65.953278 | AW12: 62.853829 | AY12: 73.271275 | BA12: 82.564922 | BC12: 97.677522
A13: 1981 | C13: 59.652083 | D13: 0.056017982 | E13: 64.276649 | F13: 0.062955548 | G13: 61.628075 | H13: 0.060661935 | I13: 63.345516 | J13: 0.059586649 | K13: 53.665237 | L13: 0.067253898 | M13: 70.135664 | N13: 0.067949331 | O13: 81.409857 | P13: 0.070477638 | Q13: 67.457722 | R13: 0.075378233 | S13: 89.317324 | T13: 0.066843676 | AA13: 86.667697 | AB13: -0.028967325 | AC13: 99.188549 | AD13: -0.050050241 | AE13: 90.684914 | AF13: 0.00049332472 | AG13: 87.64981 | AH13: 0.042209312 | AI13: 61.54152 | AJ13: 0.042050443 | AK13: 105.48937 | AL13: -0.017457828 | AM13: 111.44147 | AN13: -0.030429286 | AO13: 115.53339 | AP13: 0.030391557 | AQ13: 113.04767 | AR13: 0.062272732 | AS13: 83.406248 | AT13: 0.047832123 | AU13: 69.786845 | AV13: 0.058125494 | AW13: 66.858093 | AX13: 0.063707557 | AY13: 76.371756 | AZ13: 0.042315102 | BA13: 86.070242 | BB13: 0.042455314 | BC13: 103.4168 | BD13: 0.058757404
A14: 1982 | C14: 64.034566 | D14: 0.073467384 | E14: 67.596346 | F14: 0.051647022 | G14: 65.383155 | H14: 0.060931318 | I14: 67.013111 | J14: 0.05789825 | K14: 57.922665 | L14: 0.079333068 | M14: 72.362076 | N14: 0.031744356 | O14: 85.320775 | P14: 0.048039859 | Q14: 70.587142 | R14: 0.046390849 | S14: 93.719943 | T14: 0.049291883 | AA14: 86.154542 | AB14: -0.0059209563 | AC14: 94.966997 | AD14: -0.04256088 | AE14: 90.626161 | AF14: -0.00064788276 | AG14: 92.201601 | AH14: 0.051931559 | AI14: 67.780371 | AJ14: 0.10137629 | AK14: 100.40042 | AL14: -0.048241353 | AM14: 104.92074 | AN14: -0.058512656 | AO14: 111.65787 | AP14: -0.033544621 | AQ14: 112.45467 | AR14: -0.0052455702 | AS14: 83.193764 | AT14: -0.0025475809 | AU14: 73.996596 | AV14: 0.06032299 | AW14: 70.671149 | AX14: 0.057032073 | AY14: 81.711489 | AZ14: 0.06991763 | BA14: 90.574547 | BB14: 0.052332905 | BC14: 102.94647 | BD14: -0.0045479014
A15: 1983 | C15: 65.594728 | D15: 0.024364382 | E15: 69.157137 | F15: 0.02308986 | G15: 67.538558 | H15: 0.032965722 | I15: 69.226411 | J15: 0.033027865 | K15: 59.811007 | L15: 0.032601085 | M15: 72.501694 | N15: 0.0019294361 | O15: 86.949221 | P15: 0.01908616 | Q15: 70.871361 | R15: 0.0040264927 | S15: 96.607834 | T15: 0.030814048 | AA15: 88.654746 | AB15: 0.029019992 | AC15: 98.675536 | AD15: 0.039050822 | AE15: 91.452953 | AF15: 0.0091231038 | AG15: 93.129768 | AH15: 0.010066712 | AI15: 68.192164 | AJ15: 0.0060753984 | AK15: 103.00796 | AL15: 0.025971426 | AM15: 108.1988 | AN15: 0.031243197 | AO15: 110.68269 | AP15: -0.0087336847 | AQ15: 111.17713 | AR15: -0.011360506 | AS15: 83.550872 | AT15: 0.0042924938 | AU15: 75.738335 | AV15: 0.023538094 | AW15: 72.702644 | AX15: 0.028745752 | AY15: 82.416246 | AZ15: 0.0086249469 | BA15: 91.495654 | BB15: 0.010169598 | BC15: 102.18782 | BD15: -0.0073694061
A16: 1984 | C16: 68.055661 | D16: 0.037517236 | E16: 71.969426 | F16: 0.040665203 | G16: 69.631388 | H16: 0.030987179 | I16: 71.366105 | J16: 0.030908639 | K16: 61.69197 | L16: 0.031448443 | M16: 77.151107 | N16: 0.06412834 | O16: 88.383558 | P16: 0.016496267 | Q16: 70.97036 | R16: 0.0013968757 | S16: 99.335144 | T16: 0.028230735 | AA16: 89.864075 | AB16: 0.013640887 | AC16: 99.799913 | AD16: 0.011394685 | AE16: 95.162121 | AF16: 0.040558205 | AG16: 97.146025 | AH16: 0.043125374 | AI16: 69.523546 | AJ16: 0.019523973 | AK16: 104.93707 | AL16: 0.018727736 | AM16: 109.59915 | AN16: 0.012942386 | AO16: 114.01196 | AP16: 0.030079414 | AQ16: 115.81659 | AR16: 0.04173042 | AS16: 87.189152 | AT16: 0.043545688 | AU16: 77.897779 | AV16: 0.028511893 | AW16: 74.632225 | AX16: 0.026540724 | AY16: 85.220929 | AZ16: 0.034030708 | BA16: 95.418094 | BB16: 0.04287023 | BC16: 106.49892 | BD16: 0.042188037
A17: 1985 | C17: 69.601035 | D17: 0.022707506 | E17: 74.493551 | F17: 0.035072194 | G17: 71.391821 | H17: 0.02528218 | I17: 73.241679 | J17: 0.026281028 | K17: 62.900243 | L17: 0.019585586 | M17: 81.622285 | N17: 0.057953519 | O17: 91.611211 | P17: 0.0365187 | Q17: 72.45097 | R17: 0.020862378 | S17: 104.09209 | T17: 0.047887856 | AA17: 89.109674 | AB17: -0.0083949171 | AC17: 98.012038 | AD17: -0.017914594 | AE17: 96.953493 | AF17: 0.018824429 | AG17: 99.773962 | AH17: 0.02705141 | AI17: 70.642425 | AJ17: 0.016093526 | AK17: 106.53034 | AL17: 0.015183138 | AM17: 110.50074 | AN17: 0.0082262873 | AO17: 118.87111 | AP17: 0.042619728 | AQ17: 121.50933 | AR17: 0.049153024 | AS17: 91.032775 | AT17: 0.044083721 | AU17: 80.015115 | AV17: 0.027180961 | AW17: 76.775707 | AX17: 0.028720598 | AY17: 87.191625 | AZ17: 0.023124555 | BA17: 98.025663 | BB17: 0.027327824 | BC17: 111.59587 | BD17: 0.047859164
A18: 1986 | C18: 71.731748 | D18: 0.03061323 | E18: 74.777474 | F18: 0.0038113678 | G18: 72.513614 | H18: 0.015713195 | I18: 74.19588 | J18: 0.01302811 | K18: 64.854151 | L18: 0.031063602 | M18: 79.959939 | N18: -0.020366325 | O18: 92.191137 | P18: 0.0063303005 | Q18: 74.574715 | R18: 0.029312856 | S18: 103.19629 | T18: -0.0086058552 | AA18: 84.778234 | AB18: -0.048607957 | AC18: 91.23737 | AD18: -0.069120779 | AE18: 94.560134 | AF18: -0.024685646 | AG18: 98.943802 | AH18: -0.0083204069 | AI18: 70.977672 | AJ18: 0.0047456886 | AK18: 95.783248 | AL18: -0.10088292 | AM18: 97.951032 | AN18: -0.11357125 | AO18: 106.80159 | AP18: -0.10153458 | AQ18: 109.76212 | AR18: -0.096677394 | AS18: 87.019793 | AT18: -0.044082829 | AU18: 80.695141 | AV18: 0.0084987222 | AW18: 77.753862 | AX18: 0.012740415 | AY18: 86.915685 | AZ18: -0.0031647536 | BA18: 97.272092 | BB18: -0.0076874808 | BC18: 102.23419 | BD18: -0.083889161
A19: 1987 | C19: 73.28711 | D19: 0.021683037 | E19: 75.66438 | F19: 0.011860609 | G19: 73.071973 | H19: 0.0077000452 | I19: 74.74161 | J19: 0.0073552604 | K19: 65.479984 | L19: 0.0096498507 | M19: 81.627029 | N19: 0.020849068 | O19: 92.912687 | P19: 0.0078266717 | Q19: 76.277666 | R19: 0.022835504 | S19: 102.96578 | T19: -0.0022336572 | AA19: 84.499698 | AB19: -0.0032854675 | AC19: 90.494949 | AD19: -0.0081372444 | AE19: 94.303718 | AF19: -0.0027116692 | AG19: 98.977909 | AH19: 0.00034471768 | AI19: 71.51609 | AJ19: 0.0075857344 | AK19: 93.213038 | AL19: -0.026833606 | AM19: 94.985402 | AN19: -0.030276668 | AO19: 102.57188 | AP19: -0.039603381 | AQ19: 105.45163 | AR19: -0.039271215 | AS19: 85.825422 | AT19: -0.013725273 | AU19: 81.227763 | AV19: 0.0066004204 | AW19: 78.355696 | AX19: 0.0077402457 | AY19: 87.206834 | AZ19: 0.003349783 | BA19: 97.353976 | BB19: 0.00084180659 | BC19: 98.882814 | BD19: -0.032781319
A20: 1988 | C20: 75.322287 | D20: 0.027769919 | E20: 78.41795 | F20: 0.0363919 | G20: 74.541498 | H20: 0.020110662 | I20: 76.053715 | J20: 0.017555221 | K20: 67.719293 | L20: 0.034198377 | M20: 87.436191 | N20: 0.071167135 | O20: 96.200979 | P20: 0.035391204 | Q20: 79.393545 | R20: 0.040849162 | S20: 106.23014 | T20: 0.031703259 | AA20: 85.748582 | AB20: 0.014779747 | AC20: 91.027693 | AD20: 0.0058870014 | AE20: 96.494744 | AF20: 0.023233714 | AG20: 100.41943 | AH20: 0.014564026 | AI20: 74.113653 | AJ20: 0.036321386 | AK20: 96.456283 | AL20: 0.034793892 | AM20: 98.268646 | AN20: 0.034565779 | AO20: 107.19117 | AP20: 0.045034613 | AQ20: 109.83462 | AR20: 0.041563936 | AS20: 88.883744 | AT20: 0.035634221 | AU20: 83.21749 | AV20: 0.024495645 | AW20: 80.325824 | AX20: 0.025143394 | AY20: 89.18179 | AZ20: 0.02264681 | BA20: 98.810822 | BB20: 0.014964417 | BC20: 102.83879 | BD20: 0.040006696
A21: 1989 | C21: 77.929945 | D21: 0.034620005 | E21: 80.759582 | F21: 0.029860911 | G21: 76.914208 | H21: 0.031830715 | I21: 78.453168 | J21: 0.031549444 | K21: 69.972238 | L21: 0.033268884 | M21: 89.710657 | N21: 0.026012867 | O21: 100.82004 | P21: 0.048014701 | Q21: 83.07134 | R21: 0.04632361 | S21: 111.45804 | T21: 0.049213043 | AA21: 92.502659 | AB21: 0.07876604 | AC21: 99.895512 | AD21: 0.097418912 | AE21: 103.95243 | AF21: 0.077285968 | AG21: 107.17471 | AH21: 0.067270691 | AI21: 76.644979 | AJ21: 0.034154656 | AK21: 103.05092 | AL21: 0.068369192 | AM21: 104.5299 | AN21: 0.063715703 | AO21: 116.39489 | AP21: 0.085862687 | AQ21: 118.3328 | AR21: 0.077372547 | AS21: 96.597427 | AT21: 0.086783948 | AU21: 86.702003 | AV21: 0.041872375 | AW21: 83.318358 | AX21: 0.037254952 | AY21: 94.081689 | AZ21: 0.054942821 | BA21: 105.41206 | BB21: 0.066806857 | BC21: 111.04005 | BD21: 0.079748732
A22: 1990 | C22: 81.517648 | D22: 0.046037536 | E22: 83.943328 | F22: 0.039422518 | G22: 80.949287 | H22: 0.052462078 | I22: 82.596497 | J22: 0.052812771 | K22: 73.521546 | L22: 0.050724514 | M22: 91.153834 | N22: 0.016087015 | O22: 102.70436 | P22: 0.018689887 | Q22: 87.452449 | R22: 0.052739112 | S22: 111.00787 | T22: -0.0040389173 | AA22: 90.811928 | AB22: -0.018277647 | AC22: 96.346804 | AD22: -0.035524199 | AE22: 103.3237 | AF22: -0.0060482524 | AG22: 108.3865 | AH22: 0.011306717 | AI22: 78.902275 | AJ22: 0.029451322 | AK22: 99.694468 | AL22: -0.032570821 | AM22: 100.05703 | AN22: -0.042790372 | AO22: 114.36166 | AP22: -0.017468324 | AQ22: 117.68018 | AR22: -0.0055151297 | AS22: 97.484189 | AT22: 0.0091799801 | AU22: 89.722145 | AV22: 0.034833582 | AW22: 86.7218 | AX22: 0.040848641 | AY22: 95.758981 | AZ22: 0.01782803 | BA22: 106.66935 | BB22: 0.011927352 | BC22: 110.83723 | BD22: -0.0018265516
A23: 1991 | C23: 85.925346 | D23: 0.054070477 | E23: 88.050153 | F23: 0.048923779 | G23: 85.385334 | H23: 0.054800324 | I23: 86.950838 | J23: 0.05271823 | K23: 78.299205 | L23: 0.064983116 | M23: 94.503285 | N23: 0.036745043 | O23: 104.70404 | P23: 0.01947033 | Q23: 88.65317 | R23: 0.013729986 | S23: 113.60714 | T23: 0.02341519 | AA23: 92.770057 | AB23: 0.021562467 | AC23: 97.684895 | AD23: 0.01388828 | AE23: 105.63141 | AF23: 0.022334757 | AG23: 111.18961 | AH23: 0.025862167 | AI23: 82.087269 | AJ23: 0.04036631 | AK23: 100.49791 | AL23: 0.0080590107 | AM23: 99.64621 | AN23: -0.0041058402 | AO23: 114.32417 | AP23: -0.00032789659 | AQ23: 117.75956 | AR23: 0.00067451996 | AS23: 102.6927 | AT23: 0.05342929 | AU23: 93.328136 | AV23: 0.040190653 | AW23: 90.469835 | AX23: 0.043219063 | AY23: 98.76516 | AZ23: 0.031393182 | BA23: 109.50659 | BB23: 0.026598488 | BC23: 112.40562 | BD23: 0.014150405
A24: 1992 | C24: 87.758974 | D24: 0.021339781 | E24: 89.802918 | F24: 0.019906437 | G24: 88.836794 | H24: 0.040422171 | I24: 90.287421 | J24: 0.038373212 | K24: 82.24091 | L24: 0.050341573 | M24: 92.082568 | N24: -0.025615166 | O24: 104.37521 | P24: -0.0031406342 | Q24: 86.40451 | R24: -0.025364692 | S24: 115.20362 | T24: 0.014052607 | AA24: 93.223886 | AB24: 0.0048919779 | AC24: 98.20321 | AD24: 0.0053059878 | AE24: 106.74992 | AF24: 0.010588787 | AG24: 112.59421 | AH24: 0.012632396 | AI24: 82.406207 | AJ24: 0.0038853568 | AK24: 100.52295 | AL24: 0.00024917481 | AM24: 99.844918 | AN24: 0.001994135 | AO24: 116.49718 | AP24: 0.019007438 | AQ24: 120.60024 | AR24: 0.024122704 | AS24: 102.13521 | AT24: -0.0054287663 | AU24: 95.448024 | AV24: 0.022714341 | AW24: 92.940951 | AX24: 0.027314252 | AY24: 99.742339 | AZ24: 0.0098939675 | BA24: 110.94367 | BB24: 0.013123239 | BC24: 114.15549 | BD24: 0.015567434
... A56: 2024 | C56: 105.72469 | D56: 0.013558932 | E56: 110.00901 | F56: 0.018770554 | G56: 107.94822 | H56: 0.011626567 | I56: 107.0754 | J56: 0.010173944 | K56: 111.84114 | L56: 0.018069619 | M56: 114.82509 | N56: 0.035703043 | O56: 107.86292 | P56: 0.0040802911 | Q56: 115.05763 | R56: 0.0085086091 | S56: 104.614 | T56: 0.0019323377 | AA56: 112.24445 | AB56: 0.013780438 | AC56: 114.39756 | AD56: 0.018820671 | AE56: 101.52453 | AF56: -0.02299307 | AG56: 93.098139 | AH56: -0.031058838 | AI56: 107.149 | AJ56: -2.6192742e-05 | AK56: 121.12364 | AL56: 0.02141727 | AM56: 122.49714 | AN56: 0.022709417 | AO56: 105.45059 | AP56: -0.03226098 | AQ56: 105.0053 | AR56: -0.039483404 | AS56: 118.02505 | AT56: 0.019145146 | AU56: 105.72804 | AV56: -0.0030204827 | AW56: 107.93192 | AX56: 0.0094600123 | AY56: 102.2441 | AZ56: -0.021144406 | BA56: 100.03532 | BB56: -0.030918005 | BC56: 110.46714 | BD56: -0.0140619

Sheet gc_y
A1: =IF(INDIRECT("beschriftung!"&ADDRESS(beschriftung!$C$1*12+ROW(beschriftung!$A1)-1,COLUMN(beschriftung!B$1)))="","",INDIRECT("beschriftung!"&ADDRESS(beschriftung!$C$1*12+ROW(beschriftung!$A1)-1,COLUMN(beschriftung!B$1)))) -> ESA 2010, Annual aggregates of Gross Domestic Product, expenditure approach (SFSO, SECO), seasonally, calendar and sport event adjusted data
A2: =IF(INDIRECT("beschriftung!"&ADDRESS(beschriftung!$C$1*12+ROW(beschriftung!$A6)-1,COLUMN(beschriftung!B$1)))="","",INDIRECT("beschriftung!"&ADDRESS(beschriftung!$C$1*12+ROW(beschriftung!$A6)-1,COLUMN(beschriftung!B$1)))) -> Contributions to real GDP-growth
A3: =IF(INDIRECT("beschriftung!"&ADDRESS(beschriftung!$C$1*12+ROW(beschriftung!$A5)-1,COLUMN(beschriftung!B$1)))="","",INDIRECT("beschriftung!"&ADDRESS(beschriftung!$C$1*12+ROW(beschriftung!$A5)-1,COLUMN(beschriftung!B$1))))
C4: =IF(INDIRECT("beschriftung!"&ADDRESS(beschriftung!$C$1*12+ROW(beschriftung!$A5)-1,COLUMN(beschriftung!C$1)))="","",INDIRECT("beschriftung!"&ADDRESS(beschriftung!$C$1*12+ROW(beschriftung!$A5)-1,COLUMN(beschriftung!C$1)))) -> Gross domestic product
E5: =IF(INDIRECT("beschriftung!"&ADDRESS(beschriftung!$C$1*12+ROW(beschriftung!$A6)-1,COLUMN(beschriftung!E$1)))="","",INDIRECT("beschriftung!"&ADDRESS(beschriftung!$C$1*12+ROW(beschriftung!$A6)-1,COLUMN(beschriftung!E$1)))) -> Internal demand | Y5: =IF(INDIRECT("beschriftung!"&ADDRESS(beschriftung!$C$1*12+ROW(beschriftung!$A6)-1,COLUMN(beschriftung!Y$1)))="","",INDIRECT("beschriftung!"&ADDRESS(beschriftung!$C$1*12+ROW(beschriftung!$A6)-1,COLUMN(beschriftung!Y$1)))) -> Trade balance (goods and services) | AU5: =IF(INDIRECT("beschriftung!"&ADDRESS(beschriftung!$C$1*12+ROW(beschriftung!$A6)-1,COLUMN(beschriftung!AU$1)))="","",INDIRECT("beschriftung!"&ADDRESS(beschriftung!$C$1*12+ROW(beschriftung!$A6)-1,COLUMN(beschriftung!AU$1)))) -> Global demand excluding inventories change, stat. discrepancies and valuables
G6: =IF(INDIRECT("beschriftung!"&ADDRESS(beschriftung!$C$1*12+ROW(beschriftung!$A7)-1,COLUMN(beschriftung!G$1)))="","",INDIRECT("beschriftung!"&ADDRESS(beschriftung!$C$1*12+ROW(beschriftung!$A7)-1,COLUMN(beschriftung!G$1)))) -> Final consumption expenditure | M6: =IF(INDIRECT("beschriftung!"&ADDRESS(beschriftung!$C$1*12+ROW(beschriftung!$A7)-1,COLUMN(beschriftung!M$1)))="","",INDIRECT("beschriftung!"&ADDRESS(beschriftung!$C$1*12+ROW(beschriftung!$A7)-1,COLUMN(beschriftung!M$1)))) -> Gross capital formation | AA6: =IF(INDIRECT("beschriftung!"&ADDRESS(beschriftung!$C$1*12+ROW(beschriftung!$A7)-1,COLUMN(beschriftung!AA$1)))="","",INDIRECT("beschriftung!"&ADDRESS(beschriftung!$C$1*12+ROW(beschriftung!$A7)-1,COLUMN(beschriftung!AA$1)))) -> Exports of goods and services | AK6: =IF(INDIRECT("beschriftung!"&ADDRESS(beschriftung!$C$1*12+ROW(beschriftung!$A7)-1,COLUMN(beschriftung!AK$1)))="","",INDIRECT("beschriftung!"&ADDRESS(beschriftung!$C$1*12+ROW(beschriftung!$A7)-1,COLUMN(beschriftung!AK$1)))) -> Imports of goods and services | AW6: =IF(INDIRECT("beschriftung!"&ADDRESS(beschriftung!$C$1*12+ROW(beschriftung!$A7)-1,COLUMN(beschriftung!AW$1)))="","",INDIRECT("beschriftung!"&ADDRESS(beschriftung!$C$1*12+ROW(beschriftung!$A7)-1,COLUMN(beschriftung!AW$1)))) -> Final domestic demand | AY6: =IF(INDIRECT("beschriftung!"&ADDRESS(beschriftung!$C$1*12+ROW(beschriftung!$A7)-1,COLUMN(beschriftung!AY$1)))="","",INDIRECT("beschriftung!"&ADDRESS(beschriftung!$C$1*12+ROW(beschriftung!$A7)-1,COLUMN(beschriftung!AY$1)))) -> Exports of goods and services (excluding valuables) | BC6: =IF(INDIRECT("beschriftung!"&ADDRESS(beschriftung!$C$1*12+ROW(beschriftung!$A7)-1,COLUMN(beschriftung!BC$1)))="","",INDIRECT("beschriftung!"&ADDRESS(beschriftung!$C$1*12+ROW(beschriftung!$A7)-1,COLUMN(beschriftung!BC$1)))) -> Imports of goods and services (excluding valuables)
I7: =IF(INDIRECT("beschriftung!"&ADDRESS(beschriftung!$C$1*12+ROW(beschriftung!$A8)-1,COLUMN(beschriftung!I$1)))="","",INDIRECT("beschriftung!"&ADDRESS(beschriftung!$C$1*12+ROW(beschriftung!$A8)-1,COLUMN(beschriftung!I$1)))) -> Households and NPISH | K7: =IF(INDIRECT("beschriftung!"&ADDRESS(beschriftung!$C$1*12+ROW(beschriftung!$A8)-1,COLUMN(beschriftung!K$1)))="","",INDIRECT("beschriftung!"&ADDRESS(beschriftung!$C$1*12+ROW(beschriftung!$A8)-1,COLUMN(beschriftung!K$1)))) -> General government | O7: =IF(INDIRECT("beschriftung!"&ADDRESS(beschriftung!$C$1*12+ROW(beschriftung!$A8)-1,COLUMN(beschriftung!O$1)))="","",INDIRECT("beschriftung!"&ADDRESS(beschriftung!$C$1*12+ROW(beschriftung!$A8)-1,COLUMN(beschriftung!O$1)))) -> Gross fixed capital formation | U7: =IF(INDIRECT("beschriftung!"&ADDRESS(beschriftung!$C$1*12+ROW(beschriftung!$A8)-1,COLUMN(beschriftung!U$1)))="","",INDIRECT("beschriftung!"&ADDRESS(beschriftung!$C$1*12+ROW(beschriftung!$A8)-1,COLUMN(beschriftung!U$1)))) -> Changes in inventories and statistical discrepancies | W7: =IF(INDIRECT("beschriftung!"&ADDRESS(beschriftung!$C$1*12+ROW(beschriftung!$A8)-1,COLUMN(beschriftung!W$1)))="","",INDIRECT("beschriftung!"&ADDRESS(beschriftung!$C$1*12+ROW(beschriftung!$A8)-1,COLUMN(beschriftung!W$1)))) -> Acquisitions less disposals of valuables | AC7: =IF(INDIRECT("beschriftung!"&ADDRESS(beschriftung!$C$1*12+ROW(beschriftung!$A8)-1,COLUMN(beschriftung!AC$1)))="","",INDIRECT("beschriftung!"&ADDRESS(beschriftung!$C$1*12+ROW(beschriftung!$A8)-1,COLUMN(beschriftung!AC$1)))) -> Exports (exp.) of goods | AI7: =IF(INDIRECT("beschriftung!"&ADDRESS(beschriftung!$C$1*12+ROW(beschriftung!$A8)-1,COLUMN(beschriftung!AI$1)))="","",INDIRECT("beschriftung!"&ADDRESS(beschriftung!$C$1*12+ROW(beschriftung!$A8)-1,COLUMN(beschriftung!AI$1)))) -> Exports of services | AM7: =IF(INDIRECT("beschriftung!"&ADDRESS(beschriftung!$C$1*12+ROW(beschriftung!$A8)-1,COLUMN(beschriftung!AM$1)))="","",INDIRECT("beschriftung!"&ADDRESS(beschriftung!$C$1*12+ROW(beschriftung!$A8)-1,COLUMN(beschriftung!AM$1)))) -> Imports (imp.) of goods | AS7: =IF(INDIRECT("beschriftung!"&ADDRESS(beschriftung!$C$1*12+ROW(beschriftung!$A8)-1,COLUMN(beschriftung!AS$1)))="","",INDIRECT("beschriftung!"&ADDRESS(beschriftung!$C$1*12+ROW(beschriftung!$A8)-1,COLUMN(beschriftung!AS$1)))) -> Imports of services | BA7: =IF(INDIRECT("beschriftung!"&ADDRESS(beschriftung!$C$1*12+ROW(beschriftung!$A8)-1,COLUMN(beschriftung!BA$1)))="","",INDIRECT("beschriftung!"&ADDRESS(beschriftung!$C$1*12+ROW(beschriftung!$A8)-1,COLUMN(beschriftung!BA$1)))) -> thereof exports of goods excluding valuables
Q8: =IF(INDIRECT("beschriftung!"&ADDRESS(beschriftung!$C$1*12+ROW(beschriftung!$A9)-1,COLUMN(beschriftung!Q$1)))="","",INDIRECT("beschriftung!"&ADDRESS(beschriftung!$C$1*12+ROW(beschriftung!$A9)-1,COLUMN(beschriftung!Q$1)))) -> Construction | S8: =IF(INDIRECT("beschriftung!"&ADDRESS(beschriftung!$C$1*12+ROW(beschriftung!$A9)-1,COLUMN(beschriftung!S$1)))="","",INDIRECT("beschriftung!"&ADDRESS(beschriftung!$C$1*12+ROW(beschriftung!$A9)-1,COLUMN(beschriftung!S$1)))) -> Fixed assets and software | AE8: =IF(INDIRECT("beschriftung!"&ADDRESS(beschriftung!$C$1*12+ROW(beschriftung!$A9)-1,COLUMN(beschriftung!AE$1)))="","",INDIRECT("beschriftung!"&ADDRESS(beschriftung!$C$1*12+ROW(beschriftung!$A9)-1,COLUMN(beschriftung!AE$1)))) -> thereof exp. of goods excluding non-monetary gold | AG8: =IF(INDIRECT("beschriftung!"&ADDRESS(beschriftung!$C$1*12+ROW(beschriftung!$A9)-1,COLUMN(beschriftung!AG$1)))="","",INDIRECT("beschriftung!"&ADDRESS(beschriftung!$C$1*12+ROW(beschriftung!$A9)-1,COLUMN(beschriftung!AG$1)))) -> thereof exp. of goods excluding valuables and merchanting | AO8: =IF(INDIRECT("beschriftung!"&ADDRESS(beschriftung!$C$1*12+ROW(beschriftung!$A9)-1,COLUMN(beschriftung!AO$1)))="","",INDIRECT("beschriftung!"&ADDRESS(beschriftung!$C$1*12+ROW(beschriftung!$A9)-1,COLUMN(beschriftung!AO$1)))) -> thereof imp. of goods excluding non-monetary gold | AQ8: =IF(INDIRECT("beschriftung!"&ADDRESS(beschriftung!$C$1*12+ROW(beschriftung!$A9)-1,COLUMN(beschriftung!AQ$1)))="","",INDIRECT("beschriftung!"&ADDRESS(beschriftung!$C$1*12+ROW(beschriftung!$A9)-1,COLUMN(beschriftung!AQ$1)))) -> thereof imp. of goods excluding valuables
C11: B.1*b | E11: P.3+P.5 | G11: P.3 | I11: S.14+S15 | K11: S.13 | M11: P.5 | O11: P.51 | Q11: P.5111c | S11: P.5111be | U11: P.52 | W11: P.53 | AA11: P.6 | AC11: P.61 | AI11: P.62 | AK11: P.7 | AM11: P.71 | AS11: P.72 | AW11: P.3+P.51
A12: 1980
A13: 1981 | E13: -0.017680681 | G13: 0.0078523668 | I13: 0.00570058 | K13: 0.0021517867 | M13: -0.025533048 | O13: 0.0037565455 | Q13: 0.0046126845 | S13: -0.00085613904 | U13: -0.0098657005 | W13: -0.019423893 | Y13: 0.033993292 | AA13: 0.069845435 | AC13: 0.061149129 | AE13: 0.022192045 | AG13: 0.0086909399 | AI13: 0.0086963066 | AK13: -0.035852143 | AM13: -0.030945651 | AO13: 0.001678744 | AQ13: 0.0016041079 | AS13: -0.0049064926 | AU13: 0.029480696 | AW13: 0.011608912 | AY13: 0.017871784 | BA13: 0.0091754776 | BC13: -0.0033023848
A14: 1982 | E14: 0.006347413 | G14: 0.0024554187 | I14: 0.0018450819 | K14: 0.00061033684 | M14: 0.0038919943 | O14: -0.012821813 | Q14: -0.0043484369 | S14: -0.0084733759 | U14: -0.00066168294 | W14: 0.01737549 | Y14: -0.019749847 | AA14: -0.0094336595 | AC14: -0.011327555 | AE14: -0.0012222337 | AG14: -0.0077306153 | AI14: 0.0018938959 | AK14: -0.010316188 | AM14: -0.0051870096 | AO14: 0.0026685775 | AQ14: 0.0092466443 | AS14: -0.0051291781 | AU14: -0.016858217 | AW14: -0.010366394 | AY14: -0.0064918234 | BA14: -0.0083857192 | BC14: 0.0041174662
A15: 1983 | E15: 0.023400542 | G15: 0.0098607622 | I15: 0.0072943835 | K15: 0.0025663787 | M15: 0.01353978 | O15: 0.010132697 | Q15: 0.0064619614 | S15: 0.0036707352 | U15: -0.0079845933 | W15: 0.011391677 | Y15: -0.017353824 | AA15: -0.012113539 | AC15: -0.018269199 | AE15: 0.0025172876 | AG15: 0.0029511235 | AI15: 0.0061556601 | AK15: -0.0052402848 | AM15: -0.0027823988 | AO15: -0.016047126 | AQ15: -0.012462667 | AS15: -0.002457886 | AU15: 0.028951864 | AW15: 0.019993459 | AY15: 0.0089584053 | BA15: 0.0028027452 | BC15: -0.014920553
A16: 1984 | E16: -0.012151674 | G16: 0.011204118 | I16: 0.0096155276 | K16: 0.0015885901 | M16: -0.023355791 | O16: 0.013085335 | Q16: 0.0075092355 | S16: 0.0055760996 | U16: 0.0051251175 | W16: -0.041566244 | Y16: 0.042824855 | AA16: 0.067857433 | AC16: 0.058207555 | AE16: 0.019698016 | AG16: 0.013110103 | AI16: 0.0096498772 | AK16: -0.025032578 | AM16: -0.021374932 | AO16: -0.025605085 | AQ16: -0.018497257 | AS16: -0.0036576457 | AU16: 0.047702966 | AW16: 0.024289453 | AY16: 0.023413514 | BA16: 0.013763636 | BC16: -0.022154903
A17: 1985 | E17: 0.026428832 | G17: 0.017495768 | I17: 0.012417886 | K17: 0.0050778813 | M17: 0.0089330639 | O17: 0.010764171 | Q17: 0.0015172258 | S17: 0.0092469455 | U17: -0.003694729 | W17: 0.0018636216 | Y17: 0.010699867 | AA17: 0.037866492 | AC17: 0.026315656 | AE17: 0.019005265 | AG17: 0.017810995 | AI17: 0.011550835 | AK17: -0.027166624 | AM17: -0.021733328 | AO17: -0.01013524 | AQ17: -0.012093318 | AS17: -0.0054332963 | AU17: 0.058350043 | AW17: 0.028259939 | AY17: 0.030090104 | BA17: 0.018539268 | BC17: -0.017526615
A18: 1986 | E18: 0.063020104 | G18: 0.019241011 | I18: 0.016022711 | K18: 0.0032182997 | M18: 0.043779093 | O18: 0.021087523 | Q18: 0.0021526894 | S18: 0.018934833 | U18: 0.00036409274 | W18: 0.022327478 | Y18: -0.044657278 | AA18: 0.0068681821 | AC18: 0.0093251474 | AE18: 0.0062304973 | AG18: 0.0044726234 | AI18: -0.0024569653 | AK18: -0.05152546 | AM18: -0.04977138 | AO18: -0.025883528 | AQ18: -0.021741418 | AS18: -0.0017540797 | AU18: 0.041494231 | AW18: 0.040328533 | AY18: 0.0011656979 | BA18: 0.0036226632 | BC18: -0.023495498
A19: 1987 | E19: 0.020508307 | G19: 0.019490563 | I19: 0.017145691 | K19: 0.0023448726 | M19: 0.0010177439 | O19: 0.012874965 | Q19: 0.0046746996 | S19: 0.0082002658 | U19: -0.0026484485 | W19: -0.0092087731 | Y19: -0.0050853462 | AA19: -0.01079987 | AC19: -0.014190202 | AE19: 0.0024333927 | AG19: -0.00047262161 | AI19: 0.0033903317 | AK19: 0.0057145242 | AM19: 0.010515586 | AO19: -0.015897641 | AQ19: -0.013661456 | AS19: -0.0048010622 | AU19: 0.036533928 | AW19: 0.032365529 | AY19: 0.0041683991 | BA19: 0.00077806747 | BC19: -0.018462518
A20: 1988 | E20: 0.024462435 | G20: 0.016997536 | I20: 0.012376035 | K20: 0.0046215018 | M20: 0.0074648983 | O20: 0.025759361 | Q20: 0.0091222039 | S20: 0.016637157 | U20: -0.0075822335 | W20: -0.010712229 | Y20: 0.0083665851 | AA20: 0.03159355 | AC20: 0.030492811 | AE20: 0.017197257 | AG20: 0.015186069 | AI20: 0.0011007394 | AK20: -0.023226965 | AM20: -0.017199866 | AO20: -0.012147486 | AQ20: -0.012516136 | AS20: -0.0060270995 | AU20: 0.058954489 | AW20: 0.042756897 | AY20: 0.016197592 | BA20: 0.015096853 | BC20: -0.018543236
A21: 1989 | E21: 0.048475292 | G21: 0.023178101 | I21: 0.014141042 | K21: 0.0090370584 | M21: 0.025297191 | O21: 0.015435836 | Q21: 0.009495983 | S21: 0.0059398535 | U21: 0.004286273 | W21: 0.0055750817 | Y21: -0.0041651084 | AA21: 0.025146992 | AC21: 0.019239539 | AE21: 0.014407427 | AG21: 0.010602942 | AI21: 0.0059074525 | AK21: -0.0293121 | AM21: -0.028317912 | AO21: -0.016940961 | AQ21: -0.014978911 | AS21: -0.00099418869 | AU21: 0.05599701 | AW21: 0.038613937 | AY21: 0.017383073 | BA21: 0.01147562 | BC21: -0.015973099
A22: 1990 | E22: 0.053783293 | G22: 0.013598355 | I22: 0.0086142804 | K22: 0.0049840743 | M22: 0.040184938 | O22: 0.015029774 | Q22: 0.0014063189 | S22: 0.013623455 | U22: 0.013357474 | W22: 0.011797691 | Y22: -0.016657015 | AA22: 0.0088208638 | AC22: 0.014195745 | AE22: 0.013707377 | AG22: 0.0099303032 | AI22: -0.0053748814 | AK22: -0.025477879 | AM22: -0.024201806 | AO22: -0.011270044 | AQ22: -0.0081811079 | AS22: -0.0012760732 | AU22: 0.033225985 | AW22: 0.028628129 | AY22: 0.0045978567 | BA22: 0.009972738 | BC22: -0.0094571811
A23: 1991 | E23: -0.017101662 | G23: 0.013367953 | I23: 0.009735938 | K23: 0.003632015 | M23: -0.030469615 | O23: -0.0062044463 | Q23: -0.0046260264 | S23: -0.0015784199 | U23: -0.021094781 | W23: -0.0031703882 | Y23: 0.0078109133 | AA23: -0.0064147925 | AC23: -0.0093099227 | AE23: -0.0059826004 | AG23: -0.0017340539 | AI23: 0.0028951302 | AK23: 0.014225706 | AM23: 0.013813165 | AO23: 0.0049252303 | AQ23: 0.0033762209 | AS23: 0.00041254112 | AU23: 0.0080152699 | AW23: 0.0071635067 | AY23: 0.00085176317 | BA23: -0.0020433671 | BC23: 0.003788762
A24: 1992 | E24: -0.011547593 | G24: 0.0029053136 | I24: 0.0025425759 | K24: 0.00036273769 | M24: -0.014452906 | O24: -0.026097816 | Q24: -0.0015645776 | S24: -0.024533239 | U24: 0.0078953389 | W24: 0.0037495713 | Y24: 0.010098162 | AA24: 0.014938222 | AC24: 0.012074604 | AE24: 0.0075763634 | AG24: 0.0081337604 | AI24: 0.0028636179 | AK24: -0.0048400598 | AM24: 0.0017173847 | AO24: 0.011617023 | AQ24: 0.010571383 | AS24: -0.0065574445 | AU24: -0.013358708 | AW24: -0.023192503 | AY24: 0.0098337948 | BA24: 0.006970177 | BC24: 0.0040139384
... A56: 2024 | E56: 0.018813632 | G56: 0.0098386186 | I56: 0.0092083325 | K56: 0.00063028608 | M56: 0.0089750136 | O56: -0.0019282569 | Q56: 0.001826089 | S56: -0.0037543458 | U56: 0.015460452 | W56: -0.0045571817 | Y56: -0.0092198917 | AA56: -0.0092915811 | AC56: -0.015080203 | AE56: -0.0025985675 | AG56: 0.022120875 | AI56: 0.0057886217 | AK56: 7.1689349e-05 | AM56: 0.011752687 | AO56: -0.0060476704 | AQ56: -0.0079434969 | AS56: -0.011680997 | AU56: 0.013757783 | AW56: 0.0079103617 | AY56: 0.005847421 | BA56: 5.8799296e-05 | BC56: -0.019624494

Sheet beschriftung
A1: deutsch | C1: 4
A2: français
A3: italiano
A4: english
A11: deutsch
A12: ESVG 2010, Quartalsaggregate des Bruttoinlandprodukts, Verwendungsansatz, saison-, kalender- und Sportevent-bereinigte Daten. Hintergrundinformationen zur Sportevent-Bereinigung sind in den Konjunkturtendenzen von Herbst 2022 sowie in der technischen Notiz vom 05.09.2022 unter www.seco.admin.ch zu finden. | B12: ESVG 2010, Jahresaggregate des Bruttoinlandproduktes, Verwendungsansatz (BFS, SECO), saison-, kalender- und Sportevent-bereinigte Daten
A13: In Mio. Franken, zu laufenden Preisen und Veränderungsraten in % gegenüber dem Vorquartal | B13: In Mio. Franken, zu laufenden Preisen und Veränderungsraten in % gegenüber dem Vorjahr
A14: In Mio. Franken, reale nicht additive Volumen (annual overlap, Referenzjahr 2015) und Veränderungsraten in % gegenüber dem Vorquartal | B14: In Mio. Franken, reale nicht additive Volumen (annual overlap, Referenzjahr 2015) und Veränderungsraten in % gegenüber dem Vorjahr
A15: Implizite Preisindizes und Veränderungsraten in % gegenüber dem Vorquartal | B15: Implizite Preisindizes und Veränderungsraten in % gegenüber dem Vorjahr
C16: Bruttoinlandprodukt
A17: Reale Wachstumsbeiträge zum Bruttoinlandprodukt | B17: Reale Wachstumsbeiträge zum Bruttoinlandprodukt | E17: Inlandnachfrage | Y17: Handelsbilanz (Waren und Dienstleistungen) | AU17: Gesamtnachfrage ohne Vorratsveränderung, statistische Abw. u. Wertsachen
G18: Konsumausgaben | M18: Bruttoinvestitionen | AA18: Waren- und Dienstleistungsexporte | AK18: Waren- und Dienstleistungsimporte | AW18: Inländische Endnachfrage | AY18: Waren- und Dienstleistungs- exporte (ohne Wertsachen) | BC18: Waren- und Dienstleistungs- importe (ohne Wertsachen)
I19: Private Haushalte und POoE | K19: Staat | O19: Bruttoanlageinvestitionen | U19: Vorratsveränderung- en und statistische Abweichungen | W19: Nettozugang an Wertsachen | AA19: NA | AC19: Warenexporte | AI19: Dienstleistungs- exporte | AM19: Warenimporte | AS19: Dienstleistungs- importe | BA19: davon Warenexporte ohne Wertsachen
Q20: Bau | S20: Ausrüstungen | AE20: davon Warenexporte ohne Nichtwährungsgold | AG20: davon Warenexp. ohne Wertsachen u. Transithandel | AK20: NA | AO20: davon Warenimporte ohne Nichtwährungsgold | AQ20: davon Warenimporte ohne Wertsachen
A21: Jahr | B21: Quartal
A23: français
A24: SEC 2010, PIB trimestriel et ses composantes, approche par la dépense, données corrigées des effets saisonniers, calendaires ainsi que des effets liés aux grands événements sportifs. Pour plus d’informations concernant la correction des effets des événements sportifs, voir les tendances conjoncturelles de l'automne 2022 ainsi que la note technique du 5 septembre 2022 disponible sous www.seco.admin.ch. | B24: SEC 2010, PIB annuel et ses composantes, approche par la dépense (OFS, SECO), données corrigées des effets saisonniers, calendaires ainsi que des effets liés aux grands événements sportifs
A25: En mio. de francs, aux prix courants, variations en % par rapport au trimestre précédent | B25: En mio. de francs, aux prix courants, variations en % par rapport de l'année précédente
A26: En mio. de francs, aux prix de l'année précédente - séries chaînées ("annual overlap"), année de référence 2015, volumes non-additifs, variations en % par rapport au trimestre précédent | B26: En mio. de francs, aux prix de l'année précédente - séries chaînées ("annual overlap"), année de référence 2015, volumes non-additifs, variations en % par rapport de l'année précédente
A27: Indices des prix, variations en % par rapport au trimestre précédent | B27: Indices des prix, variations en % par rapport de l'année précédente
C28: Produit intérieur brut
A29: contributions à la croissance réelle du PIB | B29: contributions à la croissance réelle du PIB | E29: Demande intérieure | Y29: Balance commerciale (biens et services) | AU29: Demande globale sans variations des stocks, diff. statistique et objets de valeur
G30: Dépenses de consommation finale | M30: Formation brute de capital | AA30: Exportations de biens et de services | AK30: Importations de biens et de services | AM30: dans le reste du monde | AW30: Demande intérieure finale | AY30: Exportations de biens et de services (sans objets de valeur) | BC30: Importations de biens et de services (sans objets de valeur)
I31: Ménages et ISBLSM | K31: Administrations publiques | O31: Formation brute de capital fixe | U31: Variation des stocks et divergence statistique | W31: Acquisitions moins cessions d'objets de valeur | AA31: NA | AC31: Exportations (exp.) de biens | AI31: Exportations de services | AM31: Importations (imp.) de biens | AS31: Importations de services | BA31: dont exportations de biens sans objets de valeur
Q32: Construction | S32: Biens d'équipement | AE32: dont exp. de biens sans or non monétaire | AG32: dont exp. de biens sans objets de valeur et commerce de transit | AK32: NA | AO32: dont imp. de biens sans or non monétaire | AQ32: dont imp. de biens sans objets de valeur
A33: Année | B33: Trimestre
A35: italiano
A36: SEC 2010, Prodotto Interno Lordo e aggregati trimestrali, ottica della spesa, dati depurati dagli effetti stagionali e di calendario così come dagli effetti legati ai grandi eventi sportivi. Maggiori informazioni sulla correzione per gli effetti degli eventi sportivi sono disponibili nelle edizioni dall'autumno 2022 del trimestrale “tendences conjoncturelles” (disponibile in tedesco e in francese) così come nella nota tecnica del 5 settembre 2022 disponibile al sito www.seco.admin.ch | B36: SEC 2010, Prodotto Interno Lordo e aggregati annuali, ottica della spesa (UST, SECO), dati depurati dagli effetti stagionali e di calendario così come dagli effetti legati ai grandi eventi sportivi
A37: In milioni di franchi, a prezzi correnti, variazione in % rispetto all trimestre precedente | B37: In milioni di franchi, a prezzi correnti, variazione in % rispetto all'anno precedente
A38: In milioni di franchi, ai prezzi dell'anno precedente, indici a catena, anno di referenza 2015, variazione in % rispetto all trimestre precedente | B38: In milioni di franchi, ai prezzi dell'anno precedente, indici a catena, anno di referenza 2015, variazione in % rispetto all'anno precedente
A39: Indici dei prezzi, variazione in % rispetto all trimestre precedente | B39: Indici dei prezzi, variazione rispetto all'anno precedente in %
C40: Prodotto interno lordo
A41: Contributi alla crescita reale del PIL | B41: Contributi alla crescita reale del PIL | E41: Domanda interna | Y41: Bilancia commerciale (beni e servizi) | AU41: Domanda globale senza variaz. scorte, divergenze statistiche e ogg. di valore
G42: Spesa per consumi finali | M42: Investimenti lordi | AA42: Esportazioni di beni e servizi | AK42: Importazioni di beni e servizi | AW42: Domanda interna finale | AY42: Esportazioni di beni e servizi (senza oggetti di valore) | BC42: Importazioni di beni e servizi (senza oggetti di valore)
I43: Economie domestiche e ISLED | K43: Amministrazioni pubbliche | O43: Investimenti fissi lordi | U43: Variazione delle scorte e divergenze statistiche | W43: Acquisizioni meno cessioni di oggetti di valore | AA43: NA | AC43: Esportazioni (esp.) di beni | AI43: Esportazioni di servizi | AM43: Importazioni (imp.) di beni | AS43: Importazioni di servizi | BA43: di cui esportazioni di beni senza oggetti di valore
Q44: Costruzione | S44: Beni di equipaggiamento | AE44: di cui esp. di beni senza oro non monetario | AG44: di cui esp. di beni senza oggetti di valore e commercio di transito | AK44: NA | AO44: di cui imp. di beni senza oro non monetario | AQ44: di cui imp. di beni senza oggetti di valore
A45: Anno | B45: Trimestre
A47: english
A48: ESA 2010, Quarterly aggregates of Gross Domestic Product, expenditure approach, seasonally, calendar and sport event adjusted data. Background information on sport event adjustment can be found in the publication “Konjunkturtendenzen” (“Economic Trends”) from autumn 2022 and in the technical note from 5 September 2022 on the website www.seco.admin.ch. | B48: ESA 2010, Annual aggregates of Gross Domestic Product, expenditure approach (SFSO, SECO), seasonally, calendar and sport event adjusted data
A49: In Mio. Swiss Francs, at current prices, percentage change to previous quarter | B49: In Mio. Swiss Francs, at current prices, percentage change to previous year
A50: In Mio. Swiss Francs, at prices of the preceding year, chained values ("annual overlap"), reference year 2015, percentage change to previous quarter | B50: In Mio. Swiss Francs, at prices of the preceding year, chained values ("annual overlap"), reference year 2015, percentage change to previous year
A51: Implicit chain price indexes, percentage change to previous quarter | B51: Implicit chain price indexes, year-on-year growth rates
C52: Gross domestic product
A53: Contributions to real GDP-growth | B53: Contributions to real GDP-growth | E53: Internal demand | Y53: Trade balance (goods and services) | AU53: Global demand excluding inventories change, stat. discrepancies and valuables
G54: Final consumption expenditure | M54: Gross capital formation | AA54: Exports of goods and services | AK54: Imports of goods and services | AW54: Final domestic demand | AY54: Exports of goods and services (excluding valuables) | BC54: Imports of goods and services (excluding valuables)
I55: Households and NPISH | K55: General government | O55: Gross fixed capital formation | U55: Changes in inventories and statistical discrepancies | W55: Acquisitions less disposals of valuables | AA55: NA | AC55: Exports (exp.) of goods | AI55: Exports of services | AM55: Imports (imp.) of goods | AS55: Imports of services | BA55: thereof exports of goods excluding valuables
Q56: Construction | S56: Fixed assets and software | AE56: thereof exp. of goods excluding non-monetary gold | AG56: thereof exp. of goods excluding valuables and merchanting | AK56: NA | AO56: thereof imp. of goods excluding non-monetary gold | AQ56: thereof imp. of goods excluding valuables
A57: Year | B57: Quarter
